{
  "variables": {},
  "activations": [
    {
      "id": "$setup_constants",
      "execute": "$setup_constants",
      "after": "0",
      "priority": 0,
      "additionalGuards": null,
      "activationKind": null,
      "fixedVariables": null,
      "probabilisticVariables": null,
      "activating": null,
      "activatingOnlyWhenExecuted": true,
      "updating": null,
      "withPredicate": null
    },
    {
      "id": "$initialise_machine",
      "execute": "$initialise_machine",
      "after": "0",
      "priority": 0,
      "additionalGuards": null,
      "activationKind": null,
      "fixedVariables": {
        "Crash": "FALSE",
        "PresentVehicles": "{EgoVehicle,Vehicles2,Vehicles3,Vehicles4,Vehicles5}",
        "VehiclesAy": "{(EgoVehicle↦0.0),(Vehicles2↦0.0),(Vehicles3↦0.0),(Vehicles4↦0.0),(Vehicles5↦0.0)}",
        "Reward": "0.0",
        "VehiclesAx": "{(EgoVehicle↦0.0),(Vehicles2↦0.0),(Vehicles3↦0.0),(Vehicles4↦0.0),(Vehicles5↦0.0)}",
        "VehiclesVx": "{(EgoVehicle↦25.0),(Vehicles2↦-3.0452218651771545),(Vehicles3↦-3.512454628944397),(Vehicles4↦-3.6716440320014954),(Vehicles5↦-3.3735641837120056)}",
        "VehiclesY": "{(EgoVehicle↦4.0000001192092896),(Vehicles2↦0.0),(Vehicles3↦0.0),(Vehicles4↦-4.0000001192092896),(Vehicles5↦0.0)}",
        "VehiclesVy": "{(EgoVehicle↦0.0),(Vehicles2↦0.0),(Vehicles3↦0.0),(Vehicles4↦0.0),(Vehicles5↦0.0)}",
        "VehiclesX": "{(EgoVehicle↦154.94905710220337),(Vehicles2↦25.466665625572205),(Vehicles3↦47.88259267807007),(Vehicles4↦70.99917531013489),(Vehicles5↦96.02700471878052)}"
      },
      "probabilisticVariables": null,
      "activating": [
        "LANE_RIGHT_2"
      ],
      "activatingOnlyWhenExecuted": true,
      "updating": null,
      "withPredicate": null
    },
    {
      "id": "LANE_RIGHT_2",
      "execute": "LANE_RIGHT",
      "after": "1000",
      "priority": 0,
      "additionalGuards": null,
      "activationKind": null,
      "fixedVariables": {
        "Crash": "FALSE",
        "PresentVehicles": "{EgoVehicle,Vehicles2,Vehicles3,Vehicles4,Vehicles5}",
        "VehiclesAy": "{(EgoVehicle↦1.0796338319778442),(Vehicles2↦-7.4822187423706055),(Vehicles3↦-1.0796338319778442),(Vehicles4↦-1.0796338319778442),(Vehicles5↦-1.0796338319778442)}",
        "Reward": "0.8660447183419508",
        "VehiclesAx": "{(EgoVehicle↦-0.023322105407714844),(Vehicles2↦-6.529704034328461),(Vehicles3↦-1.7031103372573853),(Vehicles4↦-1.2044820189476013),(Vehicles5↦-1.721736490726471)}",
        "VehiclesVx": "{(EgoVehicle↦24.976677894592285),(Vehicles2↦-9.574925899505615),(Vehicles3↦-5.215564966201782),(Vehicles4↦-4.876126050949097),(Vehicles5↦-5.095300674438477)}",
        "VehiclesY": "{(EgoVehicle↦7.6599647998809814),(Vehicles2↦-4.644893646240234),(Vehicles3↦-3.6599650382995605),(Vehicles4↦-7.6599647998809814),(Vehicles5↦-3.6599650382995605)}",
        "VehiclesVy": "{(EgoVehicle↦1.0796338319778442),(Vehicles2↦-7.4822187423706055),(Vehicles3↦-1.0796338319778442),(Vehicles4↦-1.0796338319778442),(Vehicles5↦-1.0796338319778442)}",
        "VehiclesX": "{(EgoVehicle↦179.62931394577026),(Vehicles2↦20.241175591945648),(Vehicles3↦43.90098452568054),(Vehicles4↦67.123281955719),(Vehicles5↦92.17430353164673)}"
      },
      "probabilisticVariables": null,
      "activating": [
        "FASTER_3"
      ],
      "activatingOnlyWhenExecuted": true,
      "updating": null,
      "withPredicate": null
    },
    {
      "id": "FASTER_3",
      "execute": "FASTER",
      "after": "1000",
      "priority": 0,
      "additionalGuards": null,
      "activationKind": null,
      "fixedVariables": {
        "Crash": "FALSE",
        "PresentVehicles": "{EgoVehicle,Vehicles2,Vehicles3,Vehicles4,Vehicles5}",
        "VehiclesAy": "{(EgoVehicle↦-1.0525126825086772),(Vehicles2↦6.665927618741989),(Vehicles3↦1.0525126825086772),(Vehicles4↦1.0525126825086772),(Vehicles5↦0.06951197981834412)}",
        "Reward": "0.9824413667099782",
        "VehiclesAx": "{(EgoVehicle↦4.364874362945557),(Vehicles2↦-3.024134635925293),(Vehicles3↦-5.042344331741333),(Vehicles4↦-5.290998220443726),(Vehicles5↦-4.623485207557678)}",
        "VehiclesVx": "{(EgoVehicle↦29.341552257537842),(Vehicles2↦-12.599060535430908),(Vehicles3↦-10.257909297943115),(Vehicles4↦-10.167124271392822),(Vehicles5↦-9.718785881996155)}",
        "VehiclesY": "{(EgoVehicle↦7.993496417999268),(Vehicles2↦-7.705824851989746),(Vehicles3↦-3.993496298789978),(Vehicles4↦-7.993496417999268),(Vehicles5↦-0.4016207456588745)}",
        "VehiclesVy": "{(EgoVehicle↦0.027121149469166994),(Vehicles2↦-0.8162911236286163),(Vehicles3↦-0.027121149469166994),(Vehicles4↦-0.027121149469166994),(Vehicles5↦1.1491458117961884)}",
        "VehiclesX": "{(EgoVehicle↦200.0),(Vehicles2↦8.904094994068146),(Vehicles3↦35.82170903682709),(Vehicles4↦59.44286584854126),(Vehicles5↦83.99702906608582)}"
      },
      "probabilisticVariables": null,
      "activating": [
        "IDLE_4"
      ],
      "activatingOnlyWhenExecuted": true,
      "updating": null,
      "withPredicate": null
    },
    {
      "id": "IDLE_4",
      "execute": "IDLE",
      "after": "1000",
      "priority": 0,
      "additionalGuards": null,
      "activationKind": null,
      "fixedVariables": {
        "Crash": "FALSE",
        "PresentVehicles": "{EgoVehicle,Vehicles2,Vehicles3,Vehicles4,Vehicles5}",
        "VehiclesAy": "{(EgoVehicle↦-0.027026898560507107),(Vehicles2↦0.7497237576171756),(Vehicles3↦0.027026898560507107),(Vehicles4↦0.027026898560507107),(Vehicles5↦1.2243007821962237)}",
        "Reward": "0.9976877960072628",
        "VehiclesAx": "{(EgoVehicle↦0.571739673614502),(Vehicles2↦0.10162949562072754),(Vehicles3↦0.05042433738708496),(Vehicles4↦-1.2819766998291016),(Vehicles5↦-0.3035050630569458)}",
        "VehiclesVx": "{(EgoVehicle↦29.913291931152344),(Vehicles2↦-12.49743103981018),(Vehicles3↦-10.20748496055603),(Vehicles4↦-11.449100971221924),(Vehicles5↦-10.0222909450531)}",
        "VehiclesY": "{(EgoVehicle↦8.000001668930054),(Vehicles2↦-7.975989103317261),(Vehicles3↦-4.000001907348633),(Vehicles4↦-8.000001668930054),(Vehicles5↦-0.025938824750483036)}",
        "VehiclesVy": "{(EgoVehicle↦9.42509086598875E-05),(Vehicles2↦-0.06656736601144075),(Vehicles3↦-9.42509086598875E-05),(Vehicles4↦-9.42509086598875E-05),(Vehicles5↦0.07515497040003538)}",
        "VehiclesX": "{(EgoVehicle↦200.0),(Vehicles2↦-3.7029676139354706),(Vehicles3↦25.522208213806152),(Vehicles4↦48.66084158420563),(Vehicles5↦74.10894632339478)}"
      },
      "probabilisticVariables": null,
      "activating": [
        "IDLE_5"
      ],
      "activatingOnlyWhenExecuted": true,
      "updating": null,
      "withPredicate": null
    },
    {
      "id": "IDLE_5",
      "execute": "IDLE",
      "after": "1000",
      "priority": 0,
      "additionalGuards": null,
      "activationKind": null,
      "fixedVariables": {
        "Crash": "FALSE",
        "PresentVehicles": "{EgoVehicle,Vehicles2,Vehicles3,Vehicles4,Vehicles5}",
        "VehiclesAy": "{(EgoVehicle↦-0.00010026566940268822),(Vehicles2↦0.06657338077218355),(Vehicles3↦0.00010026566940268822),(Vehicles4↦0.004817288327103597),(Vehicles5↦0.07516098516077818)}",
        "Reward": "0.9996955122319143",
        "VehiclesAx": "{(EgoVehicle↦0.07529020309448242),(Vehicles2↦2.5269299745559692),(Vehicles3↦-1.8541932106018066),(Vehicles4↦1.5872400999069214),(Vehicles5↦-3.599611520767212)}",
        "VehiclesVx": "{(EgoVehicle↦29.988582134246826),(Vehicles2↦-9.970501065254211),(Vehicles3↦-12.061678171157837),(Vehicles4↦-9.861860871315002),(Vehicles5↦-13.621902465820312)}",
        "VehiclesY": "{(EgoVehicle↦8.000001668930054),(Vehicles2↦-4.000001907348633),(Vehicles3↦-8.000001668930054),(Vehicles4↦-0.001617132977116853),(Vehicles5↦-8.000001668930054)}",
        "VehiclesVy": "{(EgoVehicle↦-6.014760742800718E-06),(Vehicles2↦6.014760742800718E-06),(Vehicles3↦6.014760742800718E-06),(Vehicles4↦0.00472303741844371),(Vehicles5↦6.014760742800718E-06)}",
        "VehiclesX": "{(EgoVehicle↦200.0),(Vehicles2↦15.419259667396545),(Vehicles3↦36.94285750389099),(Vehicles4↦64.11582827568054),(Vehicles5↦86.00234389305115)}"
      },
      "probabilisticVariables": null,
      "activating": [
        "FASTER_6"
      ],
      "activatingOnlyWhenExecuted": true,
      "updating": null,
      "withPredicate": null
    },
    {
      "id": "FASTER_6",
      "execute": "FASTER",
      "after": "1000",
      "priority": 0,
      "additionalGuards": null,
      "activationKind": null,
      "fixedVariables": {
        "Crash": "FALSE",
        "PresentVehicles": "{EgoVehicle,Vehicles2,Vehicles3,Vehicles4,Vehicles5}",
        "VehiclesAy": "{(EgoVehicle↦5.895750891937723E-06),(Vehicles2↦-5.895750891937723E-06),(Vehicles3↦-5.895750891937723E-06),(Vehicles4↦-0.0044434351366362534),(Vehicles5↦6.133770593663712E-06)}",
        "Reward": "0.9999599028453572",
        "VehiclesAx": "{(EgoVehicle↦0.009913444519042969),(Vehicles2↦0.08349120616912842),(Vehicles3↦-0.4042661190032959),(Vehicles4↦-0.28884828090667725),(Vehicles5↦-0.16208648681640625)}",
        "VehiclesVx": "{(EgoVehicle↦29.99849557876587),(Vehicles2↦-9.887009859085083),(Vehicles3↦-12.465944290161133),(Vehicles4↦-10.15070915222168),(Vehicles5↦-13.783988952636719)}",
        "VehiclesY": "{(EgoVehicle↦8.000000238418579),(Vehicles2↦-4.0000001192092896),(Vehicles3↦-8.000000238418579),(Vehicles4↦-9.773525016498752E-05),(Vehicles5↦-8.000000238418579)}",
        "VehiclesVy": "{(EgoVehicle↦-1.1900985086299443E-07),(Vehicles2↦1.1900985086299443E-07),(Vehicles3↦1.1900985086299443E-07),(Vehicles4↦0.00027960228180745617),(Vehicles5↦1.1900985086299443E-07)}",
        "VehiclesX": "{(EgoVehicle↦200.0),(Vehicles2↦5.498728901147842),(Vehicles3↦24.707423150539398),(Vehicles4↦54.34044003486633),(Vehicles5↦72.28965163230896)}"
      },
      "probabilisticVariables": null,
      "activating": [
        "SLOWER_7"
      ],
      "activatingOnlyWhenExecuted": true,
      "updating": null,
      "withPredicate": null
    },
    {
      "id": "SLOWER_7",
      "execute": "SLOWER",
      "after": "1000",
      "priority": 0,
      "additionalGuards": null,
      "activationKind": null,
      "fixedVariables": {
        "Crash": "FALSE",
        "PresentVehicles": "{EgoVehicle,Vehicles2,Vehicles3,Vehicles4,Vehicles5}",
        "VehiclesAy": "{(EgoVehicle↦1.1812399947075392E-07),(Vehicles2↦-1.1812399947075392E-07),(Vehicles3↦-1.1812399947075392E-07),(Vehicles4↦-0.0002608226134270808),(Vehicles5↦6.67922866324508)}",
        "Reward": "0.8842196854227081",
        "VehiclesAx": "{(EgoVehicle↦-4.34025764465332),(Vehicles2↦4.638965725898743),(Vehicles3↦4.069004654884338),(Vehicles4↦3.153969645500183),(Vehicles5↦2.995307445526123)}",
        "VehiclesVx": "{(EgoVehicle↦25.65823793411255),(Vehicles2↦-5.24804413318634),(Vehicles3↦-8.396939635276794),(Vehicles4↦-6.996739506721497),(Vehicles5↦-10.788681507110596)}",
        "VehiclesY": "{(EgoVehicle↦8.000000238418579),(Vehicles2↦-4.0000001192092896),(Vehicles3↦-8.000000238418579),(Vehicles4↦-6.705595524181263E-06),(Vehicles5↦-6.944553852081299)}",
        "VehiclesVy": "{(EgoVehicle↦-8.858513922405109E-10),(Vehicles2↦8.858513922405109E-10),(Vehicles3↦8.858513922405109E-10),(Vehicles4↦1.877966838037537E-05),(Vehicles5↦6.6792285442352295)}",
        "VehiclesX": "{(EgoVehicle↦200.0),(Vehicles2↦-1.890917494893074),(Vehicles3↦14.5181342959404),(Vehicles4↦46.014395356178284),(Vehicles5↦60.74436902999878)}"
      },
      "probabilisticVariables": null,
      "activating": [
        "SLOWER_8"
      ],
      "activatingOnlyWhenExecuted": true,
      "updating": null,
      "withPredicate": null
    },
    {
      "id": "SLOWER_8",
      "execute": "SLOWER",
      "after": "1000",
      "priority": 0,
      "additionalGuards": null,
      "activationKind": null,
      "fixedVariables": {
        "Crash": "FALSE",
        "PresentVehicles": "{EgoVehicle,Vehicles2,Vehicles3,Vehicles4,Vehicles5}",
        "VehiclesAy": "{(EgoVehicle↦8.661960038125471E-10),(Vehicles2↦-8.662048855967441E-10),(Vehicles3↦-8.662048855967441E-10),(Vehicles4↦-1.739757919949625E-05),(Vehicles5↦7.420932278037071)}",
        "Reward": "0.7532031410158848",
        "VehiclesAx": "{(EgoVehicle↦-4.913120269775391),(Vehicles2↦3.7800943851470947),(Vehicles3↦5.229545533657074),(Vehicles4↦4.467853605747223),(Vehicles5↦7.704421877861023)}",
        "VehiclesVx": "{(EgoVehicle↦20.745117664337158),(Vehicles2↦-1.4679497480392456),(Vehicles3↦-3.1673941016197205),(Vehicles4↦-2.5288859009742737),(Vehicles5↦-3.0842596292495728)}",
        "VehiclesY": "{(EgoVehicle↦8.000000238418579),(Vehicles2↦-4.0000001192092896),(Vehicles3↦-8.000000238418579),(Vehicles4↦-4.954835901571641E-07),(Vehicles5↦-4.263497471809387)}",
        "VehiclesVy": "{(EgoVehicle↦-1.965538842796377E-11),(Vehicles2↦1.964650664376677E-11),(Vehicles3↦1.964650664376677E-11),(Vehicles4↦1.3820891808791202E-06),(Vehicles5↦0.7417037338018417)}",
        "VehiclesX": "{(EgoVehicle↦200.0),(Vehicles2↦-4.994469881057739),(Vehicles3↦8.739957213401794),(Vehicles4↦41.51484668254852),(Vehicles5↦54.19711470603943)}"
      },
      "probabilisticVariables": null,
      "activating": [
        "SLOWER_9"
      ],
      "activatingOnlyWhenExecuted": true,
      "updating": null,
      "withPredicate": null
    },
    {
      "id": "SLOWER_9",
      "execute": "SLOWER",
      "after": "1000",
      "priority": 0,
      "additionalGuards": null,
      "activationKind": null,
      "fixedVariables": {
        "Crash": "FALSE",
        "PresentVehicles": "{EgoVehicle,Vehicles2,Vehicles3,Vehicles4,Vehicles5}",
        "VehiclesAy": "{(EgoVehicle↦1.8474111129762605E-11),(Vehicles2↦-1.8474111129762605E-11),(Vehicles3↦-1.8474111129762605E-11),(Vehicles4↦-1.2774345670152343E-06),(Vehicles5↦0.797084541991353)}",
        "Reward": "0.7359499335219821",
        "VehiclesAx": "{(EgoVehicle↦-0.6469941139221191),(Vehicles2↦0.3351914882659912),(Vehicles3↦1.6338664293289185),(Vehicles4↦0.5065420269966125),(Vehicles5↦2.0552481710910797)}",
        "VehiclesVx": "{(EgoVehicle↦20.09812355041504),(Vehicles2↦-1.1327582597732544),(Vehicles3↦-1.533527672290802),(Vehicles4↦-2.022343873977661),(Vehicles5↦-1.029011458158493)}",
        "VehiclesY": "{(EgoVehicle↦8.000000238418579),(Vehicles2↦-4.0000001192092896),(Vehicles3↦-8.000000238418579),(Vehicles4↦-3.753982191767591E-08),(Vehicles5↦-4.019216537475586)}",
        "VehiclesVy": "{(EgoVehicle↦-1.1812772982011666E-12),(Vehicles2↦1.1723955140041653E-12),(Vehicles3↦1.1723955140041653E-12),(Vehicles4↦1.0465461386388597E-07),(Vehicles5↦0.0553808081895113)}",
        "VehiclesX": "{(EgoVehicle↦200.0),(Vehicles2↦-6.265952438116074),(Vehicles3↦6.36095330119133),(Vehicles4↦39.270853996276855),(Vehicles5↦52.075570821762085)}"
      },
      "probabilisticVariables": null,
      "activating": [
        "IDLE_10"
      ],
      "activatingOnlyWhenExecuted": true,
      "updating": null,
      "withPredicate": null
    },
    {
      "id": "IDLE_10",
      "execute": "IDLE",
      "after": "1000",
      "priority": 0,
      "additionalGuards": null,
      "activationKind": null,
      "fixedVariables": {
        "Crash": "FALSE",
        "PresentVehicles": "{EgoVehicle,Vehicles2,Vehicles3,Vehicles4,Vehicles5}",
        "VehiclesAy": "{(EgoVehicle↦1.1102230246251565E-12),(Vehicles2↦-1.1013412404281553E-12),(Vehicles3↦-1.1013412404281553E-12),(Vehicles4↦-9.667607159258296E-08),(Vehicles5↦0.059013837308157235)}",
        "Reward": "0.7336779061976823",
        "VehiclesAx": "{(EgoVehicle↦-0.08520126342773438),(Vehicles2↦0.2782312035560608),(Vehicles3↦0.48131413757801056),(Vehicles4↦0.0835677981376648),(Vehicles5↦1.0603359015658498)}",
        "VehiclesVx": "{(EgoVehicle↦20.012922286987305),(Vehicles2↦-0.8545270562171936),(Vehicles3↦-1.0522135347127914),(Vehicles4↦-1.9387760758399963),(Vehicles5↦0.03132444340735674)}",
        "VehiclesY": "{(EgoVehicle↦8.000000238418579),(Vehicles2↦-8.000000238418579),(Vehicles3↦-4.0000001192092896),(Vehicles4↦-2.8590156908592235E-09),(Vehicles5↦-4.001239657402039)}",
        "VehiclesVy": "{(EgoVehicle↦-7.105427357601002E-14),(Vehicles2↦7.105427357601002E-14),(Vehicles3↦7.105427357601002E-14),(Vehicles4↦7.978542271303013E-09),(Vehicles5↦0.0036330291186459363)}",
        "VehiclesX": "{(EgoVehicle↦200.0),(Vehicles2↦5.137960612773895),(Vehicles3↦-7.369062304496765),(Vehicles4↦37.287649512290955),(Vehicles5↦51.51437520980835)}"
      },
      "probabilisticVariables": null,
      "activating": [
        "IDLE_11"
      ],
      "activatingOnlyWhenExecuted": true,
      "updating": null,
      "withPredicate": null
    },
    {
      "id": "IDLE_11",
      "execute": "IDLE",
      "after": "1000",
      "priority": 0,
      "additionalGuards": null,
      "activationKind": null,
      "fixedVariables": {
        "Crash": "FALSE",
        "PresentVehicles": "{EgoVehicle,Vehicles2,Vehicles3,Vehicles4,Vehicles5}",
        "VehiclesAy": "{(EgoVehicle↦7.105427357601002E-14),(Vehicles2↦-7.105427357601002E-14),(Vehicles3↦-7.105427357601002E-14),(Vehicles4↦-7.3722361548789195E-09),(Vehicles5↦0.0038507577301061247)}",
        "Reward": "0.7333787091837826",
        "VehiclesAx": "{(EgoVehicle↦-0.011219978332519531),(Vehicles2↦0.34316588193178177),(Vehicles3↦0.13346590101718903),(Vehicles4↦0.07123216986656189),(Vehicles5↦0.6467510340735316)}",
        "VehiclesVx": "{(EgoVehicle↦20.001702308654785),(Vehicles2↦-0.5113611742854118),(Vehicles3↦-0.9187476336956024),(Vehicles4↦-1.8675439059734344),(Vehicles5↦0.6780754774808884)}",
        "VehiclesY": "{(EgoVehicle↦8.000000238418579),(Vehicles2↦-8.000000238418579),(Vehicles3↦-4.0000001192092896),(Vehicles4↦-2.1689983142891833E-10),(Vehicles5↦-4.000073432922363)}",
        "VehiclesVy": "{(EgoVehicle↦0.0),(Vehicles2↦0.0),(Vehicles3↦0.0),(Vehicles4↦6.063061164240935E-10),(Vehicles5↦0.0002177286114601884)}",
        "VehiclesX": "{(EgoVehicle↦200.0),(Vehicles2↦4.4386159628629684),(Vehicles3↦-8.37189257144928),(Vehicles4↦35.37602722644806),(Vehicles5↦51.829588413238525)}"
      },
      "probabilisticVariables": null,
      "activating": [
        "IDLE_12"
      ],
      "activatingOnlyWhenExecuted": true,
      "updating": null,
      "withPredicate": null
    },
    {
      "id": "IDLE_12",
      "execute": "IDLE",
      "after": "1000",
      "priority": 0,
      "additionalGuards": null,
      "activationKind": null,
      "fixedVariables": {
        "Crash": "FALSE",
        "PresentVehicles": "{EgoVehicle,Vehicles2,Vehicles3,Vehicles4,Vehicles5}",
        "VehiclesAy": "{(EgoVehicle↦0.0),(Vehicles2↦0.0),(Vehicles3↦0.0),(Vehicles4↦-5.60582691377931E-10),(Vehicles5↦0.0002300299138369155)}",
        "Reward": "0.7333393087539686",
        "VehiclesAx": "{(EgoVehicle↦-0.0014781951904296875),(Vehicles2↦0.1762983575463295),(Vehicles3↦0.16237303614616394),(Vehicles4↦0.08546441793441772),(Vehicles5↦0.3883396089076996)}",
        "VehiclesVx": "{(EgoVehicle↦20.000224113464355),(Vehicles2↦-0.33506281673908234),(Vehicles3↦-0.7563745975494385),(Vehicles4↦-1.7820794880390167),(Vehicles5↦1.066415086388588)}",
        "VehiclesY": "{(EgoVehicle↦8.000000238418579),(Vehicles2↦-8.000000238418579),(Vehicles3↦-4.0000001192092896),(Vehicles4↦-1.6329604335396652E-11),(Vehicles5↦-4.000004053115845)}",
        "VehiclesVy": "{(EgoVehicle↦0.0),(Vehicles2↦0.0),(Vehicles3↦0.0),(Vehicles4↦4.572342504616245E-11),(Vehicles5↦1.2301302376727108E-05)}",
        "VehiclesX": "{(EgoVehicle↦200.0),(Vehicles2↦4.007323086261749),(Vehicles3↦-9.226422756910324),(Vehicles4↦33.541905879974365),(Vehicles5↦52.67966389656067)}"
      },
      "probabilisticVariables": null,
      "activating": [
        "SLOWER_13"
      ],
      "activatingOnlyWhenExecuted": true,
      "updating": null,
      "withPredicate": null
    },
    {
      "id": "SLOWER_13",
      "execute": "SLOWER",
      "after": "1000",
      "priority": 0,
      "additionalGuards": null,
      "activationKind": null,
      "fixedVariables": {
        "Crash": "FALSE",
        "PresentVehicles": "{EgoVehicle,Vehicles2,Vehicles3,Vehicles4,Vehicles5}",
        "VehiclesAy": "{(EgoVehicle↦0.0),(Vehicles2↦0.0),(Vehicles3↦0.0),(Vehicles4↦-4.2312819914513966E-11),(Vehicles5↦1.2971952756402061E-05)}",
        "Reward": "0.7333341202200013",
        "VehiclesAx": "{(EgoVehicle↦-0.00019550323486328125),(Vehicles2↦0.08667672052979469),(Vehicles3↦0.15867557376623154),(Vehicles4↦0.08974909782409668),(Vehicles5↦0.21812967956066132)}",
        "VehiclesVx": "{(EgoVehicle↦20.000028610229492),(Vehicles2↦-0.24838609620928764),(Vehicles3↦-0.5976990237832069),(Vehicles4↦-1.69233039021492),(Vehicles5↦1.2845447659492493)}",
        "VehiclesY": "{(EgoVehicle↦8.000000238418579),(Vehicles2↦-8.000000238418579),(Vehicles3↦-4.0000001192092896),(Vehicles4↦-1.220357148667972E-12),(Vehicles5↦-4.0000001192092896)}",
        "VehiclesVy": "{(EgoVehicle↦0.0),(Vehicles2↦0.0),(Vehicles3↦0.0),(Vehicles4↦3.410605131648481E-12),(Vehicles5↦6.70650379674953E-07)}",
        "VehiclesX": "{(EgoVehicle↦200.0),(Vehicles2↦3.7120677530765533),(Vehicles3↦-9.918208420276642),(Vehicles4↦31.79575502872467),(Vehicles5↦53.84417176246643)}"
      },
      "probabilisticVariables": null,
      "activating": [
        "SLOWER_14"
      ],
      "activatingOnlyWhenExecuted": true,
      "updating": null,
      "withPredicate": null
    },
    {
      "id": "SLOWER_14",
      "execute": "SLOWER",
      "after": "1000",
      "priority": 0,
      "additionalGuards": null,
      "activationKind": null,
      "fixedVariables": {
        "Crash": "FALSE",
        "PresentVehicles": "{EgoVehicle,Vehicles2,Vehicles3,Vehicles4,Vehicles5}",
        "VehiclesAy": "{(EgoVehicle↦0.0),(Vehicles2↦0.0),(Vehicles3↦2.4868995751603507E-13),(Vehicles4↦3.5849812007882065E-08),(Vehicles5↦6.70650379674953E-07)}",
        "Reward": "0.7333334369562691",
        "VehiclesAx": "{(EgoVehicle↦-2.384185791015625E-05),(Vehicles2↦0.03881823271512985),(Vehicles3↦-1.0081036016345024),(Vehicles4↦3.0859939754009247),(Vehicles5↦-2.380826249718666)}",
        "VehiclesVx": "{(EgoVehicle↦20.000004768371582),(Vehicles2↦-0.2095678634941578),(Vehicles3↦-1.6058026254177094),(Vehicles4↦1.3936635851860046),(Vehicles5↦-1.0962814837694168)}",
        "VehiclesY": "{(EgoVehicle↦8.000000238418579),(Vehicles2↦-8.000000238418579),(Vehicles3↦-9.192646643896296E-14),(Vehicles4↦-4.0000001192092896),(Vehicles5↦-8.000000238418579)}",
        "VehiclesVy": "{(EgoVehicle↦0.0),(Vehicles2↦0.0),(Vehicles3↦2.4868995751603507E-13),(Vehicles4↦3.585322261301371E-08),(Vehicles5↦0.0)}",
        "VehiclesX": "{(EgoVehicle↦200.0),(Vehicles2↦3.4819211810827255),(Vehicles3↦30.138477683067322),(Vehicles4↦55.17917275428772),(Vehicles5↦83.91194939613342)}"
      },
      "probabilisticVariables": null,
      "activating": [
        "SLOWER_15"
      ],
      "activatingOnlyWhenExecuted": true,
      "updating": null,
      "withPredicate": null
    },
    {
      "id": "SLOWER_15",
      "execute": "SLOWER",
      "after": "1000",
      "priority": 0,
      "additionalGuards": null,
      "activationKind": null,
      "fixedVariables": {
        "Crash": "FALSE",
        "PresentVehicles": "{EgoVehicle,Vehicles2,Vehicles3,Vehicles4,Vehicles5}",
        "VehiclesAy": "{(EgoVehicle↦0.0),(Vehicles2↦0.0),(Vehicles3↦-2.3092638912203256E-13),(Vehicles4↦-3.3953941880326965E-08),(Vehicles5↦0.0)}",
        "Reward": "0.7333333469791521",
        "VehiclesAx": "{(EgoVehicle↦-4.76837158203125E-06),(Vehicles2↦0.013804007321596146),(Vehicles3↦0.07985308766365051),(Vehicles4↦0.041593462228775024),(Vehicles5↦0.0990045815706253)}",
        "VehiclesVx": "{(EgoVehicle↦20.0),(Vehicles2↦-0.19576385617256165),(Vehicles3↦-1.5259495377540588),(Vehicles4↦1.4352570474147797),(Vehicles5↦-0.9972769021987915)}",
        "VehiclesY": "{(EgoVehicle↦8.000000238418579),(Vehicles2↦-8.000000238418579),(Vehicles3↦-6.661338147750939E-15),(Vehicles4↦-4.0000001192092896),(Vehicles5↦-8.000000238418579)}",
        "VehiclesVy": "{(EgoVehicle↦0.0),(Vehicles2↦0.0),(Vehicles3↦1.7763568394002505E-14),(Vehicles4↦1.899280732686748E-09),(Vehicles5↦0.0)}",
        "VehiclesX": "{(EgoVehicle↦200.0),(Vehicles2↦3.279271721839905),(Vehicles3↦28.565216064453125),(Vehicles4↦56.59362077713013),(Vehicles5↦82.85649418830872)}"
      },
      "probabilisticVariables": null,
      "activating": [
        "SLOWER_16"
      ],
      "activatingOnlyWhenExecuted": true,
      "updating": null,
      "withPredicate": null
    },
    {
      "id": "SLOWER_16",
      "execute": "SLOWER",
      "after": "1000",
      "priority": 0,
      "additionalGuards": null,
      "activationKind": null,
      "fixedVariables": {
        "Crash": "FALSE",
        "PresentVehicles": "{EgoVehicle,Vehicles2,Vehicles3,Vehicles4,Vehicles5}",
        "VehiclesAy": "{(EgoVehicle↦0.0),(Vehicles2↦0.0),(Vehicles3↦-1.7763568394002505E-14),(Vehicles4↦-1.7989343348290276E-09),(Vehicles5↦0.0)}",
        "Reward": "0.7333333351303136",
        "VehiclesAx": "{(EgoVehicle↦0.0),(Vehicles2↦0.001111738383769989),(Vehicles3↦0.07213160395622253),(Vehicles4↦0.0010180473327636719),(Vehicles5↦0.08528448641300201)}",
        "VehiclesVx": "{(EgoVehicle↦20.0),(Vehicles2↦-0.19465211778879166),(Vehicles3↦-1.4538179337978363),(Vehicles4↦1.4362750947475433),(Vehicles5↦-0.9119924157857895)}",
        "VehiclesY": "{(EgoVehicle↦8.000000238418579),(Vehicles2↦-8.000000238418579),(Vehicles3↦-1.3322676295501878E-15),(Vehicles4↦-4.0000001192092896),(Vehicles5↦-8.000000238418579)}",
        "VehiclesVy": "{(EgoVehicle↦0.0),(Vehicles2↦0.0),(Vehicles3↦0.0),(Vehicles4↦1.0034639785772015E-10),(Vehicles5↦0.0)}",
        "VehiclesX": "{(EgoVehicle↦200.0),(Vehicles2↦3.0846448615193367),(Vehicles3↦27.068743109703064),(Vehicles4↦58.031731843948364),(Vehicles5↦81.89430832862854)}"
      },
      "probabilisticVariables": null,
      "activating": [
        "SLOWER_17"
      ],
      "activatingOnlyWhenExecuted": true,
      "updating": null,
      "withPredicate": null
    },
    {
      "id": "SLOWER_17",
      "execute": "SLOWER",
      "after": "1000",
      "priority": 0,
      "additionalGuards": null,
      "activationKind": null,
      "fixedVariables": {
        "Crash": "FALSE",
        "PresentVehicles": "{EgoVehicle,Vehicles2,Vehicles3,Vehicles4,Vehicles5}",
        "VehiclesAy": "{(EgoVehicle↦0.0),(Vehicles2↦0.0),(Vehicles3↦0.0),(Vehicles4↦-9.50350909079134E-11),(Vehicles5↦0.0)}",
        "Reward": "0.7333333335699727",
        "VehiclesAx": "{(EgoVehicle↦0.0),(Vehicles2↦-0.0050117261707782745),(Vehicles3↦0.06456956267356873),(Vehicles4↦-0.022561997175216675),(Vehicles5↦0.07432453334331512)}",
        "VehiclesVx": "{(EgoVehicle↦20.0),(Vehicles2↦-0.19966384395956993),(Vehicles3↦-1.3892483711242676),(Vehicles4↦1.4137130975723267),(Vehicles5↦-0.8376678824424744)}",
        "VehiclesY": "{(EgoVehicle↦8.000000238418579),(Vehicles2↦-8.000000238418579),(Vehicles3↦-1.3322676295501878E-15),(Vehicles4↦-4.0000001192092896),(Vehicles5↦-8.000000238418579)}",
        "VehiclesVy": "{(EgoVehicle↦0.0),(Vehicles2↦0.0),(Vehicles3↦0.0),(Vehicles4↦5.311306949806749E-12),(Vehicles5↦0.0)}",
        "VehiclesX": "{(EgoVehicle↦200.0),(Vehicles2↦2.888306602835655),(Vehicles3↦25.641334056854248),(Vehicles4↦59.46037173271179),(Vehicles5↦81.01283311843872)}"
      },
      "probabilisticVariables": null,
      "activating": [
        "SLOWER_18"
      ],
      "activatingOnlyWhenExecuted": true,
      "updating": null,
      "withPredicate": null
    },
    {
      "id": "SLOWER_18",
      "execute": "SLOWER",
      "after": "1000",
      "priority": 0,
      "additionalGuards": null,
      "activationKind": null,
      "fixedVariables": {
        "Crash": "FALSE",
        "PresentVehicles": "{EgoVehicle,Vehicles2,Vehicles3,Vehicles4,Vehicles5}",
        "VehiclesAy": "{(EgoVehicle↦0.0),(Vehicles2↦0.0),(Vehicles3↦0.0),(Vehicles4↦-5.027089855502709E-12),(Vehicles5↦0.0)}",
        "Reward": "0.7333333333644957",
        "VehiclesAx": "{(EgoVehicle↦0.0),(Vehicles2↦-0.007660984992980957),(Vehicles3↦0.057698339223861694),(Vehicles4↦-0.03561064600944519),(Vehicles5↦0.0654458999633789)}",
        "VehiclesVx": "{(EgoVehicle↦20.0),(Vehicles2↦-0.2073248289525509),(Vehicles3↦-1.3315500319004059),(Vehicles4↦1.3781024515628815),(Vehicles5↦-0.7722219824790955)}",
        "VehiclesY": "{(EgoVehicle↦8.000000238418579),(Vehicles2↦-8.000000238418579),(Vehicles3↦-1.3322676295501878E-15),(Vehicles4↦-4.0000001192092896),(Vehicles5↦-8.000000238418579)}",
        "VehiclesVy": "{(EgoVehicle↦0.0),(Vehicles2↦0.0),(Vehicles3↦0.0),(Vehicles4↦2.8421709430404007E-13),(Vehicles5↦0.0)}",
        "VehiclesX": "{(EgoVehicle↦200.0),(Vehicles2↦2.6857001706957817),(Vehicles3↦24.275681376457214),(Vehicles4↦60.86058020591736),(Vehicles5↦80.20198345184326)}"
      },
      "probabilisticVariables": null,
      "activating": [
        "SLOWER_19"
      ],
      "activatingOnlyWhenExecuted": true,
      "updating": null,
      "withPredicate": null
    },
    {
      "id": "SLOWER_19",
      "execute": "SLOWER",
      "after": "1000",
      "priority": 0,
      "additionalGuards": null,
      "activationKind": null,
      "fixedVariables": {
        "Crash": "FALSE",
        "PresentVehicles": "{EgoVehicle,Vehicles2,Vehicles3,Vehicles4,Vehicles5}",
        "VehiclesAy": "{(EgoVehicle↦0.0),(Vehicles2↦0.0),(Vehicles3↦0.0),(Vehicles4↦-2.6645352591003757E-13),(Vehicles5↦0.0)}",
        "Reward": "0.7333333333374371",
        "VehiclesAx": "{(EgoVehicle↦0.0),(Vehicles2↦-0.00848604366183281),(Vehicles3↦0.05169764161109924),(Vehicles4↦-0.042191892862319946),(Vehicles5↦0.058153122663497925)}",
        "VehiclesVx": "{(EgoVehicle↦20.0),(Vehicles2↦-0.2158108726143837),(Vehicles3↦-1.2798523902893066),(Vehicles4↦1.3359105587005615),(Vehicles5↦-0.7140688598155975)}",
        "VehiclesY": "{(EgoVehicle↦8.000000238418579),(Vehicles2↦-8.000000238418579),(Vehicles3↦-1.3322676295501878E-15),(Vehicles4↦-4.0000001192092896),(Vehicles5↦-8.000000238418579)}",
        "VehiclesVy": "{(EgoVehicle↦0.0),(Vehicles2↦0.0),(Vehicles3↦0.0),(Vehicles4↦1.7763568394002505E-14),(Vehicles5↦0.0)}",
        "VehiclesX": "{(EgoVehicle↦200.0),(Vehicles2↦2.474999986588955),(Vehicles3↦22.96525537967682),(Vehicles4↦62.22214698791504),(Vehicles5↦79.45355176925659)}"
      },
      "probabilisticVariables": null,
      "activating": [
        "SLOWER_20"
      ],
      "activatingOnlyWhenExecuted": true,
      "updating": null,
      "withPredicate": null
    },
    {
      "id": "SLOWER_20",
      "execute": "SLOWER",
      "after": "1000",
      "priority": 0,
      "additionalGuards": null,
      "activationKind": null,
      "fixedVariables": {
        "Crash": "FALSE",
        "PresentVehicles": "{EgoVehicle,Vehicles2,Vehicles3,Vehicles4,Vehicles5}",
        "VehiclesAy": "{(EgoVehicle↦0.0),(Vehicles2↦0.0),(Vehicles3↦0.0),(Vehicles4↦-1.7763568394002505E-14),(Vehicles5↦0.0)}",
        "Reward": "0.7333333333338737",
        "VehiclesAx": "{(EgoVehicle↦0.0),(Vehicles2↦-0.008364450186491013),(Vehicles3↦0.046573132276535034),(Vehicles4↦-0.04481911659240723),(Vehicles5↦0.052084699273109436)}",
        "VehiclesVx": "{(EgoVehicle↦20.0),(Vehicles2↦-0.2241753228008747),(Vehicles3↦-1.2332792580127716),(Vehicles4↦1.2910914421081543),(Vehicles5↦-0.6619841605424881)}",
        "VehiclesY": "{(EgoVehicle↦8.000000238418579),(Vehicles2↦-8.000000238418579),(Vehicles3↦-1.3322676295501878E-15),(Vehicles4↦-4.0000001192092896),(Vehicles5↦-8.000000238418579)}",
        "VehiclesVy": "{(EgoVehicle↦0.0),(Vehicles2↦0.0),(Vehicles3↦0.0),(Vehicles4↦0.0),(Vehicles5↦0.0)}",
        "VehiclesX": "{(EgoVehicle↦200.0),(Vehicles2↦2.2558094933629036),(Vehicles3↦21.704408526420593),(Vehicles4↦63.540226221084595),(Vehicles5↦78.76076102256775)}"
      },
      "probabilisticVariables": null,
      "activating": [
        "SLOWER_21"
      ],
      "activatingOnlyWhenExecuted": true,
      "updating": null,
      "withPredicate": null
    },
    {
      "id": "SLOWER_21",
      "execute": "SLOWER",
      "after": "1000",
      "priority": 0,
      "additionalGuards": null,
      "activationKind": null,
      "fixedVariables": {
        "Crash": "FALSE",
        "PresentVehicles": "{EgoVehicle,Vehicles2,Vehicles3,Vehicles4,Vehicles5}",
        "VehiclesAy": "{(EgoVehicle↦0.0),(Vehicles2↦0.0),(Vehicles3↦0.0),(Vehicles4↦0.0),(Vehicles5↦0.0)}",
        "Reward": "0.7333333333334044",
        "VehiclesAx": "{(EgoVehicle↦0.0),(Vehicles2↦-0.007763374596834183),(Vehicles3↦0.042252764105796814),(Vehicles4↦-0.04503466188907623),(Vehicles5↦0.046975016593933105)}",
        "VehiclesVx": "{(EgoVehicle↦20.0),(Vehicles2↦-0.2319386973977089),(Vehicles3↦-1.1910264939069748),(Vehicles4↦1.246056780219078),(Vehicles5↦-0.615009143948555)}",
        "VehiclesY": "{(EgoVehicle↦8.000000238418579),(Vehicles2↦-8.000000238418579),(Vehicles3↦-1.3322676295501878E-15),(Vehicles4↦-4.0000001192092896),(Vehicles5↦-8.000000238418579)}",
        "VehiclesVy": "{(EgoVehicle↦0.0),(Vehicles2↦0.0),(Vehicles3↦0.0),(Vehicles4↦0.0),(Vehicles5↦0.0)}",
        "VehiclesX": "{(EgoVehicle↦200.0),(Vehicles2↦2.028468996286392),(Vehicles3↦20.488345623016357),(Vehicles4↦64.81325030326843),(Vehicles5↦78.1179428100586)}"
      },
      "probabilisticVariables": null,
      "activating": [
        "SLOWER_22"
      ],
      "activatingOnlyWhenExecuted": true,
      "updating": null,
      "withPredicate": null
    },
    {
      "id": "SLOWER_22",
      "execute": "SLOWER",
      "after": "1000",
      "priority": 0,
      "additionalGuards": null,
      "activationKind": null,
      "fixedVariables": {
        "Crash": "FALSE",
        "PresentVehicles": "{EgoVehicle,Vehicles2,Vehicles3,Vehicles4,Vehicles5}",
        "VehiclesAy": "{(EgoVehicle↦0.0),(Vehicles2↦0.0),(Vehicles3↦0.0),(Vehicles4↦0.0),(Vehicles5↦0.0)}",
        "Reward": "0.7333333333333427",
        "VehiclesAx": "{(EgoVehicle↦0.0),(Vehicles2↦-0.00693250447511673),(Vehicles3↦0.03863520920276642),(Vehicles4↦-0.04378609359264374),(Vehicles5↦0.04262693226337433)}",
        "VehiclesVx": "{(EgoVehicle↦20.0),(Vehicles2↦-0.23887120187282562),(Vehicles3↦-1.1523912847042084),(Vehicles4↦1.2022706866264343),(Vehicles5↦-0.5723822116851807)}",
        "VehiclesY": "{(EgoVehicle↦8.000000238418579),(Vehicles2↦-8.000000238418579),(Vehicles3↦-1.3322676295501878E-15),(Vehicles4↦-4.0000001192092896),(Vehicles5↦-8.000000238418579)}",
        "VehiclesVy": "{(EgoVehicle↦0.0),(Vehicles2↦0.0),(Vehicles3↦0.0),(Vehicles4↦0.0),(Vehicles5↦0.0)}",
        "VehiclesX": "{(EgoVehicle↦200.0),(Vehicles2↦1.7936855554580688),(Vehicles3↦19.313037395477295),(Vehicles4↦66.04165434837341),(Vehicles5↦77.52030491828918)}"
      },
      "probabilisticVariables": null,
      "activating": [
        "SLOWER_23"
      ],
      "activatingOnlyWhenExecuted": true,
      "updating": null,
      "withPredicate": null
    },
    {
      "id": "SLOWER_23",
      "execute": "SLOWER",
      "after": "1000",
      "priority": 0,
      "additionalGuards": null,
      "activationKind": null,
      "fixedVariables": {
        "Crash": "FALSE",
        "PresentVehicles": "{EgoVehicle,Vehicles2,Vehicles3,Vehicles4,Vehicles5}",
        "VehiclesAy": "{(EgoVehicle↦0.0),(Vehicles2↦0.0),(Vehicles3↦0.0),(Vehicles4↦0.0),(Vehicles5↦0.0)}",
        "Reward": "0.7333333333333346",
        "VehiclesAx": "{(EgoVehicle↦0.0),(Vehicles2↦-0.006005838513374329),(Vehicles3↦0.03561526536941528),(Vehicles4↦-0.0416593998670578),(Vehicles5↦0.03889262676239014)}",
        "VehiclesVx": "{(EgoVehicle↦20.0),(Vehicles2↦-0.24487704038619995),(Vehicles3↦-1.116776019334793),(Vehicles4↦1.1606112867593765),(Vehicles5↦-0.5334895849227905)}",
        "VehiclesY": "{(EgoVehicle↦8.000000238418579),(Vehicles2↦-8.000000238418579),(Vehicles3↦-1.3322676295501878E-15),(Vehicles4↦-4.0000001192092896),(Vehicles5↦-8.000000238418579)}",
        "VehiclesVy": "{(EgoVehicle↦0.0),(Vehicles2↦0.0),(Vehicles3↦0.0),(Vehicles4↦0.0),(Vehicles5↦0.0)}",
        "VehiclesX": "{(EgoVehicle↦200.0),(Vehicles2↦1.5523362904787064),(Vehicles3↦18.175113201141357),(Vehicles4↦67.2270655632019),(Vehicles5↦76.96375846862793)}"
      },
      "probabilisticVariables": null,
      "activating": [
        "SLOWER_24"
      ],
      "activatingOnlyWhenExecuted": true,
      "updating": null,
      "withPredicate": null
    },
    {
      "id": "SLOWER_24",
      "execute": "SLOWER",
      "after": "1000",
      "priority": 0,
      "additionalGuards": null,
      "activationKind": null,
      "fixedVariables": {
        "Crash": "FALSE",
        "PresentVehicles": "{EgoVehicle,Vehicles2,Vehicles3,Vehicles4,Vehicles5}",
        "VehiclesAy": "{(EgoVehicle↦0.0),(Vehicles2↦0.0),(Vehicles3↦0.0),(Vehicles4↦0.0),(Vehicles5↦0.0)}",
        "Reward": "0.7333333333333335",
        "VehiclesAx": "{(EgoVehicle↦0.0),(Vehicles2↦-0.005055535584688187),(Vehicles3↦0.033095479011535645),(Vehicles4↦-0.03902070224285126),(Vehicles5↦0.03565952181816101)}",
        "VehiclesVx": "{(EgoVehicle↦20.0),(Vehicles2↦-0.24993257597088814),(Vehicles3↦-1.0836805403232574),(Vehicles4↦1.1215905845165253),(Vehicles5↦-0.4978300631046295)}",
        "VehiclesY": "{(EgoVehicle↦8.000000238418579),(Vehicles2↦-8.000000238418579),(Vehicles3↦-1.3322676295501878E-15),(Vehicles4↦-4.0000001192092896),(Vehicles5↦-8.000000238418579)}",
        "VehiclesVy": "{(EgoVehicle↦0.0),(Vehicles2↦0.0),(Vehicles3↦0.0),(Vehicles4↦0.0),(Vehicles5↦0.0)}",
        "VehiclesX": "{(EgoVehicle↦200.0),(Vehicles2↦1.3053611852228642),(Vehicles3↦17.071758210659027),(Vehicles4↦68.37184429168701),(Vehicles5↦76.44477486610413)}"
      },
      "probabilisticVariables": null,
      "activating": [
        "SLOWER_25"
      ],
      "activatingOnlyWhenExecuted": true,
      "updating": null,
      "withPredicate": null
    },
    {
      "id": "SLOWER_25",
      "execute": "SLOWER",
      "after": "1000",
      "priority": 0,
      "additionalGuards": null,
      "activationKind": null,
      "fixedVariables": {
        "Crash": "FALSE",
        "PresentVehicles": "{EgoVehicle,Vehicles2,Vehicles3,Vehicles4,Vehicles5}",
        "VehiclesAy": "{(EgoVehicle↦0.0),(Vehicles2↦0.0),(Vehicles3↦0.0),(Vehicles4↦0.0),(Vehicles5↦0.0)}",
        "Reward": "0.7333333333333334",
        "VehiclesAx": "{(EgoVehicle↦0.0),(Vehicles2↦-0.004120431840419769),(Vehicles3↦0.030989423394203186),(Vehicles4↦-0.03610342741012573),(Vehicles5↦0.03284066915512085)}",
        "VehiclesVx": "{(EgoVehicle↦20.0),(Vehicles2↦-0.2540530078113079),(Vehicles3↦-1.0526911169290543),(Vehicles4↦1.0854871571063995),(Vehicles5↦-0.46498939394950867)}",
        "VehiclesY": "{(EgoVehicle↦8.000000238418579),(Vehicles2↦-8.000000238418579),(Vehicles3↦-1.3322676295501878E-15),(Vehicles4↦-4.0000001192092896),(Vehicles5↦-8.000000238418579)}",
        "VehiclesVy": "{(EgoVehicle↦0.0),(Vehicles2↦0.0),(Vehicles3↦0.0),(Vehicles4↦0.0),(Vehicles5↦0.0)}",
        "VehiclesX": "{(EgoVehicle↦200.0),(Vehicles2↦1.0537068359553814),(Vehicles3↦16.00062847137451),(Vehicles4↦69.47875022888184),(Vehicles5↦75.96029043197632)}"
      },
      "probabilisticVariables": null,
      "activating": [
        "SLOWER_26"
      ],
      "activatingOnlyWhenExecuted": true,
      "updating": null,
      "withPredicate": null
    },
    {
      "id": "SLOWER_26",
      "execute": "SLOWER",
      "after": "1000",
      "priority": 0,
      "additionalGuards": null,
      "activationKind": null,
      "fixedVariables": {
        "Crash": "FALSE",
        "PresentVehicles": "{EgoVehicle,Vehicles2,Vehicles3,Vehicles4,Vehicles5}",
        "VehiclesAy": "{(EgoVehicle↦0.0),(Vehicles2↦0.0),(Vehicles3↦0.0),(Vehicles4↦0.0),(Vehicles5↦0.0)}",
        "Reward": "0.7333333333333334",
        "VehiclesAx": "{(EgoVehicle↦0.0),(Vehicles2↦-0.0032212398946285248),(Vehicles3↦0.029223859310150146),(Vehicles4↦-0.0330585241317749),(Vehicles5↦0.030368007719516754)}",
        "VehiclesVx": "{(EgoVehicle↦20.0),(Vehicles2↦-0.25727424770593643),(Vehicles3↦-1.0234672576189041),(Vehicles4↦1.0524286329746246),(Vehicles5↦-0.4346213862299919)}",
        "VehiclesY": "{(EgoVehicle↦8.000000238418579),(Vehicles2↦-8.000000238418579),(Vehicles3↦-1.3322676295501878E-15),(Vehicles4↦-4.0000001192092896),(Vehicles5↦-8.000000238418579)}",
        "VehiclesVy": "{(EgoVehicle↦0.0),(Vehicles2↦0.0),(Vehicles3↦0.0),(Vehicles4↦0.0),(Vehicles5↦0.0)}",
        "VehiclesX": "{(EgoVehicle↦200.0),(Vehicles2↦0.79829515889287),(Vehicles3↦14.959755539894104),(Vehicles4↦70.55076956748962),(Vehicles5↦75.50763487815857)}"
      },
      "probabilisticVariables": null,
      "activating": [
        "LANE_LEFT_27"
      ],
      "activatingOnlyWhenExecuted": true,
      "updating": null,
      "withPredicate": null
    },
    {
      "id": "LANE_LEFT_27",
      "execute": "LANE_LEFT",
      "after": "1000",
      "priority": 0,
      "additionalGuards": null,
      "activationKind": null,
      "fixedVariables": {
        "Crash": "FALSE",
        "PresentVehicles": "{EgoVehicle,Vehicles2,Vehicles3,Vehicles4,Vehicles5}",
        "VehiclesAy": "{(EgoVehicle↦-1.1458635330200195),(Vehicles2↦1.1458635330200195),(Vehicles3↦1.1458635330200195),(Vehicles4↦1.1458635330200195),(Vehicles5↦1.1458635330200195)}",
        "Reward": "0.7000000000000001",
        "VehiclesAx": "{(EgoVehicle↦-0.0328516960144043),(Vehicles2↦0.030483566224575043),(Vehicles3↦0.06058931350708008),(Vehicles4↦0.002865418791770935),(Vehicles5↦0.06103940308094025)}",
        "VehiclesVx": "{(EgoVehicle↦19.967148303985596),(Vehicles2↦-0.2267906814813614),(Vehicles3↦-0.962877944111824),(Vehicles4↦1.0552940517663956),(Vehicles5↦-0.37358198314905167)}",
        "VehiclesY": "{(EgoVehicle↦4.396300435066223),(Vehicles2↦-4.396300435066223),(Vehicles3↦3.6036994457244873),(Vehicles4↦-0.39630044996738434),(Vehicles5↦-4.396300435066223)}",
        "VehiclesVy": "{(EgoVehicle↦-1.1458635330200195),(Vehicles2↦1.1458635330200195),(Vehicles3↦1.1458635330200195),(Vehicles4↦1.1458635330200195),(Vehicles5↦1.1458635330200195)}",
        "VehiclesX": "{(EgoVehicle↦200.0),(Vehicles2↦0.9266006760299206),(Vehicles3↦14.334085583686829),(Vehicles4↦71.97754979133606),(Vehicles5↦75.47104358673096)}"
      },
      "probabilisticVariables": null,
      "activating": [
        "FASTER_28"
      ],
      "activatingOnlyWhenExecuted": true,
      "updating": null,
      "withPredicate": null
    },
    {
      "id": "FASTER_28",
      "execute": "FASTER",
      "after": "1000",
      "priority": 0,
      "additionalGuards": null,
      "activationKind": null,
      "fixedVariables": {
        "Crash": "FALSE",
        "PresentVehicles": "{EgoVehicle,Vehicles2,Vehicles3,Vehicles4,Vehicles5}",
        "VehiclesAy": "{(EgoVehicle↦1.0893553588539362),(Vehicles2↦-1.0893553588539362),(Vehicles3↦-1.0893553588539362),(Vehicles4↦-1.0893553588539362),(Vehicles5↦1.2023717071861029)}",
        "Reward": "0.8157732851985893",
        "VehiclesAx": "{(EgoVehicle↦4.374349117279053),(Vehicles2↦-4.375917539000511),(Vehicles3↦-4.347871467471123),(Vehicles4↦-4.401305690407753),(Vehicles5↦-4.348095022141933)}",
        "VehiclesVx": "{(EgoVehicle↦24.34149742126465),(Vehicles2↦-4.602708220481873),(Vehicles3↦-5.310749411582947),(Vehicles4↦-3.3460116386413574),(Vehicles5↦-4.721677005290985)}",
        "VehiclesY": "{(EgoVehicle↦4.017063617706299),(Vehicles2↦-4.017063617706299),(Vehicles3↦3.9829366207122803),(Vehicles4↦-0.017063469160348177),(Vehicles5↦-4.017063617706299)}",
        "VehiclesVy": "{(EgoVehicle↦-0.056508174166083336),(Vehicles2↦0.056508174166083336),(Vehicles3↦0.056508174166083336),(Vehicles4↦0.056508174166083336),(Vehicles5↦0.056508174166083336)}",
        "VehiclesX": "{(EgoVehicle↦200.0),(Vehicles2↦-1.723475195467472),(Vehicles3↦10.959295183420181),(Vehicles4↦70.59922814369202),(Vehicles5↦72.68550992012024)}"
      },
      "probabilisticVariables": null,
      "activating": [
        "SLOWER_29"
      ],
      "activatingOnlyWhenExecuted": true,
      "updating": null,
      "withPredicate": null
    },
    {
      "id": "SLOWER_29",
      "execute": "SLOWER",
      "after": "1000",
      "priority": 0,
      "additionalGuards": null,
      "activationKind": null,
      "fixedVariables": {
        "Crash": "FALSE",
        "PresentVehicles": "{EgoVehicle,Vehicles2,Vehicles3,Vehicles4,Vehicles5}",
        "VehiclesAy": "{(EgoVehicle↦0.05412492610048503),(Vehicles2↦-0.05412492610048503),(Vehicles3↦-0.05412492610048503),(Vehicles4↦-0.05412492610048503),(Vehicles5↦0.058891422231681645)}",
        "Reward": "0.7152460913696584",
        "VehiclesAx": "{(EgoVehicle↦-3.7697696685791016),(Vehicles2↦3.7689507752656937),(Vehicles3↦3.795175552368164),(Vehicles4↦3.745758831501007),(Vehicles5↦3.794305995106697)}",
        "VehiclesVx": "{(EgoVehicle↦20.571727752685547),(Vehicles2↦-0.8337574452161789),(Vehicles3↦-1.5155738592147827),(Vehicles4↦0.39974719285964966),(Vehicles5↦-0.927371010184288)}",
        "VehiclesY": "{(EgoVehicle↦4.000823378562927),(Vehicles2↦-4.000823378562927),(Vehicles3↦3.999176502227783),(Vehicles4↦-0.0008233688422478735),(Vehicles5↦-4.000823378562927)}",
        "VehiclesVy": "{(EgoVehicle↦-0.002383248065598309),(Vehicles2↦0.002383248065598309),(Vehicles3↦0.002383248065598309),(Vehicles4↦0.002383248065598309),(Vehicles5↦0.002383248065598309)}",
        "VehiclesX": "{(EgoVehicle↦200.0),(Vehicles2↦-4.246962070465088),(Vehicles3↦7.7383942902088165),(Vehicles4↦69.32298541069031),(Vehicles5↦70.05338668823242)}"
      },
      "probabilisticVariables": null,
      "activating": [
        "FASTER_30"
      ],
      "activatingOnlyWhenExecuted": true,
      "updating": null,
      "withPredicate": null
    },
    {
      "id": "FASTER_30",
      "execute": "FASTER",
      "after": "1000",
      "priority": 0,
      "additionalGuards": null,
      "activationKind": null,
      "fixedVariables": {
        "Crash": "FALSE",
        "PresentVehicles": "{EgoVehicle,Vehicles2,Vehicles3,Vehicles4,Vehicles5}",
        "VehiclesAy": "{(EgoVehicle↦0.0022678229106531944),(Vehicles2↦-0.0022678229106531944),(Vehicles3↦-0.0022678229106531944),(Vehicles4↦-0.0022678229106531944),(Vehicles5↦0.0024986732205434237)}",
        "Reward": "0.8177827505069857",
        "VehiclesAx": "{(EgoVehicle↦3.8451242446899414),(Vehicles2↦-4.5024556666612625),(Vehicles3↦-3.1634321808815002),(Vehicles4↦-5.14924168586731),(Vehicles5↦-2.5391919165849686)}",
        "VehiclesVx": "{(EgoVehicle↦24.41685199737549),(Vehicles2↦-5.336213111877441),(Vehicles3↦-4.679006040096283),(Vehicles4↦-4.74949449300766),(Vehicles5↦-3.4665629267692566)}",
        "VehiclesY": "{(EgoVehicle↦4.000034809112549),(Vehicles2↦3.9999650716781616),(Vehicles3↦-4.000034809112549),(Vehicles4↦-4.000034809112549),(Vehicles5↦-3.4879961276601534E-05)}",
        "VehiclesVy": "{(EgoVehicle↦-0.00011542515494511463),(Vehicles2↦0.00011542515494511463),(Vehicles3↦0.00011542515494511463),(Vehicles4↦0.00011542515494511463),(Vehicles5↦0.00011542515494511463)}",
        "VehiclesX": "{(EgoVehicle↦200.0),(Vehicles2↦4.111486300826073),(Vehicles3↦-7.202019542455673),(Vehicles4↦67.0141339302063),(Vehicles5↦67.59284138679504)}"
      },
      "probabilisticVariables": null,
      "activating": [
        "SLOWER_31"
      ],
      "activatingOnlyWhenExecuted": true,
      "updating": null,
      "withPredicate": null
    },
    {
      "id": "SLOWER_31",
      "execute": "SLOWER",
      "after": "1000",
      "priority": 0,
      "additionalGuards": null,
      "activationKind": null,
      "fixedVariables": {
        "Crash": "FALSE",
        "PresentVehicles": "{EgoVehicle,Vehicles2,Vehicles3,Vehicles4,Vehicles5}",
        "VehiclesAy": "{(EgoVehicle↦0.00011056206631110399),(Vehicles2↦-0.00011056206631110399),(Vehicles3↦-0.00011056206631110399),(Vehicles4↦-0.00011056206631110399),(Vehicles5↦0.00012028824357912526)}",
        "Reward": "0.7155104856644142",
        "VehiclesAx": "{(EgoVehicle↦-3.8352084159851074),(Vehicles2↦3.8588975369930267),(Vehicles3↦3.8357295840978622),(Vehicles4↦3.856835439801216),(Vehicles5↦2.316328212618828)}",
        "VehiclesVx": "{(EgoVehicle↦20.58164358139038),(Vehicles2↦-1.4773155748844147),(Vehicles3↦-0.8432764559984207),(Vehicles4↦-0.8926590532064438),(Vehicles5↦-1.1502347141504288)}",
        "VehiclesY": "{(EgoVehicle↦4.000001549720764),(Vehicles2↦3.9999983310699463),(Vehicles3↦-4.000001549720764),(Vehicles4↦-4.000001549720764),(Vehicles5↦3.9999983310699463)}",
        "VehiclesVy": "{(EgoVehicle↦-4.863088634010637E-06),(Vehicles2↦4.863088634010637E-06),(Vehicles3↦4.863088634010637E-06),(Vehicles4↦4.863088634010637E-06),(Vehicles5↦4.863088634010637E-06)}",
        "VehiclesX": "{(EgoVehicle↦200.0),(Vehicles2↦0.9005345404148102),(Vehicles3↦-9.76513996720314),(Vehicles4↦64.38912153244019),(Vehicles5↦65.32084941864014)}"
      },
      "probabilisticVariables": null,
      "activating": [
        "SLOWER_32"
      ],
      "activatingOnlyWhenExecuted": true,
      "updating": null,
      "withPredicate": null
    },
    {
      "id": "SLOWER_32",
      "execute": "SLOWER",
      "after": "1000",
      "priority": 0,
      "additionalGuards": null,
      "activationKind": null,
      "fixedVariables": {
        "Crash": "FALSE",
        "PresentVehicles": "{EgoVehicle,Vehicles2,Vehicles3,Vehicles4,Vehicles5}",
        "VehiclesAy": "{(EgoVehicle↦4.564295146280983E-06),(Vehicles2↦-4.564295146280983E-06),(Vehicles3↦-4.564295146280983E-06),(Vehicles4↦-4.564295146280983E-06),(Vehicles5↦5.161882121740291E-06)}",
        "Reward": "0.7020425330916121",
        "VehiclesAx": "{(EgoVehicle↦-0.5050492286682129),(Vehicles2↦0.5280395597219467),(Vehicles3↦0.47605495899915695),(Vehicles4↦0.2633148431777954),(Vehicles5↦1.9894618541002274)}",
        "VehiclesVx": "{(EgoVehicle↦20.076594352722168),(Vehicles2↦-0.949276015162468),(Vehicles3↦-0.36722149699926376),(Vehicles4↦-0.6293442100286484),(Vehicles5↦0.8392271399497986)}",
        "VehiclesY": "{(EgoVehicle↦4.0000001192092896),(Vehicles2↦3.999999761581421),(Vehicles3↦-4.0000001192092896),(Vehicles4↦3.999999761581421),(Vehicles5↦-1.0296075458882115E-07)}",
        "VehiclesVy": "{(EgoVehicle↦-2.9879348772965386E-07),(Vehicles2↦2.9879348772965386E-07),(Vehicles3↦2.9879348772965386E-07),(Vehicles4↦2.9879348772965386E-07),(Vehicles5↦2.9879348772965386E-07)}",
        "VehiclesX": "{(EgoVehicle↦200.0),(Vehicles2↦-0.2889180323109031),(Vehicles3↦63.7833297252655),(Vehicles4↦64.45552706718445),(Vehicles5↦66.85657501220703)}"
      },
      "probabilisticVariables": null,
      "activating": [
        "FASTER_33"
      ],
      "activatingOnlyWhenExecuted": true,
      "updating": null,
      "withPredicate": null
    },
    {
      "id": "FASTER_33",
      "execute": "FASTER",
      "after": "1000",
      "priority": 0,
      "additionalGuards": null,
      "activationKind": null,
      "fixedVariables": {
        "Crash": "FALSE",
        "PresentVehicles": "{EgoVehicle,Vehicles2,Vehicles3,Vehicles4,Vehicles5}",
        "VehiclesAy": "{(EgoVehicle↦2.8418245534567177E-07),(Vehicles2↦-2.8418245534567177E-07),(Vehicles3↦-2.8418245534567177E-07),(Vehicles4↦-2.8418245534567177E-07),(Vehicles5↦3.1340452011363595E-07)}",
        "Reward": "0.8160440098447116",
        "VehiclesAx": "{(EgoVehicle↦4.275054931640625),(Vehicles2↦-4.252678826451302),(Vehicles3↦-4.255780018866062),(Vehicles4↦-4.258747175335884),(Vehicles5↦-4.28865373134613)}",
        "VehiclesVx": "{(EgoVehicle↦24.351649284362793),(Vehicles2↦-5.2019548416137695),(Vehicles3↦-4.623001515865326),(Vehicles4↦-4.8880913853645325),(Vehicles5↦-3.449426591396332)}",
        "VehiclesY": "{(EgoVehicle↦4.0000001192092896),(Vehicles2↦4.0000001192092896),(Vehicles3↦-4.0000001192092896),(Vehicles4↦4.0000001192092896),(Vehicles5↦-4.4118948494542565E-09)}",
        "VehiclesVy": "{(EgoVehicle↦-1.4611032383982092E-08),(Vehicles2↦1.4611032383982092E-08),(Vehicles3↦1.4611032383982092E-08),(Vehicles4↦1.4611032383982092E-08),(Vehicles5↦1.4611032383982092E-08)}",
        "VehiclesX": "{(EgoVehicle↦200.0),(Vehicles2↦-3.587568923830986),(Vehicles3↦61.06553077697754),(Vehicles4↦61.47429943084717),(Vehicles5↦65.33181071281433)}"
      },
      "probabilisticVariables": null,
      "activating": [
        "LANE_LEFT_34"
      ],
      "activatingOnlyWhenExecuted": true,
      "updating": null,
      "withPredicate": null
    },
    {
      "id": "LANE_LEFT_34",
      "execute": "LANE_LEFT",
      "after": "1000",
      "priority": 0,
      "additionalGuards": null,
      "activationKind": null,
      "fixedVariables": {
        "Crash": "FALSE",
        "PresentVehicles": "{EgoVehicle,Vehicles2,Vehicles3,Vehicles4,Vehicles5}",
        "VehiclesAy": "{(EgoVehicle↦-1.0673459473173352),(Vehicles2↦1.0673459473173352),(Vehicles3↦1.0673459473173352),(Vehicles4↦1.0673459473173352),(Vehicles5↦1.0673459765394)}",
        "Reward": "0.7971132666249394",
        "VehiclesAx": "{(EgoVehicle↦0.5400991439819336),(Vehicles2↦-0.5182677507400513),(Vehicles3↦-0.521828830242157),(Vehicles4↦-0.5234280228614807),(Vehicles5↦-0.5514910817146301)}",
        "VehiclesVx": "{(EgoVehicle↦24.891748428344727),(Vehicles2↦-5.720222592353821),(Vehicles3↦-5.144830346107483),(Vehicles4↦-5.411519408226013),(Vehicles5↦-4.000917673110962)}",
        "VehiclesY": "{(EgoVehicle↦0.33523622900247574),(Vehicles2↦7.664763450622559),(Vehicles3↦-0.33523622900247574),(Vehicles4↦7.664763450622559),(Vehicles5↦3.6647636890411377)}",
        "VehiclesVy": "{(EgoVehicle↦-1.0673459619283676),(Vehicles2↦1.0673459619283676),(Vehicles3↦1.0673459619283676),(Vehicles4↦1.0673459619283676),(Vehicles5↦1.0673459619283676)}",
        "VehiclesX": "{(EgoVehicle↦200.0),(Vehicles2↦-8.765330165624619),(Vehicles3↦56.465333700180054),(Vehicles4↦56.60827159881592),(Vehicles5↦61.893075704574585)}"
      },
      "probabilisticVariables": null,
      "activating": [
        "IDLE_35"
      ],
      "activatingOnlyWhenExecuted": true,
      "updating": null,
      "withPredicate": null
    },
    {
      "id": "IDLE_35",
      "execute": "IDLE",
      "after": "1000",
      "priority": 0,
      "additionalGuards": null,
      "activationKind": null,
      "fixedVariables": {
        "Crash": "FALSE",
        "PresentVehicles": "{EgoVehicle,Vehicles2,Vehicles3,Vehicles4,Vehicles5}",
        "VehiclesAy": "{(EgoVehicle↦1.029823967255652),(Vehicles2↦-1.029823967255652),(Vehicles3↦-1.029823967255652),(Vehicles4↦-1.029823967255652),(Vehicles5↦1.1048679566010833)}",
        "Reward": "0.7996994254611526",
        "VehiclesAx": "{(EgoVehicle↦0.09697914123535156),(Vehicles2↦0.22865831851959229),(Vehicles3↦-0.07962405681610107),(Vehicles4↦1.304265558719635),(Vehicles5↦-1.1887997388839722)}",
        "VehiclesVx": "{(EgoVehicle↦24.988727569580078),(Vehicles2↦-5.4915642738342285),(Vehicles3↦-5.224454402923584),(Vehicles4↦-4.107253849506378),(Vehicles5↦-5.189717411994934)}",
        "VehiclesY": "{(EgoVehicle↦0.011317749274894595),(Vehicles2↦7.98868203163147),(Vehicles3↦-0.011317749274894595),(Vehicles4↦3.988682270050049),(Vehicles5↦7.98868203163147)}",
        "VehiclesVy": "{(EgoVehicle↦-0.037521994672715664),(Vehicles2↦0.037521994672715664),(Vehicles3↦0.037521994672715664),(Vehicles4↦0.037521994672715664),(Vehicles5↦0.037521994672715664)}",
        "VehiclesX": "{(EgoVehicle↦200.0),(Vehicles2↦51.143354177474976),(Vehicles3↦51.267361640930176),(Vehicles4↦57.8281044960022),(Vehicles5↦121.83810472488403)}"
      },
      "probabilisticVariables": null,
      "activating": [
        "LANE_RIGHT_36"
      ],
      "activatingOnlyWhenExecuted": true,
      "updating": null,
      "withPredicate": null
    },
    {
      "id": "LANE_RIGHT_36",
      "execute": "LANE_RIGHT",
      "after": "1000",
      "priority": 0,
      "additionalGuards": null,
      "activationKind": null,
      "fixedVariables": {
        "Crash": "FALSE",
        "PresentVehicles": "{EgoVehicle,Vehicles2,Vehicles3,Vehicles4,Vehicles5}",
        "VehiclesAy": "{(EgoVehicle↦1.1157706147059798),(Vehicles2↦-1.1157706147059798),(Vehicles3↦-1.1157706147059798),(Vehicles4↦-1.1157706147059798),(Vehicles5↦-1.0407266253605485)}",
        "Reward": "0.8326734609446645",
        "VehiclesAx": "{(EgoVehicle↦-0.013473033905029297),(Vehicles2↦0.03059566020965576),(Vehicles3↦0.030002593994140625),(Vehicles4↦0.005994141101837158),(Vehicles5↦0.04393339157104492)}",
        "VehiclesVx": "{(EgoVehicle↦24.97525453567505),(Vehicles2↦-5.460968613624573),(Vehicles3↦-5.194451808929443),(Vehicles4↦-4.101259708404541),(Vehicles5↦-5.145784020423889)}",
        "VehiclesY": "{(EgoVehicle↦3.6603991985321045),(Vehicles2↦4.339601039886475),(Vehicles3↦-3.6603991985321045),(Vehicles4↦0.33960092067718506),(Vehicles5↦4.339601039886475)}",
        "VehiclesVy": "{(EgoVehicle↦1.0782486200332642),(Vehicles2↦-1.0782486200332642),(Vehicles3↦-1.0782486200332642),(Vehicles4↦-1.0782486200332642),(Vehicles5↦-1.0782486200332642)}",
        "VehiclesX": "{(EgoVehicle↦200.0),(Vehicles2↦45.971229672431946),(Vehicles3↦46.36218249797821),(Vehicles4↦54.030317068099976),(Vehicles5↦116.97330474853516)}"
      },
      "probabilisticVariables": null,
      "activating": [
        "LANE_RIGHT_37"
      ],
      "activatingOnlyWhenExecuted": true,
      "updating": null,
      "withPredicate": null
    },
    {
      "id": "LANE_RIGHT_37",
      "execute": "LANE_RIGHT",
      "after": "1000",
      "priority": 0,
      "additionalGuards": null,
      "activationKind": null,
      "fixedVariables": {
        "Crash": "FALSE",
        "PresentVehicles": "{EgoVehicle,Vehicles2,Vehicles3,Vehicles4,Vehicles5}",
        "VehiclesAy": "{(EgoVehicle↦0.03897950053215027),(Vehicles2↦-0.03897950053215027),(Vehicles3↦-0.03897950053215027),(Vehicles4↦-0.03897950053215027),(Vehicles5↦-2.1954767405986786)}",
        "Reward": "0.8659954234207813",
        "VehiclesAx": "{(EgoVehicle↦-0.0004267692565917969),(Vehicles2↦0.017662644386291504),(Vehicles3↦0.016202330589294434),(Vehicles4↦-0.005335807800292969),(Vehicles5↦0.02935051918029785)}",
        "VehiclesVx": "{(EgoVehicle↦24.974827766418457),(Vehicles2↦-5.443305969238281),(Vehicles3↦-5.178249478340149),(Vehicles4↦-4.106595516204834),(Vehicles5↦-5.116433501243591)}",
        "VehiclesY": "{(EgoVehicle↦7.648664474487305),(Vehicles2↦0.3513358533382416),(Vehicles3↦-7.648664474487305),(Vehicles4↦-3.6486639976501465),(Vehicles5↦0.3513358533382416)}",
        "VehiclesVy": "{(EgoVehicle↦1.1172281205654144),(Vehicles2↦-1.1172281205654144),(Vehicles3↦-1.1172281205654144),(Vehicles4↦-1.1172281205654144),(Vehicles5↦-1.1172281205654144)}",
        "VehiclesX": "{(EgoVehicle↦200.0),(Vehicles2↦40.87219834327698),(Vehicles3↦41.52914583683014),(Vehicles4↦50.28167366981506),(Vehicles5↦112.19425201416016)}"
      },
      "probabilisticVariables": null,
      "activating": [
        "IDLE_38"
      ],
      "activatingOnlyWhenExecuted": true,
      "updating": null,
      "withPredicate": null
    },
    {
      "id": "IDLE_38",
      "execute": "IDLE",
      "after": "1000",
      "priority": 0,
      "additionalGuards": null,
      "activationKind": null,
      "fixedVariables": {
        "Crash": "FALSE",
        "PresentVehicles": "{EgoVehicle,Vehicles2,Vehicles3,Vehicles4,Vehicles5}",
        "VehiclesAy": "{(EgoVehicle↦-1.0779332695528865),(Vehicles2↦1.0779332695528865),(Vehicles3↦1.0779332695528865),(Vehicles4↦1.0779332695528865),(Vehicles5↦-1.1565229715779424)}",
        "Reward": "0.8666651584591968",
        "VehiclesAx": "{(EgoVehicle↦0.025115013122558594),(Vehicles2↦-0.007826685905456543),(Vehicles3↦-0.010025501251220703),(Vehicles4↦-0.02931267023086548),(Vehicles5↦0.0023883581161499023)}",
        "VehiclesVx": "{(EgoVehicle↦24.999942779541016),(Vehicles2↦-5.451132655143738),(Vehicles3↦-5.18827497959137),(Vehicles4↦-4.1359081864356995),(Vehicles5↦-5.114045143127441)}",
        "VehiclesY": "{(EgoVehicle↦7.988144874572754),(Vehicles2↦0.01185480086132884),(Vehicles3↦-7.988144874572754),(Vehicles4↦-3.988145112991333),(Vehicles5↦0.01185480086132884)}",
        "VehiclesVy": "{(EgoVehicle↦0.03929485101252794),(Vehicles2↦-0.03929485101252794),(Vehicles3↦-0.03929485101252794),(Vehicles4↦-0.03929485101252794),(Vehicles5↦-0.03929485101252794)}",
        "VehiclesX": "{(EgoVehicle↦200.0),(Vehicles2↦35.41469871997833),(Vehicles3↦36.33587658405304),(Vehicles4↦46.1521714925766),(Vehicles5↦107.06782341003418)}"
      },
      "probabilisticVariables": null,
      "activating": [
        "IDLE_39"
      ],
      "activatingOnlyWhenExecuted": true,
      "updating": null,
      "withPredicate": null
    },
    {
      "id": "IDLE_39",
      "execute": "IDLE",
      "after": "1000",
      "priority": 0,
      "additionalGuards": null,
      "activationKind": null,
      "fixedVariables": {
        "Crash": "FALSE",
        "PresentVehicles": "{EgoVehicle,Vehicles2,Vehicles3,Vehicles4,Vehicles5}",
        "VehiclesAy": "{(EgoVehicle↦-0.03804888314334676),(Vehicles2↦0.03804888314334676),(Vehicles3↦0.03804888314334676),(Vehicles4↦0.03804888314334676),(Vehicles5↦-0.04054081888170913)}",
        "Reward": "0.8666665756732354",
        "VehiclesAx": "{(EgoVehicle↦5.4836273193359375E-05),(Vehicles2↦0.017232894897460938),(Vehicles3↦0.014409422874450684),(Vehicles4↦-0.0028309226036071777),(Vehicles5↦0.026134252548217773)}",
        "VehiclesVx": "{(EgoVehicle↦24.99999761581421),(Vehicles2↦-5.433899760246277),(Vehicles3↦-5.173865556716919),(Vehicles4↦-4.138739109039307),(Vehicles5↦-5.087910890579224)}",
        "VehiclesY": "{(EgoVehicle↦7.999626159667969),(Vehicles2↦0.0003740633837878704),(Vehicles3↦-7.999626159667969),(Vehicles4↦-3.999626040458679),(Vehicles5↦0.0003740633837878704)}",
        "VehiclesVy": "{(EgoVehicle↦0.001245967869181186),(Vehicles2↦-0.001245967869181186),(Vehicles3↦-0.001245967869181186),(Vehicles4↦-0.001245967869181186),(Vehicles5↦-0.001245967869181186)}",
        "VehiclesX": "{(EgoVehicle↦200.0),(Vehicles2↦29.97044324874878),(Vehicles3↦31.153395771980286),(Vehicles4↦42.01500415802002),(Vehicles5↦101.96431875228882)}"
      },
      "probabilisticVariables": null,
      "activating": [
        "SLOWER_40"
      ],
      "activatingOnlyWhenExecuted": true,
      "updating": null,
      "withPredicate": null
    },
    {
      "id": "SLOWER_40",
      "execute": "SLOWER",
      "after": "1000",
      "priority": 0,
      "additionalGuards": null,
      "activationKind": null,
      "fixedVariables": {
        "Crash": "FALSE",
        "PresentVehicles": "{EgoVehicle,Vehicles2,Vehicles3,Vehicles4,Vehicles5}",
        "VehiclesAy": "{(EgoVehicle↦-0.0011952731028941344),(Vehicles2↦0.0011952731028941344),(Vehicles3↦0.0011952731028941344),(Vehicles4↦0.0011952731028941344),(Vehicles5↦-0.0012966626354682376)}",
        "Reward": "0.7508916204978137",
        "VehiclesAx": "{(EgoVehicle↦-4.341561794281006),(Vehicles2↦4.358798861503601),(Vehicles3↦4.355449825525284),(Vehicles4↦4.340065736323595),(Vehicles5↦4.366525933146477)}",
        "VehiclesVx": "{(EgoVehicle↦20.658435821533203),(Vehicles2↦-1.0751008987426758),(Vehicles3↦-0.8184157311916351),(Vehicles4↦0.2013266272842884),(Vehicles5↦-0.7213849574327469)}",
        "VehiclesY": "{(EgoVehicle↦7.9999823570251465),(Vehicles2↦1.7523211681691464E-05),(Vehicles3↦-7.9999823570251465),(Vehicles4↦-3.9999825954437256),(Vehicles5↦1.7523211681691464E-05)}",
        "VehiclesVy": "{(EgoVehicle↦5.069476628705161E-05),(Vehicles2↦-5.069476628705161E-05),(Vehicles3↦-5.069476628705161E-05),(Vehicles4↦-5.069476628705161E-05),(Vehicles5↦-5.069476628705161E-05)}",
        "VehiclesX": "{(EgoVehicle↦200.0),(Vehicles2↦26.938503980636597),(Vehicles3↦28.380191326141357),(Vehicles4↦40.27062952518463),(Vehicles5↦99.28154945373535)}"
      },
      "probabilisticVariables": null,
      "activating": [
        "SLOWER_41"
      ],
      "activatingOnlyWhenExecuted": true,
      "updating": null,
      "withPredicate": null
    },
    {
      "id": "SLOWER_41",
      "execute": "SLOWER",
      "after": "1000",
      "priority": 0,
      "additionalGuards": null,
      "activationKind": null,
      "fixedVariables": {
        "Crash": "FALSE",
        "PresentVehicles": "{EgoVehicle,Vehicles2,Vehicles3,Vehicles4,Vehicles5}",
        "VehiclesAy": "{(EgoVehicle↦-4.758519565939423E-05),(Vehicles2↦4.758519565939423E-05),(Vehicles3↦4.758519565939423E-05),(Vehicles4↦4.758519565939423E-05),(Vehicles5↦-5.380433691470898E-05)}",
        "Reward": "0.7356455357584974",
        "VehiclesAx": "{(EgoVehicle↦-0.5717277526855469),(Vehicles2↦0.588877834379673),(Vehicles3↦0.5850911140441895),(Vehicles4↦0.5713866464793682),(Vehicles5↦0.5955559946596622)}",
        "VehiclesVx": "{(EgoVehicle↦20.086708068847656),(Vehicles2↦-0.4862230643630028),(Vehicles3↦-0.23332461714744568),(Vehicles4↦0.7727132737636566),(Vehicles5↦-0.12582896277308464)}",
        "VehiclesY": "{(EgoVehicle↦7.9999988079071045),(Vehicles2↦1.0716414635680849E-06),(Vehicles3↦-7.9999988079071045),(Vehicles4↦-3.9999990463256836),(Vehicles5↦1.0716414635680849E-06)}",
        "VehiclesVy": "{(EgoVehicle↦3.1095706276573765E-06),(Vehicles2↦-3.1095706276573765E-06),(Vehicles3↦-3.1095706276573765E-06),(Vehicles4↦-3.1095706276573765E-06),(Vehicles5↦-3.1095706276573765E-06)}",
        "VehiclesX": "{(EgoVehicle↦200.0),(Vehicles2↦26.185670495033264),(Vehicles3↦27.882561087608337),(Vehicles4↦40.78713059425354),(Vehicles5↦98.885178565979)}"
      },
      "probabilisticVariables": null,
      "activating": [
        "SLOWER_42"
      ],
      "activatingOnlyWhenExecuted": true,
      "updating": null,
      "withPredicate": null
    },
    {
      "id": "SLOWER_42",
      "execute": "SLOWER",
      "after": "1000",
      "priority": 0,
      "additionalGuards": null,
      "activationKind": null,
      "fixedVariables": {
        "Crash": "FALSE",
        "PresentVehicles": "{EgoVehicle,Vehicles2,Vehicles3,Vehicles4,Vehicles5}",
        "VehiclesAy": "{(EgoVehicle↦-2.9163381931596177E-06),(Vehicles2↦2.9163381931596177E-06),(Vehicles3↦2.9163381931596177E-06),(Vehicles4↦2.9163381931596177E-06),(Vehicles5↦-3.302803062155135E-06)}",
        "Reward": "0.7336378208954958",
        "VehiclesAx": "{(EgoVehicle↦-0.07529020309448242),(Vehicles2↦0.09231701493263245),(Vehicles3↦0.08816924877464771),(Vehicles4↦0.07598131895065308),(Vehicles5↦0.09805704234167933)}",
        "VehiclesVx": "{(EgoVehicle↦20.011417865753174),(Vehicles2↦-0.39390604943037033),(Vehicles3↦-0.14515536837279797),(Vehicles4↦0.8486945927143097),(Vehicles5↦-0.027771920431405306)}",
        "VehiclesY": "{(EgoVehicle↦8.000000238418579),(Vehicles2↦6.653838013903624E-08),(Vehicles3↦-8.000000238418579),(Vehicles4↦-3.999999761581421),(Vehicles5↦6.653838013903624E-08)}",
        "VehiclesVy": "{(EgoVehicle↦1.9323243449775873E-07),(Vehicles2↦-1.9323243449775873E-07),(Vehicles3↦-1.9323243449775873E-07),(Vehicles4↦-1.9323243449775873E-07),(Vehicles5↦-1.9323243449775873E-07)}",
        "VehiclesX": "{(EgoVehicle↦200.0),(Vehicles2↦25.74780583381653),(Vehicles3↦27.695956826210022),(Vehicles4↦41.601577401161194),(Vehicles5↦98.81007075309753)}"
      },
      "probabilisticVariables": null,
      "activating": [
        "SLOWER_43"
      ],
      "activatingOnlyWhenExecuted": true,
      "updating": null,
      "withPredicate": null
    },
    {
      "id": "SLOWER_43",
      "execute": "SLOWER",
      "after": "1000",
      "priority": 0,
      "additionalGuards": null,
      "activationKind": null,
      "fixedVariables": {
        "Crash": "FALSE",
        "PresentVehicles": "{EgoVehicle,Vehicles2,Vehicles3,Vehicles4,Vehicles5}",
        "VehiclesAy": "{(EgoVehicle↦-1.8121150802130614E-07),(Vehicles2↦1.8121151690309034E-07),(Vehicles3↦1.8121151690309034E-07),(Vehicles4↦1.8121151690309034E-07),(Vehicles5↦-2.0525335209242712E-07)}",
        "Reward": "0.7333734304608609",
        "VehiclesAx": "{(EgoVehicle↦-0.009913444519042969),(Vehicles2↦0.0267917662858963),(Vehicles3↦0.022350121289491653),(Vehicles4↦0.011528655886650085),(Vehicles5↦0.031692468328401446)}",
        "VehiclesVx": "{(EgoVehicle↦20.00150442123413),(Vehicles2↦-0.36711428314447403),(Vehicles3↦-0.12280524708330631),(Vehicles4↦0.8602232486009598),(Vehicles5↦0.0039205478969961405)}",
        "VehiclesY": "{(EgoVehicle↦8.000000238418579),(Vehicles2↦4.138867915060018E-09),(Vehicles3↦-8.000000238418579),(Vehicles4↦-4.0000001192092896),(Vehicles5↦4.138867915060018E-09)}",
        "VehiclesVy": "{(EgoVehicle↦1.2020926476452587E-08),(Vehicles2↦-1.202091759466839E-08),(Vehicles3↦-1.202091759466839E-08),(Vehicles4↦-1.202091759466839E-08),(Vehicles5↦-1.202091759466839E-08)}",
        "VehiclesX": "{(EgoVehicle↦200.0),(Vehicles2↦25.366133451461792),(Vehicles3↦27.561280131340027),(Vehicles4↦42.45631694793701),(Vehicles5↦98.79655838012695)}"
      },
      "probabilisticVariables": null,
      "activating": [
        "SLOWER_44"
      ],
      "activatingOnlyWhenExecuted": true,
      "updating": null,
      "withPredicate": null
    },
    {
      "id": "SLOWER_44",
      "execute": "SLOWER",
      "after": "1000",
      "priority": 0,
      "additionalGuards": null,
      "activationKind": null,
      "fixedVariables": {
        "Crash": "FALSE",
        "PresentVehicles": "{EgoVehicle,Vehicles2,Vehicles3,Vehicles4,Vehicles5}",
        "VehiclesAy": "{(EgoVehicle↦-1.1272991429223111E-08),(Vehicles2↦1.1272982547438914E-08),(Vehicles3↦1.1272982547438914E-08),(Vehicles4↦1.1273000311007308E-08),(Vehicles5↦-1.2768852641897865E-08)}",
        "Reward": "0.7333386136135016",
        "VehiclesAx": "{(EgoVehicle↦-0.0013065338134765625),(Vehicles2↦0.018008127808570862),(Vehicles3↦0.013331472873687744),(Vehicles4↦0.0037385523319244385),(Vehicles5↦0.022157548228278756)}",
        "VehiclesVx": "{(EgoVehicle↦20.000197887420654),(Vehicles2↦-0.34910615533590317),(Vehicles3↦-0.10947377420961857),(Vehicles4↦0.8639618009328842),(Vehicles5↦0.026078096125274897)}",
        "VehiclesY": "{(EgoVehicle↦8.000000238418579),(Vehicles2↦2.575113455804967E-10),(Vehicles3↦-8.000000238418579),(Vehicles4↦-4.0000001192092896),(Vehicles5↦2.575113455804967E-10)}",
        "VehiclesVy": "{(EgoVehicle↦7.479350472294755E-10),(Vehicles2↦-7.479350472294755E-10),(Vehicles3↦-7.479350472294755E-10),(Vehicles4↦-7.479172836610815E-10),(Vehicles5↦-7.479350472294755E-10)}",
        "VehiclesX": "{(EgoVehicle↦200.0),(Vehicles2↦25.006434321403503),(Vehicles3↦27.444037795066833),(Vehicles4↦43.31817328929901),(Vehicles5↦98.80961179733276)}"
      },
      "probabilisticVariables": null,
      "activating": [
        "SLOWER_45"
      ],
      "activatingOnlyWhenExecuted": true,
      "updating": null,
      "withPredicate": null
    },
    {
      "id": "SLOWER_45",
      "execute": "SLOWER",
      "after": "1000",
      "priority": 0,
      "additionalGuards": null,
      "activationKind": null,
      "fixedVariables": {
        "Crash": "FALSE",
        "PresentVehicles": "{EgoVehicle,Vehicles2,Vehicles3,Vehicles4,Vehicles5}",
        "VehiclesAy": "{(EgoVehicle↦-7.014122616055829E-10),(Vehicles2↦7.014122616055829E-10),(Vehicles3↦7.014122616055829E-10),(Vehicles4↦7.013944980371889E-10),(Vehicles5↦-7.94457832853368E-10)}",
        "Reward": "0.73333402867887",
        "VehiclesAx": "{(EgoVehicle↦-0.000171661376953125),(Vehicles2↦0.016679875552654266),(Vehicles3↦0.011819535866379738),(Vehicles4↦0.003329142928123474),(Vehicles5↦0.020156444516032934)}",
        "VehiclesVx": "{(EgoVehicle↦20.0000262260437),(Vehicles2↦-0.3324262797832489),(Vehicles3↦-0.09765423834323883),(Vehicles4↦0.8672909438610077),(Vehicles5↦0.04623454064130783)}",
        "VehiclesY": "{(EgoVehicle↦8.000000238418579),(Vehicles2↦1.602185051297056E-11),(Vehicles3↦-8.000000238418579),(Vehicles4↦-4.0000001192092896),(Vehicles5↦1.602185051297056E-11)}",
        "VehiclesVy": "{(EgoVehicle↦4.652278562389256E-11),(Vehicles2↦-4.652278562389256E-11),(Vehicles3↦-4.652278562389256E-11),(Vehicles4↦-4.652278562389256E-11),(Vehicles5↦-4.652278562389256E-11)}",
        "VehiclesX": "{(EgoVehicle↦200.0),(Vehicles2↦24.66404139995575),(Vehicles3↦27.3393452167511),(Vehicles4↦44.18343901634216),(Vehicles5↦98.84384870529175)}"
      },
      "probabilisticVariables": null,
      "activating": [
        "SLOWER_46"
      ],
      "activatingOnlyWhenExecuted": true,
      "updating": null,
      "withPredicate": null
    },
    {
      "id": "SLOWER_46",
      "execute": "SLOWER",
      "after": "1000",
      "priority": 0,
      "additionalGuards": null,
      "activationKind": null,
      "fixedVariables": {
        "Crash": "FALSE",
        "PresentVehicles": "{EgoVehicle,Vehicles2,Vehicles3,Vehicles4,Vehicles5}",
        "VehiclesAy": "{(EgoVehicle↦-4.362732397567015E-11),(Vehicles2↦4.362732397567015E-11),(Vehicles3↦4.362732397567015E-11),(Vehicles4↦4.362732397567015E-11),(Vehicles5↦-4.941824727211497E-11)}",
        "Reward": "0.7333334249014699",
        "VehiclesAx": "{(EgoVehicle↦-2.384185791015625E-05),(Vehicles2↦0.01631956547498703),(Vehicles3↦0.011320393532514572),(Vehicles4↦0.0038173049688339233),(Vehicles5↦0.019193338230252266)}",
        "VehiclesVx": "{(EgoVehicle↦20.00000238418579),(Vehicles2↦-0.31610671430826187),(Vehicles3↦-0.08633384481072426),(Vehicles4↦0.8711082488298416),(Vehicles5↦0.0654278788715601)}",
        "VehiclesY": "{(EgoVehicle↦8.000000238418579),(Vehicles2↦9.965361869035405E-13),(Vehicles3↦-8.000000238418579),(Vehicles4↦-4.0000001192092896),(Vehicles5↦9.965361869035405E-13)}",
        "VehiclesVy": "{(EgoVehicle↦2.8954616482224083E-12),(Vehicles2↦-2.8954616482224083E-12),(Vehicles3↦-2.8954616482224083E-12),(Vehicles4↦-2.8954616482224083E-12),(Vehicles5↦-2.8954616482224083E-12)}",
        "VehiclesX": "{(EgoVehicle↦200.0),(Vehicles2↦24.338164925575256),(Vehicles3↦27.246251702308655),(Vehicles4↦45.05221247673035),(Vehicles5↦98.89782667160034)}"
      },
      "probabilisticVariables": null,
      "activating": [
        "SLOWER_47"
      ],
      "activatingOnlyWhenExecuted": true,
      "updating": null,
      "withPredicate": null
    },
    {
      "id": "SLOWER_47",
      "execute": "SLOWER",
      "after": "1000",
      "priority": 0,
      "additionalGuards": null,
      "activationKind": null,
      "fixedVariables": {
        "Crash": "FALSE",
        "PresentVehicles": "{EgoVehicle,Vehicles2,Vehicles3,Vehicles4,Vehicles5}",
        "VehiclesAy": "{(EgoVehicle↦-2.7178259642823832E-12),(Vehicles2↦2.708944180085382E-12),(Vehicles3↦2.708944180085382E-12),(Vehicles4↦2.7267077484793845E-12),(Vehicles5↦-3.0819791163594346E-12)}",
        "Reward": "0.7333333453916887",
        "VehiclesAx": "{(EgoVehicle↦-2.384185791015625E-06),(Vehicles2↦0.016075484454631805),(Vehicles3↦0.01097655389457941),(Vehicles4↦0.004355832934379578),(Vehicles5↦0.018409062176942825)}",
        "VehiclesVx": "{(EgoVehicle↦20.0),(Vehicles2↦-0.30003122985363007),(Vehicles3↦-0.07535729091614485),(Vehicles4↦0.8754640817642212),(Vehicles5↦0.08383694104850292)}",
        "VehiclesY": "{(EgoVehicle↦8.000000238418579),(Vehicles2↦6.394884621840902E-14),(Vehicles3↦-8.000000238418579),(Vehicles4↦-4.0000001192092896),(Vehicles5↦6.394884621840902E-14)}",
        "VehiclesVy": "{(EgoVehicle↦1.7763568394002505E-13),(Vehicles2↦-1.865174681370263E-13),(Vehicles3↦-1.865174681370263E-13),(Vehicles4↦-1.687538997430238E-13),(Vehicles5↦-1.865174681370263E-13)}",
        "VehiclesX": "{(EgoVehicle↦200.0),(Vehicles2↦24.028506875038147),(Vehicles3↦27.164334058761597),(Vehicles4↦45.925021171569824),(Vehicles5↦98.97067546844482)}"
      },
      "probabilisticVariables": null,
      "activating": [
        "SLOWER_48"
      ],
      "activatingOnlyWhenExecuted": true,
      "updating": null,
      "withPredicate": null
    },
    {
      "id": "SLOWER_48",
      "execute": "SLOWER",
      "after": "1000",
      "priority": 0,
      "additionalGuards": null,
      "activationKind": null,
      "fixedVariables": {
        "Crash": "FALSE",
        "PresentVehicles": "{EgoVehicle,Vehicles2,Vehicles3,Vehicles4,Vehicles5}",
        "VehiclesAy": "{(EgoVehicle↦-1.5987211554602254E-13),(Vehicles2↦1.687538997430238E-13),(Vehicles3↦1.687538997430238E-13),(Vehicles4↦1.509903313490213E-13),(Vehicles5↦-2.042810365310288E-13)}",
        "Reward": "0.733333334921265",
        "VehiclesAx": "{(EgoVehicle↦0.0),(Vehicles2↦0.01583784818649292),(Vehicles3↦0.010673059150576591),(Vehicles4↦0.004839301109313965),(Vehicles5↦0.017687128856778145)}",
        "VehiclesVx": "{(EgoVehicle↦20.0),(Vehicles2↦-0.28419338166713715),(Vehicles3↦-0.06468423176556826),(Vehicles4↦0.8803033828735352),(Vehicles5↦0.10152406990528107)}",
        "VehiclesY": "{(EgoVehicle↦8.000000238418579),(Vehicles2↦2.6645352591003757E-15),(Vehicles3↦-8.000000238418579),(Vehicles4↦-4.0000001192092896),(Vehicles5↦2.6645352591003757E-15)}",
        "VehiclesVy": "{(EgoVehicle↦1.7763568394002505E-14),(Vehicles2↦-1.7763568394002505E-14),(Vehicles3↦-1.7763568394002505E-14),(Vehicles4↦-1.7763568394002505E-14),(Vehicles5↦-1.7763568394002505E-14)}",
        "VehiclesX": "{(EgoVehicle↦200.0),(Vehicles2↦23.73483031988144),(Vehicles3↦27.0932674407959),(Vehicles4↦46.80238366127014),(Vehicles5↦99.06164407730103)}"
      },
      "probabilisticVariables": null,
      "activating": [
        "SLOWER_49"
      ],
      "activatingOnlyWhenExecuted": true,
      "updating": null,
      "withPredicate": null
    },
    {
      "id": "SLOWER_49",
      "execute": "SLOWER",
      "after": "1000",
      "priority": 0,
      "additionalGuards": null,
      "activationKind": null,
      "fixedVariables": {
        "Crash": "FALSE",
        "PresentVehicles": "{EgoVehicle,Vehicles2,Vehicles3,Vehicles4,Vehicles5}",
        "VehiclesAy": "{(EgoVehicle↦-1.7763568394002505E-14),(Vehicles2↦1.7763568394002505E-14),(Vehicles3↦1.7763568394002505E-14),(Vehicles4↦1.7763568394002505E-14),(Vehicles5↦-1.7763568394002505E-14)}",
        "Reward": "0.7333333335424438",
        "VehiclesAx": "{(EgoVehicle↦0.0),(Vehicles2↦0.015594083815813065),(Vehicles3↦0.010392898693680763),(Vehicles4↦0.0052597373723983765),(Vehicles5↦0.01700914464890957)}",
        "VehiclesVx": "{(EgoVehicle↦20.0),(Vehicles2↦-0.2685992978513241),(Vehicles3↦-0.05429133307188749),(Vehicles4↦0.8855631202459335),(Vehicles5↦0.11853321455419064)}",
        "VehiclesY": "{(EgoVehicle↦8.000000238418579),(Vehicles2↦0.0),(Vehicles3↦-8.000000238418579),(Vehicles4↦-4.0000001192092896),(Vehicles5↦0.0)}",
        "VehiclesVy": "{(EgoVehicle↦0.0),(Vehicles2↦0.0),(Vehicles3↦0.0),(Vehicles4↦0.0),(Vehicles5↦0.0)}",
        "VehiclesX": "{(EgoVehicle↦200.0),(Vehicles2↦23.456893861293793),(Vehicles3↦27.0327627658844),(Vehicles4↦47.68476188182831),(Vehicles5↦99.17002320289612)}"
      },
      "probabilisticVariables": null,
      "activating": [
        "SLOWER_50"
      ],
      "activatingOnlyWhenExecuted": true,
      "updating": null,
      "withPredicate": null
    },
    {
      "id": "SLOWER_50",
      "execute": "SLOWER",
      "after": "1000",
      "priority": 0,
      "additionalGuards": null,
      "activationKind": null,
      "fixedVariables": {
        "Crash": "FALSE",
        "PresentVehicles": "{EgoVehicle,Vehicles2,Vehicles3,Vehicles4,Vehicles5}",
        "VehiclesAy": "{(EgoVehicle↦0.0),(Vehicles2↦0.0),(Vehicles3↦0.0),(Vehicles4↦0.0),(Vehicles5↦0.0)}",
        "Reward": "0.7333333333608705",
        "VehiclesAx": "{(EgoVehicle↦0.0),(Vehicles2↦0.01534435898065567),(Vehicles3↦0.010132179595530033),(Vehicles4↦0.005621239542961121),(Vehicles5↦0.01636996865272522)}",
        "VehiclesVx": "{(EgoVehicle↦20.0),(Vehicles2↦-0.2532549388706684),(Vehicles3↦-0.04415915347635746),(Vehicles4↦0.8911843597888947),(Vehicles5↦0.13490318320691586)}",
        "VehiclesY": "{(EgoVehicle↦8.000000238418579),(Vehicles2↦0.0),(Vehicles3↦-8.000000238418579),(Vehicles4↦-4.0000001192092896),(Vehicles5↦0.0)}",
        "VehiclesVy": "{(EgoVehicle↦0.0),(Vehicles2↦0.0),(Vehicles3↦0.0),(Vehicles4↦0.0),(Vehicles5↦0.0)}",
        "VehiclesX": "{(EgoVehicle↦200.0),(Vehicles2↦23.19445312023163),(Vehicles3↦26.982545852661133),(Vehicles4↦48.5725462436676),(Vehicles5↦99.29515719413757)}"
      },
      "probabilisticVariables": null,
      "activating": [
        "SLOWER_51"
      ],
      "activatingOnlyWhenExecuted": true,
      "updating": null,
      "withPredicate": null
    },
    {
      "id": "SLOWER_51",
      "execute": "SLOWER",
      "after": "1000",
      "priority": 0,
      "additionalGuards": null,
      "activationKind": null,
      "fixedVariables": {
        "Crash": "FALSE",
        "PresentVehicles": "{EgoVehicle,Vehicles2,Vehicles3,Vehicles4,Vehicles5}",
        "VehiclesAy": "{(EgoVehicle↦0.0),(Vehicles2↦0.0),(Vehicles3↦0.0),(Vehicles4↦0.0),(Vehicles5↦0.0)}",
        "Reward": "0.7333333333369597",
        "VehiclesAx": "{(EgoVehicle↦0.0),(Vehicles2↦0.015090089291334152),(Vehicles3↦0.009888899512588978),(Vehicles4↦0.005929246544837952),(Vehicles5↦0.015766434371471405)}",
        "VehiclesVx": "{(EgoVehicle↦20.0),(Vehicles2↦-0.23816484957933426),(Vehicles3↦-0.03427025396376848),(Vehicles4↦0.8971136063337326),(Vehicles5↦0.15066961757838726)}",
        "VehiclesY": "{(EgoVehicle↦8.000000238418579),(Vehicles2↦0.0),(Vehicles3↦-8.000000238418579),(Vehicles4↦-4.0000001192092896),(Vehicles5↦0.0)}",
        "VehiclesVy": "{(EgoVehicle↦0.0),(Vehicles2↦0.0),(Vehicles3↦0.0),(Vehicles4↦0.0),(Vehicles5↦0.0)}",
        "VehiclesX": "{(EgoVehicle↦200.0),(Vehicles2↦22.94725477695465),(Vehicles3↦26.942360401153564),(Vehicles4↦49.46607947349548),(Vehicles5↦99.4364082813263)}"
      },
      "probabilisticVariables": null,
      "activating": [
        "SLOWER_52"
      ],
      "activatingOnlyWhenExecuted": true,
      "updating": null,
      "withPredicate": null
    },
    {
      "id": "SLOWER_52",
      "execute": "SLOWER",
      "after": "1000",
      "priority": 0,
      "additionalGuards": null,
      "activationKind": null,
      "fixedVariables": {
        "Crash": "FALSE",
        "PresentVehicles": "{EgoVehicle,Vehicles2,Vehicles3,Vehicles4,Vehicles5}",
        "VehiclesAy": "{(EgoVehicle↦0.0),(Vehicles2↦0.0),(Vehicles3↦0.0),(Vehicles4↦0.0),(Vehicles5↦0.0)}",
        "Reward": "0.7333333333338109",
        "VehiclesAx": "{(EgoVehicle↦0.0),(Vehicles2↦0.014832783490419388),(Vehicles3↦0.009661437943577766),(Vehicles4↦0.006189271807670593),(Vehicles5↦0.015195896849036217)}",
        "VehiclesVx": "{(EgoVehicle↦20.0),(Vehicles2↦-0.22333206608891487),(Vehicles3↦-0.024608816020190716),(Vehicles4↦0.9033028781414032),(Vehicles5↦0.16586551442742348)}",
        "VehiclesY": "{(EgoVehicle↦8.000000238418579),(Vehicles2↦0.0),(Vehicles3↦-8.000000238418579),(Vehicles4↦-4.0000001192092896),(Vehicles5↦0.0)}",
        "VehiclesVy": "{(EgoVehicle↦0.0),(Vehicles2↦0.0),(Vehicles3↦0.0),(Vehicles4↦0.0),(Vehicles5↦0.0)}",
        "VehiclesX": "{(EgoVehicle↦200.0),(Vehicles2↦22.715042531490326),(Vehicles3↦26.91197097301483),(Vehicles4↦50.36565065383911),(Vehicles5↦99.59320425987244)}"
      },
      "probabilisticVariables": null,
      "activating": [
        "SLOWER_53"
      ],
      "activatingOnlyWhenExecuted": true,
      "updating": null,
      "withPredicate": null
    },
    {
      "id": "SLOWER_53",
      "execute": "SLOWER",
      "after": "1000",
      "priority": 0,
      "additionalGuards": null,
      "activationKind": null,
      "fixedVariables": {
        "Crash": "FALSE",
        "PresentVehicles": "{EgoVehicle,Vehicles2,Vehicles3,Vehicles4,Vehicles5}",
        "VehiclesAy": "{(EgoVehicle↦0.0),(Vehicles2↦0.0),(Vehicles3↦0.0),(Vehicles4↦0.0),(Vehicles5↦0.0)}",
        "Reward": "0.7333333333333963",
        "VehiclesAx": "{(EgoVehicle↦0.0),(Vehicles2↦0.014573764055967331),(Vehicles3↦0.009448368800804019),(Vehicles4↦0.006406083703041077),(Vehicles5↦0.014655981212854385)}",
        "VehiclesVx": "{(EgoVehicle↦20.0),(Vehicles2↦-0.20875830203294754),(Vehicles3↦-0.015160447219386697),(Vehicles4↦0.9097089618444443),(Vehicles5↦0.18052149564027786)}",
        "VehiclesY": "{(EgoVehicle↦8.000000238418579),(Vehicles2↦0.0),(Vehicles3↦-8.000000238418579),(Vehicles4↦-4.0000001192092896),(Vehicles5↦0.0)}",
        "VehiclesVy": "{(EgoVehicle↦0.0),(Vehicles2↦0.0),(Vehicles3↦0.0),(Vehicles4↦0.0),(Vehicles5↦0.0)}",
        "VehiclesX": "{(EgoVehicle↦200.0),(Vehicles2↦22.49756157398224),(Vehicles3↦26.891160011291504),(Vehicles4↦51.27149820327759),(Vehicles5↦99.76497292518616)}"
      },
      "probabilisticVariables": null,
      "activating": [
        "SLOWER_54"
      ],
      "activatingOnlyWhenExecuted": true,
      "updating": null,
      "withPredicate": null
    },
    {
      "id": "SLOWER_54",
      "execute": "SLOWER",
      "after": "1000",
      "priority": 0,
      "additionalGuards": null,
      "activationKind": null,
      "fixedVariables": {
        "Crash": "FALSE",
        "PresentVehicles": "{EgoVehicle,Vehicles2,Vehicles3,Vehicles4,Vehicles5}",
        "VehiclesAy": "{(EgoVehicle↦0.0),(Vehicles2↦0.0),(Vehicles3↦0.0),(Vehicles4↦0.0),(Vehicles5↦0.0)}",
        "Reward": "0.7333333333333415",
        "VehiclesAx": "{(EgoVehicle↦0.0),(Vehicles2↦0.014314092695713043),(Vehicles3↦0.009248414426110685),(Vehicles4↦0.006584078073501587),(Vehicles5↦0.014144480228424072)}",
        "VehiclesVx": "{(EgoVehicle↦20.0),(Vehicles2↦-0.1944442093372345),(Vehicles3↦-0.005912032793276012),(Vehicles4↦0.9162930399179459),(Vehicles5↦0.19466597586870193)}",
        "VehiclesY": "{(EgoVehicle↦8.000000238418579),(Vehicles2↦0.0),(Vehicles3↦-8.000000238418579),(Vehicles4↦-4.0000001192092896),(Vehicles5↦0.0)}",
        "VehiclesVy": "{(EgoVehicle↦0.0),(Vehicles2↦0.0),(Vehicles3↦0.0),(Vehicles4↦0.0),(Vehicles5↦0.0)}",
        "VehiclesX": "{(EgoVehicle↦200.0),(Vehicles2↦22.294549643993378),(Vehicles3↦26.87971293926239),(Vehicles4↦52.18383073806763),(Vehicles5↦99.95118975639343)}"
      },
      "probabilisticVariables": null,
      "activating": [
        "SLOWER_55"
      ],
      "activatingOnlyWhenExecuted": true,
      "updating": null,
      "withPredicate": null
    },
    {
      "id": "SLOWER_55",
      "execute": "SLOWER",
      "after": "1000",
      "priority": 0,
      "additionalGuards": null,
      "activationKind": null,
      "fixedVariables": {
        "Crash": "FALSE",
        "PresentVehicles": "{EgoVehicle,Vehicles2,Vehicles3,Vehicles4,Vehicles5}",
        "VehiclesAy": "{(EgoVehicle↦0.0),(Vehicles2↦0.0),(Vehicles3↦0.0),(Vehicles4↦0.0),(Vehicles5↦0.0)}",
        "Reward": "0.7333333333333344",
        "VehiclesAx": "{(EgoVehicle↦0.0),(Vehicles2↦0.01405477523803711),(Vehicles3↦0.009060411539394408),(Vehicles4↦0.00672757625579834),(Vehicles5↦0.013659466058015823)}",
        "VehiclesVx": "{(EgoVehicle↦20.0),(Vehicles2↦-0.1803894340991974),(Vehicles3↦0.0031483787461183965),(Vehicles4↦0.9230206161737442),(Vehicles5↦0.20832544192671776)}",
        "VehiclesY": "{(EgoVehicle↦8.000000238418579),(Vehicles2↦0.0),(Vehicles3↦-8.000000238418579),(Vehicles4↦-4.0000001192092896),(Vehicles5↦0.0)}",
        "VehiclesVy": "{(EgoVehicle↦0.0),(Vehicles2↦0.0),(Vehicles3↦0.0),(Vehicles4↦0.0),(Vehicles5↦0.0)}",
        "VehiclesX": "{(EgoVehicle↦200.0),(Vehicles2↦22.10574746131897),(Vehicles3↦26.87743902206421),(Vehicles4↦53.102803230285645),(Vehicles5↦100.15136003494263)}"
      },
      "probabilisticVariables": null,
      "activating": [
        "SLOWER_56"
      ],
      "activatingOnlyWhenExecuted": true,
      "updating": null,
      "withPredicate": null
    },
    {
      "id": "SLOWER_56",
      "execute": "SLOWER",
      "after": "1000",
      "priority": 0,
      "additionalGuards": null,
      "activationKind": null,
      "fixedVariables": {
        "Crash": "FALSE",
        "PresentVehicles": "{EgoVehicle,Vehicles2,Vehicles3,Vehicles4,Vehicles5}",
        "VehiclesAy": "{(EgoVehicle↦0.0),(Vehicles2↦0.0),(Vehicles3↦0.0),(Vehicles4↦0.0),(Vehicles5↦0.0)}",
        "Reward": "0.7333333333333334",
        "VehiclesAx": "{(EgoVehicle↦0.0),(Vehicles2↦0.013796575367450714),(Vehicles3↦0.008883312402758747),(Vehicles4↦0.00684008002281189),(Vehicles5↦0.013199057430028915)}",
        "VehiclesVx": "{(EgoVehicle↦20.0),(Vehicles2↦-0.16659285873174667),(Vehicles3↦0.012031691148877144),(Vehicles4↦0.9298606961965561),(Vehicles5↦0.22152449935674667)}",
        "VehiclesY": "{(EgoVehicle↦8.000000238418579),(Vehicles2↦0.0),(Vehicles3↦-8.000000238418579),(Vehicles4↦-4.0000001192092896),(Vehicles5↦0.0)}",
        "VehiclesVy": "{(EgoVehicle↦0.0),(Vehicles2↦0.0),(Vehicles3↦0.0),(Vehicles4↦0.0),(Vehicles5↦0.0)}",
        "VehiclesX": "{(EgoVehicle↦200.0),(Vehicles2↦21.93089723587036),(Vehicles3↦26.884156465530396),(Vehicles4↦54.028552770614624),(Vehicles5↦100.36500692367554)}"
      },
      "probabilisticVariables": null,
      "activating": [
        "SLOWER_57"
      ],
      "activatingOnlyWhenExecuted": true,
      "updating": null,
      "withPredicate": null
    },
    {
      "id": "SLOWER_57",
      "execute": "SLOWER",
      "after": "1000",
      "priority": 0,
      "additionalGuards": null,
      "activationKind": null,
      "fixedVariables": {
        "Crash": "FALSE",
        "PresentVehicles": "{EgoVehicle,Vehicles2,Vehicles3,Vehicles4,Vehicles5}",
        "VehiclesAy": "{(EgoVehicle↦0.0),(Vehicles2↦0.0),(Vehicles3↦0.0),(Vehicles4↦0.0),(Vehicles5↦0.0)}",
        "Reward": "0.7333333333333334",
        "VehiclesAx": "{(EgoVehicle↦0.0),(Vehicles2↦0.013540228828787804),(Vehicles3↦0.008716168813407421),(Vehicles4↦0.0069250911474227905),(Vehicles5↦0.012761708348989487)}",
        "VehiclesVx": "{(EgoVehicle↦20.0),(Vehicles2↦-0.15305262990295887),(Vehicles3↦0.020747859962284565),(Vehicles4↦0.9367857873439789),(Vehicles5↦0.23428620770573616)}",
        "VehiclesY": "{(EgoVehicle↦8.000000238418579),(Vehicles2↦0.0),(Vehicles3↦-8.000000238418579),(Vehicles4↦-4.0000001192092896),(Vehicles5↦0.0)}",
        "VehiclesVy": "{(EgoVehicle↦0.0),(Vehicles2↦0.0),(Vehicles3↦0.0),(Vehicles4↦0.0),(Vehicles5↦0.0)}",
        "VehiclesX": "{(EgoVehicle↦200.0),(Vehicles2↦21.7697411775589),(Vehicles3↦26.899686455726624),(Vehicles4↦54.961174726486206),(Vehicles5↦100.59165954589844)}"
      },
      "probabilisticVariables": null,
      "activating": [
        "SLOWER_58"
      ],
      "activatingOnlyWhenExecuted": true,
      "updating": null,
      "withPredicate": null
    },
    {
      "id": "SLOWER_58",
      "execute": "SLOWER",
      "after": "1000",
      "priority": 0,
      "additionalGuards": null,
      "activationKind": null,
      "fixedVariables": {
        "Crash": "FALSE",
        "PresentVehicles": "{EgoVehicle,Vehicles2,Vehicles3,Vehicles4,Vehicles5}",
        "VehiclesAy": "{(EgoVehicle↦0.0),(Vehicles2↦0.0),(Vehicles3↦0.0),(Vehicles4↦0.0),(Vehicles5↦0.0)}",
        "Reward": "0.7333333333333334",
        "VehiclesAx": "{(EgoVehicle↦0.0),(Vehicles2↦0.013286257162690163),(Vehicles3↦0.008558123372495174),(Vehicles4↦0.006985589861869812),(Vehicles5↦0.012345798313617706)}",
        "VehiclesVx": "{(EgoVehicle↦20.0),(Vehicles2↦-0.1397663727402687),(Vehicles3↦0.02930598333477974),(Vehicles4↦0.9437713772058487),(Vehicles5↦0.24663200601935387)}",
        "VehiclesY": "{(EgoVehicle↦8.000000238418579),(Vehicles2↦0.0),(Vehicles3↦-8.000000238418579),(Vehicles4↦-4.0000001192092896),(Vehicles5↦0.0)}",
        "VehiclesVy": "{(EgoVehicle↦0.0),(Vehicles2↦0.0),(Vehicles3↦0.0),(Vehicles4↦0.0),(Vehicles5↦0.0)}",
        "VehiclesX": "{(EgoVehicle↦200.0),(Vehicles2↦21.62202298641205),(Vehicles3↦26.92387104034424),(Vehicles4↦55.900752544403076),(Vehicles5↦100.83092451095581)}"
      },
      "probabilisticVariables": null,
      "activating": [
        "SLOWER_59"
      ],
      "activatingOnlyWhenExecuted": true,
      "updating": null,
      "withPredicate": null
    },
    {
      "id": "SLOWER_59",
      "execute": "SLOWER",
      "after": "1000",
      "priority": 0,
      "additionalGuards": null,
      "activationKind": null,
      "fixedVariables": {
        "Crash": "FALSE",
        "PresentVehicles": "{EgoVehicle,Vehicles2,Vehicles3,Vehicles4,Vehicles5}",
        "VehiclesAy": "{(EgoVehicle↦0.0),(Vehicles2↦0.0),(Vehicles3↦0.0),(Vehicles4↦0.0),(Vehicles5↦0.0)}",
        "Reward": "0.7333333333333334",
        "VehiclesAx": "{(EgoVehicle↦0.0),(Vehicles2↦0.013035191223025322),(Vehicles3↦0.008408399298787117),(Vehicles4↦0.007024407386779785),(Vehicles5↦0.011949986219406128)}",
        "VehiclesVx": "{(EgoVehicle↦20.0),(Vehicles2↦-0.12673118151724339),(Vehicles3↦0.037714382633566856),(Vehicles4↦0.9507957845926285),(Vehicles5↦0.25858199223876)}",
        "VehiclesY": "{(EgoVehicle↦8.000000238418579),(Vehicles2↦0.0),(Vehicles3↦-8.000000238418579),(Vehicles4↦-4.0000001192092896),(Vehicles5↦0.0)}",
        "VehiclesVy": "{(EgoVehicle↦0.0),(Vehicles2↦0.0),(Vehicles3↦0.0),(Vehicles4↦0.0),(Vehicles5↦0.0)}",
        "VehiclesX": "{(EgoVehicle↦200.0),(Vehicles2↦21.487490832805634),(Vehicles3↦26.956549286842346),(Vehicles4↦56.847333908081055),(Vehicles5↦101.08236074447632)}"
      },
      "probabilisticVariables": null,
      "activating": [
        "SLOWER_60"
      ],
      "activatingOnlyWhenExecuted": true,
      "updating": null,
      "withPredicate": null
    },
    {
      "id": "SLOWER_60",
      "execute": "SLOWER",
      "after": "1000",
      "priority": 0,
      "additionalGuards": null,
      "activationKind": null,
      "fixedVariables": {
        "Crash": "FALSE",
        "PresentVehicles": "{EgoVehicle,Vehicles2,Vehicles3,Vehicles4,Vehicles5}",
        "VehiclesAy": "{(EgoVehicle↦0.0),(Vehicles2↦0.0),(Vehicles3↦0.0),(Vehicles4↦0.0),(Vehicles5↦0.0)}",
        "Reward": "0.7333333333333334",
        "VehiclesAx": "{(EgoVehicle↦0.0),(Vehicles2↦0.012787403538823128),(Vehicles3↦0.008266284130513668),(Vehicles4↦0.007044076919555664),(Vehicles5↦0.011573024094104767)}",
        "VehiclesVx": "{(EgoVehicle↦20.0),(Vehicles2↦-0.11394377797842026),(Vehicles3↦0.045980666764080524),(Vehicles4↦0.9578398615121841),(Vehicles5↦0.27015501633286476)}",
        "VehiclesY": "{(EgoVehicle↦8.000000238418579),(Vehicles2↦0.0),(Vehicles3↦-8.000000238418579),(Vehicles4↦-4.0000001192092896),(Vehicles5↦0.0)}",
        "VehiclesVy": "{(EgoVehicle↦0.0),(Vehicles2↦0.0),(Vehicles3↦0.0),(Vehicles4↦0.0),(Vehicles5↦0.0)}",
        "VehiclesX": "{(EgoVehicle↦200.0),(Vehicles2↦21.365894377231598),(Vehicles3↦26.997584104537964),(Vehicles4↦57.80094265937805),(Vehicles5↦101.34561061859131)}"
      },
      "probabilisticVariables": null,
      "activating": [
        "SLOWER_61"
      ],
      "activatingOnlyWhenExecuted": true,
      "updating": null,
      "withPredicate": null
    },
    {
      "id": "SLOWER_61",
      "execute": "SLOWER",
      "after": "1000",
      "priority": 0,
      "additionalGuards": null,
      "activationKind": null,
      "fixedVariables": {
        "Crash": "FALSE",
        "PresentVehicles": "{EgoVehicle,Vehicles2,Vehicles3,Vehicles4,Vehicles5}",
        "VehiclesAy": "{(EgoVehicle↦0.0),(Vehicles2↦0.0),(Vehicles3↦0.0),(Vehicles4↦0.0),(Vehicles5↦0.0)}",
        "Reward": "0.7333333333333334",
        "VehiclesAx": "{(EgoVehicle↦0.0),(Vehicles2↦0.012543229386210442),(Vehicles3↦0.008131153881549835),(Vehicles4↦0.007046908140182495),(Vehicles5↦0.01121368259191513)}",
        "VehiclesVx": "{(EgoVehicle↦20.0),(Vehicles2↦-0.10140054859220982),(Vehicles3↦0.05411182064563036),(Vehicles4↦0.9648867696523666),(Vehicles5↦0.2813686989247799)}",
        "VehiclesY": "{(EgoVehicle↦8.000000238418579),(Vehicles2↦0.0),(Vehicles3↦-8.000000238418579),(Vehicles4↦-4.0000001192092896),(Vehicles5↦0.0)}",
        "VehiclesVy": "{(EgoVehicle↦0.0),(Vehicles2↦0.0),(Vehicles3↦0.0),(Vehicles4↦0.0),(Vehicles5↦0.0)}",
        "VehiclesX": "{(EgoVehicle↦200.0),(Vehicles2↦21.256987750530243),(Vehicles3↦27.046826481819153),(Vehicles4↦58.76160264015198),(Vehicles5↦101.62026882171631)}"
      },
      "probabilisticVariables": null,
      "activating": null,
      "activatingOnlyWhenExecuted": true,
      "updating": null,
      "withPredicate": null
    }
  ],
  "listeners": [],
  "metadata": {
    "fileType": "Timed_Trace",
    "formatVersion": 3,
    "savedAt": "2023-12-04T22:31:19.250875Z",
    "creator": "Simulation: MONTE_CARLO_SIMULATION; MAX_STEPS_BEFORE_PROPERTY : 0, EXECUTIONS : 1000, ENDING_TIME : 60000",
    "proB2KernelVersion": "4.12.3-SNAPSHOT",
    "proBCliVersion": "1.12.3-nightly",
    "modelName": "HighwayEnvironment2"
  }
}