{
  "variables": {},
  "activations": [
    {
      "id": "$setup_constants",
      "execute": "$setup_constants",
      "after": "0",
      "priority": 0,
      "additionalGuards": null,
      "activationKind": null,
      "fixedVariables": null,
      "probabilisticVariables": null,
      "activating": null,
      "activatingOnlyWhenExecuted": true,
      "updating": null,
      "withPredicate": null
    },
    {
      "id": "$initialise_machine",
      "execute": "$initialise_machine",
      "after": "0",
      "priority": 0,
      "additionalGuards": null,
      "activationKind": null,
      "fixedVariables": {
        "Crash": "FALSE",
        "PresentVehicles": "{EgoVehicle,Vehicles2,Vehicles3,Vehicles4,Vehicles5}",
        "VehiclesAy": "{(EgoVehicle↦0.0),(Vehicles2↦0.0),(Vehicles3↦0.0),(Vehicles4↦0.0),(Vehicles5↦0.0)}",
        "Reward": "0.0",
        "VehiclesAx": "{(EgoVehicle↦0.0),(Vehicles2↦0.0),(Vehicles3↦0.0),(Vehicles4↦0.0),(Vehicles5↦0.0)}",
        "VehiclesVx": "{(EgoVehicle↦25.0),(Vehicles2↦-3.8222545385360718),(Vehicles3↦-1.8144983053207397),(Vehicles4↦-3.9918196201324463),(Vehicles5↦-3.190661668777466)}",
        "VehiclesY": "{(EgoVehicle↦0.0),(Vehicles2↦0.0),(Vehicles3↦8.000000238418579),(Vehicles4↦8.000000238418579),(Vehicles5↦0.0)}",
        "VehiclesVy": "{(EgoVehicle↦0.0),(Vehicles2↦0.0),(Vehicles3↦0.0),(Vehicles4↦0.0),(Vehicles5↦0.0)}",
        "VehiclesX": "{(EgoVehicle↦155.78209161758423),(Vehicles2↦20.573893189430237),(Vehicles3↦44.248417019844055),(Vehicles4↦66.2578821182251),(Vehicles5↦90.4614806175232)}"
      },
      "probabilisticVariables": null,
      "activating": [
        "SLOWER_2"
      ],
      "activatingOnlyWhenExecuted": true,
      "updating": null,
      "withPredicate": null
    },
    {
      "id": "SLOWER_2",
      "execute": "SLOWER",
      "after": "1000",
      "priority": 0,
      "additionalGuards": null,
      "activationKind": null,
      "fixedVariables": {
        "Crash": "FALSE",
        "PresentVehicles": "{EgoVehicle,Vehicles2,Vehicles3,Vehicles4,Vehicles5}",
        "VehiclesAy": "{(EgoVehicle↦0.0),(Vehicles2↦0.0),(Vehicles3↦-4.893220961093903),(Vehicles4↦0.0),(Vehicles5↦0.0)}",
        "Reward": "0.6842249657064472",
        "VehiclesAx": "{(EgoVehicle↦-4.341564178466797),(Vehicles2↦3.5639429837465286),(Vehicles3↦-2.316770553588867),(Vehicles4↦4.113234458491206),(Vehicles5↦3.6685917153954506)}",
        "VehiclesVx": "{(EgoVehicle↦20.658435821533203),(Vehicles2↦-0.25831155478954315),(Vehicles3↦-4.131268858909607),(Vehicles4↦0.12141483835875988),(Vehicles5↦0.47793004661798477)}",
        "VehiclesY": "{(EgoVehicle↦0.0),(Vehicles2↦0.0),(Vehicles3↦6.020882606506348),(Vehicles4↦8.000000238418579),(Vehicles5↦0.0)}",
        "VehiclesVy": "{(EgoVehicle↦0.0),(Vehicles2↦0.0),(Vehicles3↦-4.893220961093903),(Vehicles4↦0.0),(Vehicles5↦0.0)}",
        "VehiclesX": "{(EgoVehicle↦178.38703393936157),(Vehicles2↦18.796969950199127),(Vehicles3↦42.15973615646362),(Vehicles4↦64.62721824645996),(Vehicles5↦89.36145305633545)}"
      },
      "probabilisticVariables": null,
      "activating": [
        "LANE_RIGHT_3"
      ],
      "activatingOnlyWhenExecuted": true,
      "updating": null,
      "withPredicate": null
    },
    {
      "id": "LANE_RIGHT_3",
      "execute": "LANE_RIGHT",
      "after": "1000",
      "priority": 0,
      "additionalGuards": null,
      "activationKind": null,
      "fixedVariables": {
        "Crash": "FALSE",
        "PresentVehicles": "{EgoVehicle,Vehicles2,Vehicles3,Vehicles4,Vehicles5}",
        "VehiclesAy": "{(EgoVehicle↦1.1575503647327423),(Vehicles2↦-1.1575503647327423),(Vehicles3↦3.243737816810608),(Vehicles4↦-1.1575503647327423),(Vehicles5↦-1.1575503647327423)}",
        "Reward": "0.701422038389655",
        "VehiclesAx": "{(EgoVehicle↦-0.6051087379455566),(Vehicles2↦0.18342407420277596),(Vehicles3↦1.7595039308071136),(Vehicles4↦0.3086306620389223),(Vehicles5↦0.22161927074193954)}",
        "VehiclesVx": "{(EgoVehicle↦20.053327083587646),(Vehicles2↦-0.0748874805867672),(Vehicles3↦-2.3717649281024933),(Vehicles4↦0.4300455003976822),(Vehicles5↦0.6995493173599243)}",
        "VehiclesY": "{(EgoVehicle↦3.5990391969680786),(Vehicles2↦-3.5990391969680786),(Vehicles3↦0.5765085965394974),(Vehicles4↦4.4009610414505005),(Vehicles5↦-3.5990391969680786)}",
        "VehiclesVy": "{(EgoVehicle↦1.1575503647327423),(Vehicles2↦-1.1575503647327423),(Vehicles3↦-1.6494831442832947),(Vehicles4↦-1.1575503647327423),(Vehicles5↦-1.1575503647327423)}",
        "VehiclesX": "{(EgoVehicle↦198.35355281829834),(Vehicles2↦19.04182732105255),(Vehicles3↦39.12755250930786),(Vehicles4↦65.30023217201233),(Vehicles5↦90.3640627861023)}"
      },
      "probabilisticVariables": null,
      "activating": [
        "LANE_RIGHT_4"
      ],
      "activatingOnlyWhenExecuted": true,
      "updating": null,
      "withPredicate": null
    },
    {
      "id": "LANE_RIGHT_4",
      "execute": "LANE_RIGHT",
      "after": "1000",
      "priority": 0,
      "additionalGuards": null,
      "activationKind": null,
      "fixedVariables": {
        "Crash": "FALSE",
        "PresentVehicles": "{EgoVehicle,Vehicles2,Vehicles3,Vehicles4,Vehicles5}",
        "VehiclesAy": "{(EgoVehicle↦0.06186880171298981),(Vehicles2↦-0.06186880171298981),(Vehicles3↦0.39272502064704895),(Vehicles4↦-0.06186880171298981),(Vehicles5↦-2.3769695311784744)}",
        "Reward": "0.7333333333333334",
        "VehiclesAx": "{(EgoVehicle↦-0.07909655570983887),(Vehicles2↦-0.154517013579607),(Vehicles3↦0.9732909500598907),(Vehicles4↦-0.05160767585039139),(Vehicles5↦-0.18875457346439362)}",
        "VehiclesVx": "{(EgoVehicle↦19.974230527877808),(Vehicles2↦-0.2294044941663742),(Vehicles3↦-1.3984739780426025),(Vehicles4↦0.3784378245472908),(Vehicles5↦0.5107947438955307)}",
        "VehiclesY": "{(EgoVehicle↦7.578322649002075),(Vehicles2↦-7.578322649002075),(Vehicles3↦-3.5651711225509644),(Vehicles4↦0.4216770976781845),(Vehicles5↦-7.578322649002075)}",
        "VehiclesVy": "{(EgoVehicle↦1.2194191664457321),(Vehicles2↦-1.2194191664457321),(Vehicles3↦-1.2567581236362457),(Vehicles4↦-1.2194191664457321),(Vehicles5↦-1.2194191664457321)}",
        "VehiclesX": "{(EgoVehicle↦200.0),(Vehicles2↦19.345414638519287),(Vehicles3↦37.63670325279236),(Vehicles4↦66.15310311317444),(Vehicles5↦91.43363833427429)}"
      },
      "probabilisticVariables": null,
      "activating": [
        "FASTER_5"
      ],
      "activatingOnlyWhenExecuted": true,
      "updating": null,
      "withPredicate": null
    },
    {
      "id": "FASTER_5",
      "execute": "FASTER",
      "after": "1000",
      "priority": 0,
      "additionalGuards": null,
      "activationKind": null,
      "fixedVariables": {
        "Crash": "FALSE",
        "PresentVehicles": "{EgoVehicle,Vehicles2,Vehicles3,Vehicles4,Vehicles5}",
        "VehiclesAy": "{(EgoVehicle↦-1.1593201709911227),(Vehicles2↦1.1593201709911227),(Vehicles3↦1.1940277367830276),(Vehicles4↦1.1593201709911227),(Vehicles5↦-1.2795181619003415)}",
        "Reward": "0.8491464864524669",
        "VehiclesAx": "{(EgoVehicle↦4.368761777877808),(Vehicles2↦-4.500870779156685),(Vehicles3↦-3.864620327949524),(Vehicles4↦-4.428827650845051),(Vehicles5↦-4.594119116663933)}",
        "VehiclesVx": "{(EgoVehicle↦24.342992305755615),(Vehicles2↦-4.730275273323059),(Vehicles3↦-5.2630943059921265),(Vehicles4↦-4.05038982629776),(Vehicles5↦-4.083324372768402)}",
        "VehiclesY": "{(EgoVehicle↦7.981852054595947),(Vehicles2↦-7.981852054595947),(Vehicles3↦-3.9809317588806152),(Vehicles4↦0.018147908616811037),(Vehicles5↦-7.981852054595947)}",
        "VehiclesVy": "{(EgoVehicle↦0.060098995454609394),(Vehicles2↦-0.060098995454609394),(Vehicles3↦-0.06273038685321808),(Vehicles4↦-0.060098995454609394),(Vehicles5↦-0.060098995454609394)}",
        "VehiclesX": "{(EgoVehicle↦200.0),(Vehicles2↦16.636592149734497),(Vehicles3↦34.043294191360474),(Vehicles4↦64.08278346061707),(Vehicles5↦89.431893825531)}"
      },
      "probabilisticVariables": null,
      "activating": [
        "SLOWER_6"
      ],
      "activatingOnlyWhenExecuted": true,
      "updating": null,
      "withPredicate": null
    },
    {
      "id": "SLOWER_6",
      "execute": "SLOWER",
      "after": "1000",
      "priority": 0,
      "additionalGuards": null,
      "activationKind": null,
      "fixedVariables": {
        "Crash": "FALSE",
        "PresentVehicles": "{EgoVehicle,Vehicles2,Vehicles3,Vehicles4,Vehicles5}",
        "VehiclesAy": "{(EgoVehicle↦-0.05756439553806558),(Vehicles2↦0.05756439553806558),(Vehicles3↦0.06001778936479241),(Vehicles4↦0.05756439553806558),(Vehicles5↦-0.0626335953711532)}",
        "Reward": "0.7485847045043443",
        "VehiclesAx": "{(EgoVehicle↦-3.771066665649414),(Vehicles2↦3.6931976675987244),(Vehicles3↦4.037831872701645),(Vehicles4↦3.747514709830284),(Vehicles5↦3.572792075574398)}",
        "VehiclesVx": "{(EgoVehicle↦20.5719256401062),(Vehicles2↦-1.0370776057243347),(Vehicles3↦-1.2252624332904816),(Vehicles4↦-0.3028751164674759),(Vehicles5↦-0.5105322971940041)}",
        "VehiclesY": "{(EgoVehicle↦7.999124050140381),(Vehicles2↦-7.999124050140381),(Vehicles3↦-3.999062418937683),(Vehicles4↦0.0008756597817409784),(Vehicles5↦-7.999124050140381)}",
        "VehiclesVy": "{(EgoVehicle↦0.0025345999165438116),(Vehicles2↦-0.0025345999165438116),(Vehicles3↦-0.002712597488425672),(Vehicles4↦-0.0025345999165438116),(Vehicles5↦-0.0025345999165438116)}",
        "VehiclesX": "{(EgoVehicle↦200.0),(Vehicles2↦13.952377438545227),(Vehicles3↦30.98157048225403),(Vehicles4↦62.10126280784607),(Vehicles5↦87.34672665596008)}"
      },
      "probabilisticVariables": null,
      "activating": [
        "FASTER_7"
      ],
      "activatingOnlyWhenExecuted": true,
      "updating": null,
      "withPredicate": null
    },
    {
      "id": "FASTER_7",
      "execute": "FASTER",
      "after": "1000",
      "priority": 0,
      "additionalGuards": null,
      "activationKind": null,
      "fixedVariables": {
        "Crash": "FALSE",
        "PresentVehicles": "{EgoVehicle,Vehicles2,Vehicles3,Vehicles4,Vehicles5}",
        "VehiclesAy": "{(EgoVehicle↦-0.0024118447981891222),(Vehicles2↦0.0024118447981891222),(Vehicles3↦0.0025780528085306287),(Vehicles4↦0.0024118447981891222),(Vehicles5↦-0.002657355034898501)}",
        "Reward": "0.8511167791853724",
        "VehiclesAx": "{(EgoVehicle↦3.8449525833129883),(Vehicles2↦-3.893040418624878),(Vehicles3↦-3.715914636850357),(Vehicles4↦-3.8499849289655685),(Vehicles5↦-4.003999195992947)}",
        "VehiclesVx": "{(EgoVehicle↦24.41687822341919),(Vehicles2↦-4.930118024349213),(Vehicles3↦-4.941177070140839),(Vehicles4↦-4.152860045433044),(Vehicles5↦-4.514531493186951)}",
        "VehiclesY": "{(EgoVehicle↦7.999963045120239),(Vehicles2↦-7.999963045120239),(Vehicles3↦-3.999958634376526),(Vehicles4↦3.709499378601322E-05),(Vehicles5↦-7.999963045120239)}",
        "VehiclesVy": "{(EgoVehicle↦0.00012275511835468933),(Vehicles2↦-0.00012275511835468933),(Vehicles3↦-0.00013454467989504337),(Vehicles4↦-0.00012275511835468933),(Vehicles5↦-0.00012275511835468933)}",
        "VehiclesX": "{(EgoVehicle↦200.0),(Vehicles2↦10.77318862080574),(Vehicles3↦27.69492268562317),(Vehicles4↦59.674257040023804),(Vehicles5↦84.64818000793457)}"
      },
      "probabilisticVariables": null,
      "activating": [
        "SLOWER_8"
      ],
      "activatingOnlyWhenExecuted": true,
      "updating": null,
      "withPredicate": null
    },
    {
      "id": "SLOWER_8",
      "execute": "SLOWER",
      "after": "1000",
      "priority": 0,
      "additionalGuards": null,
      "activationKind": null,
      "fixedVariables": {
        "Crash": "FALSE",
        "PresentVehicles": "{EgoVehicle,Vehicles2,Vehicles3,Vehicles4,Vehicles5}",
        "VehiclesAy": "{(EgoVehicle↦-0.00011758320454191562),(Vehicles2↦0.00011758320454191562),(Vehicles3↦0.00012859938408382732),(Vehicles4↦0.00011758320454191562),(Vehicles5↦-0.00012792703216746304)}",
        "Reward": "0.7488439105659438",
        "VehiclesAx": "{(EgoVehicle↦-3.8352322578430176),(Vehicles2↦3.804687336087227),(Vehicles3↦3.8877492398023605),(Vehicles4↦3.839312121272087),(Vehicles5↦3.716149181127548)}",
        "VehiclesVx": "{(EgoVehicle↦20.581645965576172),(Vehicles2↦-1.1254306882619858),(Vehicles3↦-1.053427830338478),(Vehicles4↦-0.31354792416095734),(Vehicles5↦-0.7983823120594025)}",
        "VehiclesY": "{(EgoVehicle↦7.999998092651367),(Vehicles2↦-7.999998092651367),(Vehicles3↦-3.9999979734420776),(Vehicles4↦1.786980249107728E-06),(Vehicles5↦-7.999998092651367)}",
        "VehiclesVy": "{(EgoVehicle↦5.17191381277371E-06),(Vehicles2↦-5.17191381277371E-06),(Vehicles3↦-5.945295811216056E-06),(Vehicles4↦-5.17191381277371E-06),(Vehicles5↦-5.17191381277371E-06)}",
        "VehiclesX": "{(EgoVehicle↦200.0),(Vehicles2↦7.945502549409866),(Vehicles3↦24.894897639751434),(Vehicles4↦57.63827562332153),(Vehicles5↦82.19872117042542)}"
      },
      "probabilisticVariables": null,
      "activating": [
        "SLOWER_9"
      ],
      "activatingOnlyWhenExecuted": true,
      "updating": null,
      "withPredicate": null
    },
    {
      "id": "SLOWER_9",
      "execute": "SLOWER",
      "after": "1000",
      "priority": 0,
      "additionalGuards": null,
      "activationKind": null,
      "fixedVariables": {
        "Crash": "FALSE",
        "PresentVehicles": "{EgoVehicle,Vehicles2,Vehicles3,Vehicles4,Vehicles5}",
        "VehiclesAy": "{(EgoVehicle↦-4.854145778665497E-06),(Vehicles2↦4.854145778665497E-06),(Vehicles3↦5.576965484976881E-06),(Vehicles4↦4.854145778665497E-06),(Vehicles5↦-5.489681846881922E-06)}",
        "Reward": "0.735375878483309",
        "VehiclesAx": "{(EgoVehicle↦-0.5050516128540039),(Vehicles2↦0.48561878502368927),(Vehicles3↦0.5167646333575249),(Vehicles4↦0.513398926705122),(Vehicles5↦0.42015545070171356)}",
        "VehiclesVx": "{(EgoVehicle↦20.076594352722168),(Vehicles2↦-0.6398119032382965),(Vehicles3↦-0.5366631969809532),(Vehicles4↦0.19985100254416466),(Vehicles5↦-0.3782268613576889)}",
        "VehiclesY": "{(EgoVehicle↦8.000000238418579),(Vehicles2↦-8.000000238418579),(Vehicles3↦-3.999999761581421),(Vehicles4↦1.0949916173785823E-07),(Vehicles5↦-8.000000238418579)}",
        "VehiclesVy": "{(EgoVehicle↦3.177680341082123E-07),(Vehicles2↦-3.177680341082123E-07),(Vehicles3↦-3.683303262391746E-07),(Vehicles4↦-3.177680341082123E-07),(Vehicles5↦-3.177680341082123E-07)}",
        "VehiclesX": "{(EgoVehicle↦200.0),(Vehicles2↦7.090199738740921),(Vehicles3↦24.12704974412918),(Vehicles4↦57.60646462440491),(Vehicles5↦81.64258599281311)}"
      },
      "probabilisticVariables": null,
      "activating": [
        "SLOWER_10"
      ],
      "activatingOnlyWhenExecuted": true,
      "updating": null,
      "withPredicate": null
    },
    {
      "id": "SLOWER_10",
      "execute": "SLOWER",
      "after": "1000",
      "priority": 0,
      "additionalGuards": null,
      "activationKind": null,
      "fixedVariables": {
        "Crash": "FALSE",
        "PresentVehicles": "{EgoVehicle,Vehicles2,Vehicles3,Vehicles4,Vehicles5}",
        "VehiclesAy": "{(EgoVehicle↦-2.9801869416701265E-07),(Vehicles2↦2.9801869416701265E-07),(Vehicles3↦3.4527563030906094E-07),(Vehicles4↦2.9801869416701265E-07),(Vehicles5↦-3.3751737404941196E-07)}",
        "Reward": "0.7336023104724249",
        "VehiclesAx": "{(EgoVehicle↦-0.06650686264038086),(Vehicles2↦0.05449030548334122),(Vehicles3↦0.057934150099754333),(Vehicles4↦0.0766930915415287),(Vehicles5↦0.0072472915053367615)}",
        "VehiclesVx": "{(EgoVehicle↦20.010087490081787),(Vehicles2↦-0.5853215977549553),(Vehicles3↦-0.4787290468811989),(Vehicles4↦0.27654409408569336),(Vehicles5↦-0.37097956985235214)}",
        "VehiclesY": "{(EgoVehicle↦8.000000238418579),(Vehicles2↦-8.000000238418579),(Vehicles3↦-4.0000001192092896),(Vehicles4↦6.800461527234347E-09),(Vehicles5↦-8.000000238418579)}",
        "VehiclesVy": "{(EgoVehicle↦1.974933994119965E-08),(Vehicles2↦-1.974933994119965E-08),(Vehicles3↦-2.3054695930113667E-08),(Vehicles4↦-1.974933994119965E-08),(Vehicles5↦-1.974933994119965E-08)}",
        "VehiclesX": "{(EgoVehicle↦200.0),(Vehicles2↦6.481786817312241),(Vehicles3↦23.624703288078308),(Vehicles4↦57.84699320793152),(Vehicles5↦81.27565383911133)}"
      },
      "probabilisticVariables": null,
      "activating": [
        "FASTER_11"
      ],
      "activatingOnlyWhenExecuted": true,
      "updating": null,
      "withPredicate": null
    },
    {
      "id": "FASTER_11",
      "execute": "FASTER",
      "after": "1000",
      "priority": 0,
      "additionalGuards": null,
      "activationKind": null,
      "fixedVariables": {
        "Crash": "FALSE",
        "PresentVehicles": "{EgoVehicle,Vehicles2,Vehicles3,Vehicles4,Vehicles5}",
        "VehiclesAy": "{(EgoVehicle↦-1.8782913002723944E-08),(Vehicles2↦1.8782913002723944E-08),(Vehicles3↦2.187188208324642E-08),(Vehicles4↦1.8782913002723944E-08),(Vehicles5↦-2.0715766879675357E-08)}",
        "Reward": "0.849143788484709",
        "VehiclesAx": "{(EgoVehicle↦4.3328046798706055),(Vehicles2↦-4.339827485382557),(Vehicles3↦-4.349859915673733),(Vehicles4↦-4.32196319103241),(Vehicles5↦-4.374968446791172)}",
        "VehiclesVx": "{(EgoVehicle↦24.342892169952393),(Vehicles2↦-4.925149083137512),(Vehicles3↦-4.828588962554932),(Vehicles4↦-4.045419096946716),(Vehicles5↦-4.745948016643524)}",
        "VehiclesY": "{(EgoVehicle↦8.000000238418579),(Vehicles2↦-8.000000238418579),(Vehicles3↦-4.0000001192092896),(Vehicles4↦2.9178259808304574E-10),(Vehicles5↦-8.000000238418579)}",
        "VehiclesVy": "{(EgoVehicle↦9.664269384757063E-10),(Vehicles2↦-9.664269384757063E-10),(Vehicles3↦-1.1828138468672478E-09),(Vehicles4↦-9.664269384757063E-10),(Vehicles5↦-9.664269384757063E-10)}",
        "VehiclesX": "{(EgoVehicle↦200.0),(Vehicles2↦3.5031039267778397),(Vehicles3↦20.749273896217346),(Vehicles4↦55.73762059211731),(Vehicles5↦78.49651575088501)}"
      },
      "probabilisticVariables": null,
      "activating": [
        "LANE_RIGHT_12"
      ],
      "activatingOnlyWhenExecuted": true,
      "updating": null,
      "withPredicate": null
    },
    {
      "id": "LANE_RIGHT_12",
      "execute": "LANE_RIGHT",
      "after": "1000",
      "priority": 0,
      "additionalGuards": null,
      "activationKind": null,
      "fixedVariables": {
        "Crash": "FALSE",
        "PresentVehicles": "{EgoVehicle,Vehicles2,Vehicles3,Vehicles4,Vehicles5}",
        "VehiclesAy": "{(EgoVehicle↦-9.350209495551098E-10),(Vehicles2↦9.350209495551098E-10),(Vehicles3↦1.1372147667998433E-09),(Vehicles4↦9.350209495551098E-10),(Vehicles5↦-9.978329273963027E-10)}",
        "Reward": "0.8643591271529932",
        "VehiclesAx": "{(EgoVehicle↦0.5705761909484863),(Vehicles2↦-0.5743509531021118),(Vehicles3↦-0.5893081426620483),(Vehicles4↦-0.5596178770065308),(Vehicles5↦-1.2947097420692444)}",
        "VehiclesVx": "{(EgoVehicle↦24.91346836090088),(Vehicles2↦-5.499500036239624),(Vehicles3↦-5.41789710521698),(Vehicles4↦-4.605036973953247),(Vehicles5↦-6.0406577587127686)}",
        "VehiclesY": "{(EgoVehicle↦8.000000238418579),(Vehicles2↦-8.000000238418579),(Vehicles3↦-4.0000001192092896),(Vehicles4↦9.42979028195623E-12),(Vehicles5↦-4.0000001192092896)}",
        "VehiclesVy": "{(EgoVehicle↦3.140598892059643E-11),(Vehicles2↦-3.140598892059643E-11),(Vehicles3↦-4.559908006740443E-11),(Vehicles4↦-3.140598892059643E-11),(Vehicles5↦-3.140598892059643E-11)}",
        "VehiclesX": "{(EgoVehicle↦200.0),(Vehicles2↦-1.7385197803378105),(Vehicles3↦15.598376095294952),(Vehicles4↦51.381826400756836),(Vehicles5↦72.85189032554626)}"
      },
      "probabilisticVariables": null,
      "activating": [
        "LANE_RIGHT_13"
      ],
      "activatingOnlyWhenExecuted": true,
      "updating": null,
      "withPredicate": null
    },
    {
      "id": "LANE_RIGHT_13",
      "execute": "LANE_RIGHT",
      "after": "1000",
      "priority": 0,
      "additionalGuards": null,
      "activationKind": null,
      "fixedVariables": {
        "Crash": "FALSE",
        "PresentVehicles": "{EgoVehicle,Vehicles2,Vehicles3,Vehicles4,Vehicles5}",
        "VehiclesAy": "{(EgoVehicle↦-3.041122909053229E-11),(Vehicles2↦3.041122909053229E-11),(Vehicles3↦4.368061468085216E-11),(Vehicles4↦3.041122909053229E-11),(Vehicles5↦-3.240074875066057E-11)}",
        "Reward": "0.8663627931504628",
        "VehiclesAx": "{(EgoVehicle↦0.0751352310180664),(Vehicles2↦-0.07697999477386475),(Vehicles3↦-0.09170889854431152),(Vehicles4↦-0.06429731845855713),(Vehicles5↦0.04992067813873291)}",
        "VehiclesVx": "{(EgoVehicle↦24.988603591918945),(Vehicles2↦-5.576480031013489),(Vehicles3↦-5.5096060037612915),(Vehicles4↦-4.669334292411804),(Vehicles5↦-5.990737080574036)}",
        "VehiclesY": "{(EgoVehicle↦8.000000238418579),(Vehicles2↦-8.000000238418579),(Vehicles3↦-4.0000001192092896),(Vehicles4↦2.957634137601417E-13),(Vehicles5↦-4.0000001192092896)}",
        "VehiclesVy": "{(EgoVehicle↦9.947598300641403E-13),(Vehicles2↦-9.947598300641403E-13),(Vehicles3↦-1.9184653865522705E-12),(Vehicles4↦-9.947598300641403E-13),(Vehicles5↦-9.947598300641403E-13)}",
        "VehiclesX": "{(EgoVehicle↦200.0),(Vehicles2↦-7.280318439006805),(Vehicles3↦10.13212502002716),(Vehicles4↦46.73968851566315),(Vehicles5↦66.82135462760925)}"
      },
      "probabilisticVariables": null,
      "activating": [
        "SLOWER_14"
      ],
      "activatingOnlyWhenExecuted": true,
      "updating": null,
      "withPredicate": null
    },
    {
      "id": "SLOWER_14",
      "execute": "SLOWER",
      "after": "1000",
      "priority": 0,
      "additionalGuards": null,
      "activationKind": null,
      "fixedVariables": {
        "Crash": "FALSE",
        "PresentVehicles": "{EgoVehicle,Vehicles2,Vehicles3,Vehicles4,Vehicles5}",
        "VehiclesAy": "{(EgoVehicle↦-9.592326932761353E-13),(Vehicles2↦8.970602038971265E-13),(Vehicles3↦1.8740564655672642E-12),(Vehicles4↦9.50350909079134E-13),(Vehicles5↦-1.0391687510491465E-12)}",
        "Reward": "0.7508516161076056",
        "VehiclesAx": "{(EgoVehicle↦-4.331667423248291),(Vehicles2↦4.386170357465744),(Vehicles3↦5.182578228414059),(Vehicles4↦3.1183040142059326),(Vehicles5↦4.848476201295853)}",
        "VehiclesVx": "{(EgoVehicle↦20.656936168670654),(Vehicles2↦-1.1903096735477448),(Vehicles3↦-0.3270277753472328),(Vehicles4↦-1.5510302782058716),(Vehicles5↦-1.142260879278183)}",
        "VehiclesY": "{(EgoVehicle↦8.000000238418579),(Vehicles2↦-4.0000001192092896),(Vehicles3↦1.3322676295501878E-14),(Vehicles4↦-4.0000001192092896),(Vehicles5↦-8.000000238418579)}",
        "VehiclesVy": "{(EgoVehicle↦3.552713678800501E-14),(Vehicles2↦-9.769962616701378E-14),(Vehicles3↦-4.440892098500626E-14),(Vehicles4↦-4.440892098500626E-14),(Vehicles5↦-4.440892098500626E-14)}",
        "VehiclesX": "{(EgoVehicle↦200.0),(Vehicles2↦7.00678750872612),(Vehicles3↦44.46422755718231),(Vehicles4↦63.264626264572144),(Vehicles5↦64.95148539543152)}"
      },
      "probabilisticVariables": null,
      "activating": [
        "LANE_RIGHT_15"
      ],
      "activatingOnlyWhenExecuted": true,
      "updating": null,
      "withPredicate": null
    },
    {
      "id": "LANE_RIGHT_15",
      "execute": "LANE_RIGHT",
      "after": "1000",
      "priority": 0,
      "additionalGuards": null,
      "activationKind": null,
      "fixedVariables": {
        "Crash": "FALSE",
        "PresentVehicles": "{EgoVehicle,Vehicles2,Vehicles3,Vehicles4,Vehicles5}",
        "VehiclesAy": "{(EgoVehicle↦-3.552713678800501E-14),(Vehicles2↦9.769962616701378E-14),(Vehicles3↦4.440892098500626E-14),(Vehicles4↦4.440892098500626E-14),(Vehicles5↦-4.440892098500626E-14)}",
        "Reward": "0.7356402676904392",
        "VehiclesAx": "{(EgoVehicle↦-0.5704259872436523),(Vehicles2↦0.5631733685731888),(Vehicles3↦0.580839030444622),(Vehicles4↦0.6653415411710739),(Vehicles5↦0.5476914718747139)}",
        "VehiclesVx": "{(EgoVehicle↦20.086510181427002),(Vehicles2↦-0.627136304974556),(Vehicles3↦0.2538112550973892),(Vehicles4↦-0.8856887370347977),(Vehicles5↦-0.5945694074034691)}",
        "VehiclesY": "{(EgoVehicle↦8.000000238418579),(Vehicles2↦-4.0000001192092896),(Vehicles3↦0.0),(Vehicles4↦-4.0000001192092896),(Vehicles5↦-8.000000238418579)}",
        "VehiclesVy": "{(EgoVehicle↦0.0),(Vehicles2↦0.0),(Vehicles3↦0.0),(Vehicles4↦0.0),(Vehicles5↦0.0)}",
        "VehiclesX": "{(EgoVehicle↦200.0),(Vehicles2↦6.127830222249031),(Vehicles3↦44.45606470108032),(Vehicles4↦62.06716299057007),(Vehicles5↦64.11475539207458)}"
      },
      "probabilisticVariables": null,
      "activating": [
        "LANE_RIGHT_16"
      ],
      "activatingOnlyWhenExecuted": true,
      "updating": null,
      "withPredicate": null
    },
    {
      "id": "LANE_RIGHT_16",
      "execute": "LANE_RIGHT",
      "after": "1000",
      "priority": 0,
      "additionalGuards": null,
      "activationKind": null,
      "fixedVariables": {
        "Crash": "FALSE",
        "PresentVehicles": "{EgoVehicle,Vehicles2,Vehicles3,Vehicles4,Vehicles5}",
        "VehiclesAy": "{(EgoVehicle↦0.0),(Vehicles2↦0.0),(Vehicles3↦0.0),(Vehicles4↦0.0),(Vehicles5↦0.0)}",
        "Reward": "0.7336371271581373",
        "VehiclesAx": "{(EgoVehicle↦-0.0751185417175293),(Vehicles2↦0.07322259247303009),(Vehicles3↦0.08531056344509125),(Vehicles4↦0.15974976122379303),(Vehicles5↦0.052894242107868195)}",
        "VehiclesVx": "{(EgoVehicle↦20.011391639709473),(Vehicles2↦-0.5539137125015259),(Vehicles3↦0.33912181854248047),(Vehicles4↦-0.7259389758110046),(Vehicles5↦-0.5416751652956009)}",
        "VehiclesY": "{(EgoVehicle↦8.000000238418579),(Vehicles2↦-4.0000001192092896),(Vehicles3↦0.0),(Vehicles4↦-4.0000001192092896),(Vehicles5↦-8.000000238418579)}",
        "VehiclesVy": "{(EgoVehicle↦0.0),(Vehicles2↦0.0),(Vehicles3↦0.0),(Vehicles4↦0.0),(Vehicles5↦0.0)}",
        "VehiclesX": "{(EgoVehicle↦200.0),(Vehicles2↦5.540949106216431),(Vehicles3↦44.75541114807129),(Vehicles4↦61.25749945640564),(Vehicles5↦63.552701473236084)}"
      },
      "probabilisticVariables": null,
      "activating": [
        "LANE_RIGHT_17"
      ],
      "activatingOnlyWhenExecuted": true,
      "updating": null,
      "withPredicate": null
    },
    {
      "id": "LANE_RIGHT_17",
      "execute": "LANE_RIGHT",
      "after": "1000",
      "priority": 0,
      "additionalGuards": null,
      "activationKind": null,
      "fixedVariables": {
        "Crash": "FALSE",
        "PresentVehicles": "{EgoVehicle,Vehicles2,Vehicles3,Vehicles4,Vehicles5}",
        "VehiclesAy": "{(EgoVehicle↦0.0),(Vehicles2↦0.0),(Vehicles3↦0.0),(Vehicles4↦0.0),(Vehicles5↦0.0)}",
        "Reward": "0.7333733391045011",
        "VehiclesAx": "{(EgoVehicle↦-0.009891986846923828),(Vehicles2↦0.013182535767555237),(Vehicles3↦0.019874945282936096),(Vehicles4↦0.08633702993392944),(Vehicles5↦-0.011935904622077942)}",
        "VehiclesVx": "{(EgoVehicle↦20.00149965286255),(Vehicles2↦-0.5407311767339706),(Vehicles3↦0.35899676382541656),(Vehicles4↦-0.6396019458770752),(Vehicles5↦-0.5536110699176788)}",
        "VehiclesY": "{(EgoVehicle↦8.000000238418579),(Vehicles2↦-4.0000001192092896),(Vehicles3↦0.0),(Vehicles4↦-4.0000001192092896),(Vehicles5↦-8.000000238418579)}",
        "VehiclesVy": "{(EgoVehicle↦0.0),(Vehicles2↦0.0),(Vehicles3↦0.0),(Vehicles4↦0.0),(Vehicles5↦0.0)}",
        "VehiclesX": "{(EgoVehicle↦200.0),(Vehicles2↦4.993407428264618),(Vehicles3↦45.103996992111206),(Vehicles4↦60.568177700042725),(Vehicles5↦63.007718324661255)}"
      },
      "probabilisticVariables": null,
      "activating": [
        "LANE_RIGHT_18"
      ],
      "activatingOnlyWhenExecuted": true,
      "updating": null,
      "withPredicate": null
    },
    {
      "id": "LANE_RIGHT_18",
      "execute": "LANE_RIGHT",
      "after": "1000",
      "priority": 0,
      "additionalGuards": null,
      "activationKind": null,
      "fixedVariables": {
        "Crash": "FALSE",
        "PresentVehicles": "{EgoVehicle,Vehicles2,Vehicles3,Vehicles4,Vehicles5}",
        "VehiclesAy": "{(EgoVehicle↦0.0),(Vehicles2↦0.0),(Vehicles3↦0.0),(Vehicles4↦0.0),(Vehicles5↦0.0)}",
        "Reward": "0.7333386015830344",
        "VehiclesAx": "{(EgoVehicle↦-0.0013017654418945312),(Vehicles2↦0.009380578994750977),(Vehicles3↦0.011086612939834595),(Vehicles4↦0.07113710045814514),(Vehicles5↦-0.019997134804725647)}",
        "VehiclesVx": "{(EgoVehicle↦20.000197887420654),(Vehicles2↦-0.5313505977392197),(Vehicles3↦0.37008337676525116),(Vehicles4↦-0.56846484541893),(Vehicles5↦-0.5736082047224045)}",
        "VehiclesY": "{(EgoVehicle↦8.000000238418579),(Vehicles2↦-4.0000001192092896),(Vehicles3↦0.0),(Vehicles4↦-4.0000001192092896),(Vehicles5↦-8.000000238418579)}",
        "VehiclesVy": "{(EgoVehicle↦0.0),(Vehicles2↦0.0),(Vehicles3↦0.0),(Vehicles4↦0.0),(Vehicles5↦0.0)}",
        "VehiclesX": "{(EgoVehicle↦200.0),(Vehicles2↦4.456262290477753),(Vehicles3↦45.467641949653625),(Vehicles4↦59.957706928253174),(Vehicles5↦62.44625449180603)}"
      },
      "probabilisticVariables": null,
      "activating": [
        "LANE_RIGHT_19"
      ],
      "activatingOnlyWhenExecuted": true,
      "updating": null,
      "withPredicate": null
    },
    {
      "id": "LANE_RIGHT_19",
      "execute": "LANE_RIGHT",
      "after": "1000",
      "priority": 0,
      "additionalGuards": null,
      "activationKind": null,
      "fixedVariables": {
        "Crash": "FALSE",
        "PresentVehicles": "{EgoVehicle,Vehicles2,Vehicles3,Vehicles4,Vehicles5}",
        "VehiclesAy": "{(EgoVehicle↦0.0),(Vehicles2↦0.0),(Vehicles3↦0.0),(Vehicles4↦0.0),(Vehicles5↦0.0)}",
        "Reward": "0.7333340270946108",
        "VehiclesAx": "{(EgoVehicle↦-0.000171661376953125),(Vehicles2↦0.01252792775630951),(Vehicles3↦0.009765438735485077),(Vehicles4↦0.06459824740886688),(Vehicles5↦-0.020368173718452454)}",
        "VehiclesVx": "{(EgoVehicle↦20.0000262260437),(Vehicles2↦-0.5188226699829102),(Vehicles3↦0.37984881550073624),(Vehicles4↦-0.5038665980100632),(Vehicles5↦-0.5939763784408569)}",
        "VehiclesY": "{(EgoVehicle↦8.000000238418579),(Vehicles2↦-4.0000001192092896),(Vehicles3↦0.0),(Vehicles4↦-4.0000001192092896),(Vehicles5↦-8.000000238418579)}",
        "VehiclesVy": "{(EgoVehicle↦0.0),(Vehicles2↦0.0),(Vehicles3↦0.0),(Vehicles4↦0.0),(Vehicles5↦0.0)}",
        "VehiclesX": "{(EgoVehicle↦200.0),(Vehicles2↦3.9296284317970276),(Vehicles3↦45.84167301654816),(Vehicles4↦59.4154953956604),(Vehicles5↦61.86445355415344)}"
      },
      "probabilisticVariables": null,
      "activating": [
        "LANE_RIGHT_20"
      ],
      "activatingOnlyWhenExecuted": true,
      "updating": null,
      "withPredicate": null
    },
    {
      "id": "LANE_RIGHT_20",
      "execute": "LANE_RIGHT",
      "after": "1000",
      "priority": 0,
      "additionalGuards": null,
      "activationKind": null,
      "fixedVariables": {
        "Crash": "FALSE",
        "PresentVehicles": "{EgoVehicle,Vehicles2,Vehicles3,Vehicles4,Vehicles5}",
        "VehiclesAy": "{(EgoVehicle↦0.0),(Vehicles2↦0.0),(Vehicles3↦0.0),(Vehicles4↦0.0),(Vehicles5↦0.0)}",
        "Reward": "0.7333334246928431",
        "VehiclesAx": "{(EgoVehicle↦-2.384185791015625E-05),(Vehicles2↦0.016110911965370178),(Vehicles3↦0.009432695806026459),(Vehicles4↦0.05996987223625183),(Vehicles5↦-0.019506700336933136)}",
        "VehiclesVx": "{(EgoVehicle↦20.00000238418579),(Vehicles2↦-0.50271175801754),(Vehicles3↦0.3892815113067627),(Vehicles4↦-0.44389672577381134),(Vehicles5↦-0.6134830787777901)}",
        "VehiclesY": "{(EgoVehicle↦8.000000238418579),(Vehicles2↦-4.0000001192092896),(Vehicles3↦0.0),(Vehicles4↦-4.0000001192092896),(Vehicles5↦-8.000000238418579)}",
        "VehiclesVy": "{(EgoVehicle↦0.0),(Vehicles2↦0.0),(Vehicles3↦0.0),(Vehicles4↦0.0),(Vehicles5↦0.0)}",
        "VehiclesX": "{(EgoVehicle↦200.0),(Vehicles2↦3.4169767051935196),(Vehicles3↦46.22531235218048),(Vehicles4↦58.93595218658447),(Vehicles5↦61.26258969306946)}"
      },
      "probabilisticVariables": null,
      "activating": [
        "LANE_RIGHT_21"
      ],
      "activatingOnlyWhenExecuted": true,
      "updating": null,
      "withPredicate": null
    },
    {
      "id": "LANE_RIGHT_21",
      "execute": "LANE_RIGHT",
      "after": "1000",
      "priority": 0,
      "additionalGuards": null,
      "activationKind": null,
      "fixedVariables": {
        "Crash": "FALSE",
        "PresentVehicles": "{EgoVehicle,Vehicles2,Vehicles3,Vehicles4,Vehicles5}",
        "VehiclesAy": "{(EgoVehicle↦0.0),(Vehicles2↦0.0),(Vehicles3↦0.0),(Vehicles4↦0.0),(Vehicles5↦0.0)}",
        "Reward": "0.7333333453642153",
        "VehiclesAx": "{(EgoVehicle↦-2.384185791015625E-06),(Vehicles2↦0.01928318291902542),(Vehicles3↦0.009233616292476654),(Vehicles4↦0.05619283765554428),(Vehicles5↦-0.018286295235157013)}",
        "VehiclesVx": "{(EgoVehicle↦20.0),(Vehicles2↦-0.48342857509851456),(Vehicles3↦0.39851512759923935),(Vehicles4↦-0.38770388811826706),(Vehicles5↦-0.6317693740129471)}",
        "VehiclesY": "{(EgoVehicle↦8.000000238418579),(Vehicles2↦-4.0000001192092896),(Vehicles3↦0.0),(Vehicles4↦-4.0000001192092896),(Vehicles5↦-8.000000238418579)}",
        "VehiclesVy": "{(EgoVehicle↦0.0),(Vehicles2↦0.0),(Vehicles3↦0.0),(Vehicles4↦0.0),(Vehicles5↦0.0)}",
        "VehiclesX": "{(EgoVehicle↦200.0),(Vehicles2↦2.9217444360256195),(Vehicles3↦46.618303656578064),(Vehicles4↦58.514803647994995),(Vehicles5↦60.641682147979736)}"
      },
      "probabilisticVariables": null,
      "activating": [
        "LANE_RIGHT_22"
      ],
      "activatingOnlyWhenExecuted": true,
      "updating": null,
      "withPredicate": null
    },
    {
      "id": "LANE_RIGHT_22",
      "execute": "LANE_RIGHT",
      "after": "1000",
      "priority": 0,
      "additionalGuards": null,
      "activationKind": null,
      "fixedVariables": {
        "Crash": "FALSE",
        "PresentVehicles": "{EgoVehicle,Vehicles2,Vehicles3,Vehicles4,Vehicles5}",
        "VehiclesAy": "{(EgoVehicle↦0.0),(Vehicles2↦0.0),(Vehicles3↦0.0),(Vehicles4↦0.0),(Vehicles5↦0.0)}",
        "Reward": "0.7333333349176471",
        "VehiclesAx": "{(EgoVehicle↦0.0),(Vehicles2↦0.02196371555328369),(Vehicles3↦0.009054318070411682),(Vehicles4↦0.05299776792526245),(Vehicles5↦-0.016856268048286438)}",
        "VehiclesVx": "{(EgoVehicle↦20.0),(Vehicles2↦-0.46146485954523087),(Vehicles3↦0.40756944566965103),(Vehicles4↦-0.3347061201930046),(Vehicles5↦-0.6486256420612335)}",
        "VehiclesY": "{(EgoVehicle↦8.000000238418579),(Vehicles2↦-4.0000001192092896),(Vehicles3↦0.0),(Vehicles4↦-4.0000001192092896),(Vehicles5↦-8.000000238418579)}",
        "VehiclesVy": "{(EgoVehicle↦0.0),(Vehicles2↦0.0),(Vehicles3↦0.0),(Vehicles4↦0.0),(Vehicles5↦0.0)}",
        "VehiclesX": "{(EgoVehicle↦200.0),(Vehicles2↦2.4469060823321342),(Vehicles3↦47.020453214645386),(Vehicles4↦58.1485390663147),(Vehicles5↦60.00304818153381)}"
      },
      "probabilisticVariables": null,
      "activating": [
        "LANE_RIGHT_23"
      ],
      "activatingOnlyWhenExecuted": true,
      "updating": null,
      "withPredicate": null
    },
    {
      "id": "LANE_RIGHT_23",
      "execute": "LANE_RIGHT",
      "after": "1000",
      "priority": 0,
      "additionalGuards": null,
      "activationKind": null,
      "fixedVariables": {
        "Crash": "FALSE",
        "PresentVehicles": "{EgoVehicle,Vehicles2,Vehicles3,Vehicles4,Vehicles5}",
        "VehiclesAy": "{(EgoVehicle↦0.0),(Vehicles2↦0.0),(Vehicles3↦0.0),(Vehicles4↦0.0),(Vehicles5↦0.0)}",
        "Reward": "0.7333333335419673",
        "VehiclesAx": "{(EgoVehicle↦0.0),(Vehicles2↦0.0241817906498909),(Vehicles3↦0.008879080414772034),(Vehicles4↦0.05024898797273636),(Vehicles5↦-0.015272721648216248)}",
        "VehiclesVx": "{(EgoVehicle↦20.0),(Vehicles2↦-0.43728306889533997),(Vehicles3↦0.41644852608442307),(Vehicles4↦-0.28445713222026825),(Vehicles5↦-0.6638983637094498)}",
        "VehiclesY": "{(EgoVehicle↦8.000000238418579),(Vehicles2↦-4.0000001192092896),(Vehicles3↦0.0),(Vehicles4↦-4.0000001192092896),(Vehicles5↦-8.000000238418579)}",
        "VehiclesVy": "{(EgoVehicle↦0.0),(Vehicles2↦0.0),(Vehicles3↦0.0),(Vehicles4↦0.0),(Vehicles5↦0.0)}",
        "VehiclesX": "{(EgoVehicle↦200.0),(Vehicles2↦1.99495367705822),(Vehicles3↦47.4315881729126),(Vehicles4↦57.83413648605347),(Vehicles5↦59.34818387031555)}"
      },
      "probabilisticVariables": null,
      "activating": [
        "LANE_RIGHT_24"
      ],
      "activatingOnlyWhenExecuted": true,
      "updating": null,
      "withPredicate": null
    },
    {
      "id": "LANE_RIGHT_24",
      "execute": "LANE_RIGHT",
      "after": "1000",
      "priority": 0,
      "additionalGuards": null,
      "activationKind": null,
      "fixedVariables": {
        "Crash": "FALSE",
        "PresentVehicles": "{EgoVehicle,Vehicles2,Vehicles3,Vehicles4,Vehicles5}",
        "VehiclesAy": "{(EgoVehicle↦0.0),(Vehicles2↦0.0),(Vehicles3↦0.0),(Vehicles4↦0.0),(Vehicles5↦0.0)}",
        "Reward": "0.7333333333608077",
        "VehiclesAx": "{(EgoVehicle↦0.0),(Vehicles2↦0.025984421372413635),(Vehicles3↦0.00870540738105774),(Vehicles4↦0.04785127937793732),(Vehicles5↦-0.013577714562416077)}",
        "VehiclesVx": "{(EgoVehicle↦20.0),(Vehicles2↦-0.41129864752292633),(Vehicles3↦0.4251539334654808),(Vehicles4↦-0.23660585284233093),(Vehicles5↦-0.6774760782718658)}",
        "VehiclesY": "{(EgoVehicle↦8.000000238418579),(Vehicles2↦-4.0000001192092896),(Vehicles3↦0.0),(Vehicles4↦-4.0000001192092896),(Vehicles5↦-8.000000238418579)}",
        "VehiclesVy": "{(EgoVehicle↦0.0),(Vehicles2↦0.0),(Vehicles3↦0.0),(Vehicles4↦0.0),(Vehicles5↦0.0)}",
        "VehiclesX": "{(EgoVehicle↦200.0),(Vehicles2↦1.5679355710744858),(Vehicles3↦47.85153269767761),(Vehicles4↦57.5689971446991),(Vehicles5↦58.67871642112732)}"
      },
      "probabilisticVariables": null,
      "activating": [
        "LANE_RIGHT_25"
      ],
      "activatingOnlyWhenExecuted": true,
      "updating": null,
      "withPredicate": null
    },
    {
      "id": "LANE_RIGHT_25",
      "execute": "LANE_RIGHT",
      "after": "1000",
      "priority": 0,
      "additionalGuards": null,
      "activationKind": null,
      "fixedVariables": {
        "Crash": "FALSE",
        "PresentVehicles": "{EgoVehicle,Vehicles2,Vehicles3,Vehicles4,Vehicles5}",
        "VehiclesAy": "{(EgoVehicle↦0.0),(Vehicles2↦0.0),(Vehicles3↦0.0),(Vehicles4↦0.0),(Vehicles5↦0.0)}",
        "Reward": "0.7333333333369514",
        "VehiclesAx": "{(EgoVehicle↦0.0),(Vehicles2↦0.02742089331150055),(Vehicles3↦0.008532889187335968),(Vehicles4↦0.04573225975036621),(Vehicles5↦-0.011807829141616821)}",
        "VehiclesVx": "{(EgoVehicle↦20.0),(Vehicles2↦-0.3838777542114258),(Vehicles3↦0.4336868226528168),(Vehicles4↦-0.19087359309196472),(Vehicles5↦-0.6892839074134827)}",
        "VehiclesY": "{(EgoVehicle↦8.000000238418579),(Vehicles2↦-4.0000001192092896),(Vehicles3↦0.0),(Vehicles4↦-4.0000001192092896),(Vehicles5↦-8.000000238418579)}",
        "VehiclesVy": "{(EgoVehicle↦0.0),(Vehicles2↦0.0),(Vehicles3↦0.0),(Vehicles4↦0.0),(Vehicles5↦0.0)}",
        "VehiclesX": "{(EgoVehicle↦200.0),(Vehicles2↦1.1675038374960423),(Vehicles3↦48.28011393547058),(Vehicles4↦57.35084414482117),(Vehicles5↦57.9963743686676)}"
      },
      "probabilisticVariables": null,
      "activating": [
        "LANE_RIGHT_26"
      ],
      "activatingOnlyWhenExecuted": true,
      "updating": null,
      "withPredicate": null
    },
    {
      "id": "LANE_RIGHT_26",
      "execute": "LANE_RIGHT",
      "after": "1000",
      "priority": 0,
      "additionalGuards": null,
      "activationKind": null,
      "fixedVariables": {
        "Crash": "FALSE",
        "PresentVehicles": "{EgoVehicle,Vehicles2,Vehicles3,Vehicles4,Vehicles5}",
        "VehiclesAy": "{(EgoVehicle↦0.0),(Vehicles2↦0.0),(Vehicles3↦0.0),(Vehicles4↦0.0),(Vehicles5↦0.0)}",
        "Reward": "0.7333333333338098",
        "VehiclesAx": "{(EgoVehicle↦0.0),(Vehicles2↦0.02853821963071823),(Vehicles3↦0.008361302316188812),(Vehicles4↦0.043836310505867004),(Vehicles5↦-0.009995251893997192)}",
        "VehiclesVx": "{(EgoVehicle↦20.0),(Vehicles2↦-0.35533953458070755),(Vehicles3↦0.4420481249690056),(Vehicles4↦-0.14703728258609772),(Vehicles5↦-0.6992791593074799)}",
        "VehiclesY": "{(EgoVehicle↦8.000000238418579),(Vehicles2↦-4.0000001192092896),(Vehicles3↦0.0),(Vehicles4↦-4.0000001192092896),(Vehicles5↦-8.000000238418579)}",
        "VehiclesVy": "{(EgoVehicle↦0.0),(Vehicles2↦0.0),(Vehicles3↦0.0),(Vehicles4↦0.0),(Vehicles5↦0.0)}",
        "VehiclesX": "{(EgoVehicle↦200.0),(Vehicles2↦0.7949636317789555),(Vehicles3↦48.717159032821655),(Vehicles4↦57.177650928497314),(Vehicles5↦57.30294585227966)}"
      },
      "probabilisticVariables": null,
      "activating": [
        "LANE_RIGHT_27"
      ],
      "activatingOnlyWhenExecuted": true,
      "updating": null,
      "withPredicate": null
    },
    {
      "id": "LANE_RIGHT_27",
      "execute": "LANE_RIGHT",
      "after": "1000",
      "priority": 0,
      "additionalGuards": null,
      "activationKind": null,
      "fixedVariables": {
        "Crash": "FALSE",
        "PresentVehicles": "{EgoVehicle,Vehicles2,Vehicles3,Vehicles4,Vehicles5}",
        "VehiclesAy": "{(EgoVehicle↦0.0),(Vehicles2↦0.0),(Vehicles3↦0.0),(Vehicles4↦0.0),(Vehicles5↦0.0)}",
        "Reward": "0.733333333333396",
        "VehiclesAx": "{(EgoVehicle↦0.0),(Vehicles2↦0.02938009798526764),(Vehicles3↦0.008190944790840149),(Vehicles4↦-0.5604097992181778),(Vehicles5↦0.5943623930215836)}",
        "VehiclesVx": "{(EgoVehicle↦20.0),(Vehicles2↦-0.3259594365954399),(Vehicles3↦0.45023906975984573),(Vehicles4↦-0.7074470818042755),(Vehicles5↦-0.1049167662858963)}",
        "VehiclesY": "{(EgoVehicle↦8.000000238418579),(Vehicles2↦-4.0000001192092896),(Vehicles3↦0.0),(Vehicles4↦-8.000000238418579),(Vehicles5↦-4.0000001192092896)}",
        "VehiclesVy": "{(EgoVehicle↦0.0),(Vehicles2↦0.0),(Vehicles3↦0.0),(Vehicles4↦0.0),(Vehicles5↦0.0)}",
        "VehiclesX": "{(EgoVehicle↦200.0),(Vehicles2↦0.45131873339414597),(Vehicles3↦49.162498116493225),(Vehicles4↦56.60025477409363),(Vehicles5↦57.04759359359741)}"
      },
      "probabilisticVariables": null,
      "activating": [
        "SLOWER_28"
      ],
      "activatingOnlyWhenExecuted": true,
      "updating": null,
      "withPredicate": null
    },
    {
      "id": "SLOWER_28",
      "execute": "SLOWER",
      "after": "1000",
      "priority": 0,
      "additionalGuards": null,
      "activationKind": null,
      "fixedVariables": {
        "Crash": "FALSE",
        "PresentVehicles": "{EgoVehicle,Vehicles2,Vehicles3,Vehicles4,Vehicles5}",
        "VehiclesAy": "{(EgoVehicle↦0.0),(Vehicles2↦0.0),(Vehicles3↦0.0),(Vehicles4↦0.0),(Vehicles5↦0.0)}",
        "Reward": "0.7333333333333415",
        "VehiclesAx": "{(EgoVehicle↦0.0),(Vehicles2↦0.02998586744070053),(Vehicles3↦0.008021779358386993),(Vehicles4↦-0.006349608302116394),(Vehicles5↦0.04055176395922899)}",
        "VehiclesVx": "{(EgoVehicle↦20.0),(Vehicles2↦-0.2959735691547394),(Vehicles3↦0.4582608491182327),(Vehicles4↦-0.7137966901063919),(Vehicles5↦-0.06436500232666731)}",
        "VehiclesY": "{(EgoVehicle↦8.000000238418579),(Vehicles2↦-4.0000001192092896),(Vehicles3↦0.0),(Vehicles4↦-8.000000238418579),(Vehicles5↦-4.0000001192092896)}",
        "VehiclesVy": "{(EgoVehicle↦0.0),(Vehicles2↦0.0),(Vehicles3↦0.0),(Vehicles4↦0.0),(Vehicles5↦0.0)}",
        "VehiclesX": "{(EgoVehicle↦200.0),(Vehicles2↦0.1373136998154223),(Vehicles3↦49.61595833301544),(Vehicles4↦55.89011907577515),(Vehicles5↦56.959015130996704)}"
      },
      "probabilisticVariables": null,
      "activating": [
        "SLOWER_29"
      ],
      "activatingOnlyWhenExecuted": true,
      "updating": null,
      "withPredicate": null
    },
    {
      "id": "SLOWER_29",
      "execute": "SLOWER",
      "after": "1000",
      "priority": 0,
      "additionalGuards": null,
      "activationKind": null,
      "fixedVariables": {
        "Crash": "FALSE",
        "PresentVehicles": "{EgoVehicle,Vehicles2,Vehicles3,Vehicles4,Vehicles5}",
        "VehiclesAy": "{(EgoVehicle↦0.0),(Vehicles2↦0.0),(Vehicles3↦0.0),(Vehicles4↦0.0),(Vehicles5↦0.0)}",
        "Reward": "0.7333333333333344",
        "VehiclesAx": "{(EgoVehicle↦0.0),(Vehicles2↦0.024316012859344482),(Vehicles3↦-0.4679170501185581),(Vehicles4↦-0.004560574889183044),(Vehicles5↦0.16459023114293814)}",
        "VehiclesVx": "{(EgoVehicle↦20.0),(Vehicles2↦-0.2716575562953949),(Vehicles3↦-0.009656201000325382),(Vehicles4↦-0.718357264995575),(Vehicles5↦0.10022522881627083)}",
        "VehiclesY": "{(EgoVehicle↦8.000000238418579),(Vehicles2↦-4.0000001192092896),(Vehicles3↦0.0),(Vehicles4↦-8.000000238418579),(Vehicles5↦-4.0000001192092896)}",
        "VehiclesVy": "{(EgoVehicle↦0.0),(Vehicles2↦0.0),(Vehicles3↦0.0),(Vehicles4↦0.0),(Vehicles5↦0.0)}",
        "VehiclesX": "{(EgoVehicle↦200.0),(Vehicles2↦-0.14757185708731413),(Vehicles3↦49.96855556964874),(Vehicles4↦55.17435669898987),(Vehicles5↦56.875449419021606)}"
      },
      "probabilisticVariables": null,
      "activating": [
        "SLOWER_30"
      ],
      "activatingOnlyWhenExecuted": true,
      "updating": null,
      "withPredicate": null
    },
    {
      "id": "SLOWER_30",
      "execute": "SLOWER",
      "after": "1000",
      "priority": 0,
      "additionalGuards": null,
      "activationKind": null,
      "fixedVariables": {
        "Crash": "FALSE",
        "PresentVehicles": "{EgoVehicle,Vehicles2,Vehicles3,Vehicles4,Vehicles5}",
        "VehiclesAy": "{(EgoVehicle↦0.0),(Vehicles2↦0.0),(Vehicles3↦0.0),(Vehicles4↦0.0),(Vehicles5↦0.0)}",
        "Reward": "0.7333333333333334",
        "VehiclesAx": "{(EgoVehicle↦0.0),(Vehicles2↦0.05590476095676422),(Vehicles3↦-0.37778375030029565),(Vehicles4↦0.27892686426639557),(Vehicles5↦-0.10449999768752605)}",
        "VehiclesVx": "{(EgoVehicle↦20.0),(Vehicles2↦-0.21575279533863068),(Vehicles3↦-0.38743995130062103),(Vehicles4↦-0.4394304007291794),(Vehicles5↦-0.004274768871255219)}",
        "VehiclesY": "{(EgoVehicle↦8.000000238418579),(Vehicles2↦-4.0000001192092896),(Vehicles3↦0.0),(Vehicles4↦-8.000000238418579),(Vehicles5↦-4.0000001192092896)}",
        "VehiclesVy": "{(EgoVehicle↦0.0),(Vehicles2↦0.0),(Vehicles3↦0.0),(Vehicles4↦0.0),(Vehicles5↦0.0)}",
        "VehiclesX": "{(EgoVehicle↦200.0),(Vehicles2↦-0.39327568374574184),(Vehicles3↦49.781784415245056),(Vehicles4↦54.44532632827759),(Vehicles5↦57.01904296875)}"
      },
      "probabilisticVariables": null,
      "activating": [
        "SLOWER_31"
      ],
      "activatingOnlyWhenExecuted": true,
      "updating": null,
      "withPredicate": null
    },
    {
      "id": "SLOWER_31",
      "execute": "SLOWER",
      "after": "1000",
      "priority": 0,
      "additionalGuards": null,
      "activationKind": null,
      "fixedVariables": {
        "Crash": "FALSE",
        "PresentVehicles": "{EgoVehicle,Vehicles2,Vehicles3,Vehicles4,Vehicles5}",
        "VehiclesAy": "{(EgoVehicle↦0.0),(Vehicles2↦0.0),(Vehicles3↦0.0),(Vehicles4↦0.0),(Vehicles5↦0.0)}",
        "Reward": "0.7333333333333334",
        "VehiclesAx": "{(EgoVehicle↦0.0),(Vehicles2↦0.00876065343618393),(Vehicles3↦-0.15048813074827194),(Vehicles4↦0.6098460592329502),(Vehicles5↦-0.14453411276917905)}",
        "VehiclesVx": "{(EgoVehicle↦20.0),(Vehicles2↦-0.20699214190244675),(Vehicles3↦-0.537928082048893),(Vehicles4↦0.17041565850377083),(Vehicles5↦-0.14880888164043427)}",
        "VehiclesY": "{(EgoVehicle↦8.000000238418579),(Vehicles2↦-4.0000001192092896),(Vehicles3↦0.0),(Vehicles4↦-8.000000238418579),(Vehicles5↦-4.0000001192092896)}",
        "VehiclesVy": "{(EgoVehicle↦0.0),(Vehicles2↦0.0),(Vehicles3↦0.0),(Vehicles4↦0.0),(Vehicles5↦0.0)}",
        "VehiclesX": "{(EgoVehicle↦200.0),(Vehicles2↦-0.6032942794263363),(Vehicles3↦49.322107434272766),(Vehicles4↦54.27557826042175),(Vehicles5↦56.94633722305298)}"
      },
      "probabilisticVariables": null,
      "activating": [
        "SLOWER_32"
      ],
      "activatingOnlyWhenExecuted": true,
      "updating": null,
      "withPredicate": null
    },
    {
      "id": "SLOWER_32",
      "execute": "SLOWER",
      "after": "1000",
      "priority": 0,
      "additionalGuards": null,
      "activationKind": null,
      "fixedVariables": {
        "Crash": "FALSE",
        "PresentVehicles": "{EgoVehicle,Vehicles2,Vehicles3,Vehicles4,Vehicles5}",
        "VehiclesAy": "{(EgoVehicle↦0.0),(Vehicles2↦0.0),(Vehicles3↦0.0),(Vehicles4↦0.0),(Vehicles5↦0.0)}",
        "Reward": "0.7333333333333334",
        "VehiclesAx": "{(EgoVehicle↦0.0),(Vehicles2↦-0.005998983979225159),(Vehicles3↦-0.042375847697257996),(Vehicles4↦0.34853706136345863),(Vehicles5↦-0.048597753047943115)}",
        "VehiclesVx": "{(EgoVehicle↦20.0),(Vehicles2↦-0.2129911258816719),(Vehicles3↦-0.580303929746151),(Vehicles4↦0.5189527198672295),(Vehicles5↦-0.19740663468837738)}",
        "VehiclesY": "{(EgoVehicle↦8.000000238418579),(Vehicles2↦-4.0000001192092896),(Vehicles3↦0.0),(Vehicles4↦-8.000000238418579),(Vehicles5↦-4.0000001192092896)}",
        "VehiclesVy": "{(EgoVehicle↦0.0),(Vehicles2↦0.0),(Vehicles3↦0.0),(Vehicles4↦0.0),(Vehicles5↦0.0)}",
        "VehiclesX": "{(EgoVehicle↦200.0),(Vehicles2↦-0.8123226463794708),(Vehicles3↦48.76137673854828),(Vehicles4↦54.60177659988403),(Vehicles5↦56.772804260253906)}"
      },
      "probabilisticVariables": null,
      "activating": [
        "SLOWER_33"
      ],
      "activatingOnlyWhenExecuted": true,
      "updating": null,
      "withPredicate": null
    },
    {
      "id": "SLOWER_33",
      "execute": "SLOWER",
      "after": "1000",
      "priority": 0,
      "additionalGuards": null,
      "activationKind": null,
      "fixedVariables": {
        "Crash": "FALSE",
        "PresentVehicles": "{EgoVehicle,Vehicles2,Vehicles3,Vehicles4,Vehicles5}",
        "VehiclesAy": "{(EgoVehicle↦0.0),(Vehicles2↦0.0),(Vehicles3↦0.0),(Vehicles4↦0.0),(Vehicles5↦0.0)}",
        "Reward": "0.7333333333333334",
        "VehiclesAx": "{(EgoVehicle↦0.0),(Vehicles2↦-0.005715079605579376),(Vehicles3↦0.010059066116809845),(Vehicles4↦0.18806803971529007),(Vehicles5↦-0.00039031729102134705)}",
        "VehiclesVx": "{(EgoVehicle↦20.0),(Vehicles2↦-0.21870620548725128),(Vehicles3↦-0.5702448636293411),(Vehicles4↦0.7070207595825195),(Vehicles5↦-0.19779695197939873)}",
        "VehiclesY": "{(EgoVehicle↦8.000000238418579),(Vehicles2↦-4.0000001192092896),(Vehicles3↦0.0),(Vehicles4↦-8.000000238418579),(Vehicles5↦-4.0000001192092896)}",
        "VehiclesVy": "{(EgoVehicle↦0.0),(Vehicles2↦0.0),(Vehicles3↦0.0),(Vehicles4↦0.0),(Vehicles5↦0.0)}",
        "VehiclesX": "{(EgoVehicle↦200.0),(Vehicles2↦-1.0279103182256222),(Vehicles3↦48.182281851768494),(Vehicles4↦55.205631256103516),(Vehicles5↦56.57258629798889)}"
      },
      "probabilisticVariables": null,
      "activating": [
        "SLOWER_34"
      ],
      "activatingOnlyWhenExecuted": true,
      "updating": null,
      "withPredicate": null
    },
    {
      "id": "SLOWER_34",
      "execute": "SLOWER",
      "after": "1000",
      "priority": 0,
      "additionalGuards": null,
      "activationKind": null,
      "fixedVariables": {
        "Crash": "FALSE",
        "PresentVehicles": "{EgoVehicle,Vehicles2,Vehicles3,Vehicles4,Vehicles5}",
        "VehiclesAy": "{(EgoVehicle↦0.0),(Vehicles2↦0.0),(Vehicles3↦0.0),(Vehicles4↦0.0),(Vehicles5↦0.0)}",
        "Reward": "0.7333333333333334",
        "VehiclesAx": "{(EgoVehicle↦0.0),(Vehicles2↦-0.0005028955638408661),(Vehicles3↦0.034813471138477325),(Vehicles4↦0.09515583515167236),(Vehicles5↦0.023446418344974518)}",
        "VehiclesVx": "{(EgoVehicle↦20.0),(Vehicles2↦-0.21920910105109215),(Vehicles3↦-0.5354313924908638),(Vehicles4↦0.8021765947341919),(Vehicles5↦-0.1743505336344242)}",
        "VehiclesY": "{(EgoVehicle↦8.000000238418579),(Vehicles2↦-4.0000001192092896),(Vehicles3↦0.0),(Vehicles4↦-8.000000238418579),(Vehicles5↦-4.0000001192092896)}",
        "VehiclesVy": "{(EgoVehicle↦0.0),(Vehicles2↦0.0),(Vehicles3↦0.0),(Vehicles4↦0.0),(Vehicles5↦0.0)}",
        "VehiclesX": "{(EgoVehicle↦200.0),(Vehicles2↦-1.2473013252019882),(Vehicles3↦47.624680399894714),(Vehicles4↦55.95619082450867),(Vehicles5↦56.38288855552673)}"
      },
      "probabilisticVariables": null,
      "activating": [
        "SLOWER_35"
      ],
      "activatingOnlyWhenExecuted": true,
      "updating": null,
      "withPredicate": null
    },
    {
      "id": "SLOWER_35",
      "execute": "SLOWER",
      "after": "1000",
      "priority": 0,
      "additionalGuards": null,
      "activationKind": null,
      "fixedVariables": {
        "Crash": "FALSE",
        "PresentVehicles": "{EgoVehicle,Vehicles2,Vehicles3,Vehicles4,Vehicles5}",
        "VehiclesAy": "{(EgoVehicle↦0.0),(Vehicles2↦0.0),(Vehicles3↦0.0),(Vehicles4↦0.0),(Vehicles5↦0.0)}",
        "Reward": "0.7333333333333334",
        "VehiclesAx": "{(EgoVehicle↦0.0),(Vehicles2↦0.005505271255970001),(Vehicles3↦0.04554908722639084),(Vehicles4↦-0.9419003129005432),(Vehicles5↦1.0197079367935658)}",
        "VehiclesVx": "{(EgoVehicle↦20.0),(Vehicles2↦-0.21370382979512215),(Vehicles3↦-0.48988230526447296),(Vehicles4↦-0.13972371816635132),(Vehicles5↦0.8453574031591415)}",
        "VehiclesY": "{(EgoVehicle↦8.000000238418579),(Vehicles2↦-4.0000001192092896),(Vehicles3↦0.0),(Vehicles4↦-4.0000001192092896),(Vehicles5↦-8.000000238418579)}",
        "VehiclesVy": "{(EgoVehicle↦0.0),(Vehicles2↦0.0),(Vehicles3↦0.0),(Vehicles4↦0.0),(Vehicles5↦0.0)}",
        "VehiclesX": "{(EgoVehicle↦200.0),(Vehicles2↦-1.4647720381617546),(Vehicles3↦47.10696637630463),(Vehicles4↦56.221818923950195),(Vehicles5↦56.77866339683533)}"
      },
      "probabilisticVariables": null,
      "activating": [
        "LANE_RIGHT_36"
      ],
      "activatingOnlyWhenExecuted": true,
      "updating": null,
      "withPredicate": null
    },
    {
      "id": "LANE_RIGHT_36",
      "execute": "LANE_RIGHT",
      "after": "1000",
      "priority": 0,
      "additionalGuards": null,
      "activationKind": null,
      "fixedVariables": {
        "Crash": "FALSE",
        "PresentVehicles": "{EgoVehicle,Vehicles2,Vehicles3,Vehicles4,Vehicles5}",
        "VehiclesAy": "{(EgoVehicle↦0.0),(Vehicles2↦0.0),(Vehicles3↦0.0),(Vehicles4↦0.0),(Vehicles5↦0.0)}",
        "Reward": "0.7333333333333334",
        "VehiclesAx": "{(EgoVehicle↦0.0),(Vehicles2↦0.010822713375091553),(Vehicles3↦0.04919692873954773),(Vehicles4↦0.039304764941334724),(Vehicles5↦0.014673620462417603)}",
        "VehiclesVx": "{(EgoVehicle↦20.0),(Vehicles2↦-0.2028811164200306),(Vehicles3↦-0.44068537652492523),(Vehicles4↦-0.1004189532250166),(Vehicles5↦0.8600310236215591)}",
        "VehiclesY": "{(EgoVehicle↦8.000000238418579),(Vehicles2↦-4.0000001192092896),(Vehicles3↦0.0),(Vehicles4↦-4.0000001192092896),(Vehicles5↦-8.000000238418579)}",
        "VehiclesVy": "{(EgoVehicle↦0.0),(Vehicles2↦0.0),(Vehicles3↦0.0),(Vehicles4↦0.0),(Vehicles5↦0.0)}",
        "VehiclesX": "{(EgoVehicle↦200.0),(Vehicles2↦-1.6745306551456451),(Vehicles3↦46.63664698600769),(Vehicles4↦56.09760880470276),(Vehicles5↦57.63153433799744)}"
      },
      "probabilisticVariables": null,
      "activating": [
        "FASTER_37"
      ],
      "activatingOnlyWhenExecuted": true,
      "updating": null,
      "withPredicate": null
    },
    {
      "id": "FASTER_37",
      "execute": "FASTER",
      "after": "1000",
      "priority": 0,
      "additionalGuards": null,
      "activationKind": null,
      "fixedVariables": {
        "Crash": "FALSE",
        "PresentVehicles": "{EgoVehicle,Vehicles2,Vehicles3,Vehicles4,Vehicles5}",
        "VehiclesAy": "{(EgoVehicle↦0.0),(Vehicles2↦0.0),(Vehicles3↦0.0),(Vehicles4↦0.0),(Vehicles5↦0.0)}",
        "Reward": "0.8491083676268861",
        "VehiclesAx": "{(EgoVehicle↦4.341564178466797),(Vehicles2↦-4.326486568897963),(Vehicles3↦-4.292232170701027),(Vehicles4↦-4.300851793959737),(Vehicles5↦-4.342343583703041)}",
        "VehiclesVx": "{(EgoVehicle↦24.341564178466797),(Vehicles2↦-4.529367685317993),(Vehicles3↦-4.732917547225952),(Vehicles4↦-4.401270747184753),(Vehicles5↦-3.482312560081482)}",
        "VehiclesY": "{(EgoVehicle↦8.000000238418579),(Vehicles2↦-4.0000001192092896),(Vehicles3↦0.0),(Vehicles4↦-4.0000001192092896),(Vehicles5↦-8.000000238418579)}",
        "VehiclesVy": "{(EgoVehicle↦0.0),(Vehicles2↦0.0),(Vehicles3↦0.0),(Vehicles4↦0.0),(Vehicles5↦0.0)}",
        "VehiclesX": "{(EgoVehicle↦200.0),(Vehicles2↦-4.266740381717682),(Vehicles3↦43.82070600986481),(Vehicles4↦53.618377447128296),(Vehicles5↦56.09707832336426)}"
      },
      "probabilisticVariables": null,
      "activating": [
        "SLOWER_38"
      ],
      "activatingOnlyWhenExecuted": true,
      "updating": null,
      "withPredicate": null
    },
    {
      "id": "SLOWER_38",
      "execute": "SLOWER",
      "after": "1000",
      "priority": 0,
      "additionalGuards": null,
      "activationKind": null,
      "fixedVariables": {
        "Crash": "FALSE",
        "PresentVehicles": "{EgoVehicle,Vehicles2,Vehicles3,Vehicles4,Vehicles5}",
        "VehiclesAy": "{(EgoVehicle↦0.0),(Vehicles2↦0.0),(Vehicles3↦0.0),(Vehicles4↦0.0),(Vehicles5↦0.0)}",
        "Reward": "0.7485794283843362",
        "VehiclesAx": "{(EgoVehicle↦-3.76983642578125),(Vehicles2↦3.788154721260071),(Vehicles3↦3.817637339234352),(Vehicles4↦3.810364753007889),(Vehicles5↦3.760748468339443)}",
        "VehiclesVx": "{(EgoVehicle↦20.571727752685547),(Vehicles2↦-0.7412129640579224),(Vehicles3↦-0.9152802079916),(Vehicles4↦-0.5909059941768646),(Vehicles5↦0.2784359082579613)}",
        "VehiclesY": "{(EgoVehicle↦8.000000238418579),(Vehicles2↦-4.0000001192092896),(Vehicles3↦0.0),(Vehicles4↦-4.0000001192092896),(Vehicles5↦-8.000000238418579)}",
        "VehiclesVy": "{(EgoVehicle↦0.0),(Vehicles2↦0.0),(Vehicles3↦0.0),(Vehicles4↦0.0),(Vehicles5↦0.0)}",
        "VehiclesX": "{(EgoVehicle↦200.0),(Vehicles2↦-6.709340959787369),(Vehicles3↦41.186732053756714),(Vehicles4↦51.31303668022156),(Vehicles5↦54.691267013549805)}"
      },
      "probabilisticVariables": null,
      "activating": [
        "SLOWER_39"
      ],
      "activatingOnlyWhenExecuted": true,
      "updating": null,
      "withPredicate": null
    },
    {
      "id": "SLOWER_39",
      "execute": "SLOWER",
      "after": "1000",
      "priority": 0,
      "additionalGuards": null,
      "activationKind": null,
      "fixedVariables": {
        "Crash": "FALSE",
        "PresentVehicles": "{EgoVehicle,Vehicles2,Vehicles3,Vehicles4,Vehicles5}",
        "VehiclesAy": "{(EgoVehicle↦0.0),(Vehicles2↦0.0),(Vehicles3↦0.0),(Vehicles4↦0.0),(Vehicles5↦0.0)}",
        "Reward": "0.7353410495540414",
        "VehiclesAx": "{(EgoVehicle↦-0.49643754959106445),(Vehicles2↦0.5171670764684677),(Vehicles3↦0.5419978499412537),(Vehicles4↦0.5360551457852125),(Vehicles5↦0.48292893916368484)}",
        "VehiclesVx": "{(EgoVehicle↦20.075290203094482),(Vehicles2↦-0.22404588758945465),(Vehicles3↦-0.3732823580503464),(Vehicles4↦-0.05485084839165211),(Vehicles5↦0.7613648474216461)}",
        "VehiclesY": "{(EgoVehicle↦8.000000238418579),(Vehicles2↦-4.0000001192092896),(Vehicles3↦0.0),(Vehicles4↦-4.0000001192092896),(Vehicles5↦-8.000000238418579)}",
        "VehiclesVy": "{(EgoVehicle↦0.0),(Vehicles2↦0.0),(Vehicles3↦0.0),(Vehicles4↦0.0),(Vehicles5↦0.0)}",
        "VehiclesX": "{(EgoVehicle↦200.0),(Vehicles2↦-7.168561965227127),(Vehicles3↦40.563735365867615),(Vehicles4↦51.01193189620972),(Vehicles5↦55.23841977119446)}"
      },
      "probabilisticVariables": null,
      "activating": [
        "FASTER_40"
      ],
      "activatingOnlyWhenExecuted": true,
      "updating": null,
      "withPredicate": null
    },
    {
      "id": "FASTER_40",
      "execute": "FASTER",
      "after": "1000",
      "priority": 0,
      "additionalGuards": null,
      "activationKind": null,
      "fixedVariables": {
        "Crash": "FALSE",
        "PresentVehicles": "{EgoVehicle,Vehicles2,Vehicles3,Vehicles4,Vehicles5}",
        "VehiclesAy": "{(EgoVehicle↦0.0),(Vehicles2↦0.0),(Vehicles3↦0.0),(Vehicles4↦0.0),(Vehicles5↦0.0)}",
        "Reward": "0.8493727582403127",
        "VehiclesAx": "{(EgoVehicle↦4.276187419891357),(Vehicles2↦-4.253700599074364),(Vehicles3↦-4.23310823738575),(Vehicles4↦-4.237788049504161),(Vehicles5↦-4.2920176684856415)}",
        "VehiclesVx": "{(EgoVehicle↦24.35147762298584),(Vehicles2↦-4.477746486663818),(Vehicles3↦-4.606390595436096),(Vehicles4↦-4.292638897895813),(Vehicles5↦-3.5306528210639954)}",
        "VehiclesY": "{(EgoVehicle↦8.000000238418579),(Vehicles2↦-4.0000001192092896),(Vehicles3↦0.0),(Vehicles4↦-4.0000001192092896),(Vehicles5↦-8.000000238418579)}",
        "VehiclesVy": "{(EgoVehicle↦0.0),(Vehicles2↦0.0),(Vehicles3↦0.0),(Vehicles4↦0.0),(Vehicles5↦0.0)}",
        "VehiclesX": "{(EgoVehicle↦200.0),(Vehicles2↦-9.742728620767593),(Vehicles3↦37.84888982772827),(Vehicles4↦48.613545298576355),(Vehicles5↦53.634583950042725)}"
      },
      "probabilisticVariables": null,
      "activating": [
        "SLOWER_41"
      ],
      "activatingOnlyWhenExecuted": true,
      "updating": null,
      "withPredicate": null
    },
    {
      "id": "SLOWER_41",
      "execute": "SLOWER",
      "after": "1000",
      "priority": 0,
      "additionalGuards": null,
      "activationKind": null,
      "fixedVariables": {
        "Crash": "FALSE",
        "PresentVehicles": "{EgoVehicle,Vehicles2,Vehicles3,Vehicles4,Vehicles5}",
        "VehiclesAy": "{(EgoVehicle↦0.0),(Vehicles2↦0.0),(Vehicles3↦0.0),(Vehicles4↦0.0),(Vehicles5↦3.552713678800501E-14)}",
        "Reward": "0.7486142452552401",
        "VehiclesAx": "{(EgoVehicle↦-3.7784433364868164),(Vehicles2↦3.69040384888649),(Vehicles3↦4.12928756326437),(Vehicles4↦4.5234280079603195),(Vehicles5↦3.417213186621666)}",
        "VehiclesVx": "{(EgoVehicle↦20.573034286499023),(Vehicles2↦-0.7873426377773285),(Vehicles3↦-0.4771030321717262),(Vehicles4↦0.23078911006450653),(Vehicles5↦-0.1134396344423294)}",
        "VehiclesY": "{(EgoVehicle↦8.000000238418579),(Vehicles2↦0.0),(Vehicles3↦-4.0000001192092896),(Vehicles4↦-8.000000238418579),(Vehicles5↦-4.0000001192092896)}",
        "VehiclesVy": "{(EgoVehicle↦0.0),(Vehicles2↦0.0),(Vehicles3↦0.0),(Vehicles4↦0.0),(Vehicles5↦3.552713678800501E-14)}",
        "VehiclesX": "{(EgoVehicle↦200.0),(Vehicles2↦35.34334599971771),(Vehicles3↦46.42026126384735),(Vehicles4↦52.181607484817505),(Vehicles5↦107.50011205673218)}"
      },
      "probabilisticVariables": null,
      "activating": [
        "SLOWER_42"
      ],
      "activatingOnlyWhenExecuted": true,
      "updating": null,
      "withPredicate": null
    },
    {
      "id": "SLOWER_42",
      "execute": "SLOWER",
      "after": "1000",
      "priority": 0,
      "additionalGuards": null,
      "activationKind": null,
      "fixedVariables": {
        "Crash": "FALSE",
        "PresentVehicles": "{EgoVehicle,Vehicles2,Vehicles3,Vehicles4,Vehicles5}",
        "VehiclesAy": "{(EgoVehicle↦0.0),(Vehicles2↦0.0),(Vehicles3↦0.0),(Vehicles4↦0.0),(Vehicles5↦3.552713678800501E-14)}",
        "Reward": "0.7353456344917736",
        "VehiclesAx": "{(EgoVehicle↦-0.4975724220275879),(Vehicles2↦0.5358077958226204),(Vehicles3↦0.5333567596971989),(Vehicles4↦0.48002302646636963),(Vehicles5↦0.5285730585455894)}",
        "VehiclesVx": "{(EgoVehicle↦20.075461864471436),(Vehicles2↦-0.2515348419547081),(Vehicles3↦0.05625372752547264),(Vehicles4↦0.7108121365308762),(Vehicles5↦0.41513342410326004)}",
        "VehiclesY": "{(EgoVehicle↦8.000000238418579),(Vehicles2↦0.0),(Vehicles3↦-4.0000001192092896),(Vehicles4↦-8.000000238418579),(Vehicles5↦-4.0000001192092896)}",
        "VehiclesVy": "{(EgoVehicle↦0.0),(Vehicles2↦0.0),(Vehicles3↦0.0),(Vehicles4↦0.0),(Vehicles5↦0.0)}",
        "VehiclesX": "{(EgoVehicle↦200.0),(Vehicles2↦34.84597206115723),(Vehicles3↦46.23206555843353),(Vehicles4↦52.679890394210815),(Vehicles5↦107.67370462417603)}"
      },
      "probabilisticVariables": null,
      "activating": [
        "SLOWER_43"
      ],
      "activatingOnlyWhenExecuted": true,
      "updating": null,
      "withPredicate": null
    },
    {
      "id": "SLOWER_43",
      "execute": "SLOWER",
      "after": "1000",
      "priority": 0,
      "additionalGuards": null,
      "activationKind": null,
      "fixedVariables": {
        "Crash": "FALSE",
        "PresentVehicles": "{EgoVehicle,Vehicles2,Vehicles3,Vehicles4,Vehicles5}",
        "VehiclesAy": "{(EgoVehicle↦0.0),(Vehicles2↦0.0),(Vehicles3↦0.0),(Vehicles4↦0.0),(Vehicles5↦0.0)}",
        "Reward": "0.7335983277245682",
        "VehiclesAx": "{(EgoVehicle↦-0.06552457809448242),(Vehicles2↦0.1015421561896801),(Vehicles3↦0.10004159063100815),(Vehicles4↦0.047775134444236755),(Vehicles5↦0.09489849209785461)}",
        "VehiclesVx": "{(EgoVehicle↦20.009937286376953),(Vehicles2↦-0.149992685765028),(Vehicles3↦0.1562953181564808),(Vehicles4↦0.7585872709751129),(Vehicles5↦0.5100319162011147)}",
        "VehiclesY": "{(EgoVehicle↦8.000000238418579),(Vehicles2↦0.0),(Vehicles3↦-4.0000001192092896),(Vehicles4↦-8.000000238418579),(Vehicles5↦-4.0000001192092896)}",
        "VehiclesVy": "{(EgoVehicle↦0.0),(Vehicles2↦0.0),(Vehicles3↦0.0),(Vehicles4↦0.0),(Vehicles5↦0.0)}",
        "VehiclesX": "{(EgoVehicle↦200.0),(Vehicles2↦34.6451610326767),(Vehicles3↦46.33837342262268),(Vehicles4↦53.41975688934326),(Vehicles5↦108.13685655593872)}"
      },
      "probabilisticVariables": null,
      "activating": [
        "SLOWER_44"
      ],
      "activatingOnlyWhenExecuted": true,
      "updating": null,
      "withPredicate": null
    },
    {
      "id": "SLOWER_44",
      "execute": "SLOWER",
      "after": "1000",
      "priority": 0,
      "additionalGuards": null,
      "activationKind": null,
      "fixedVariables": {
        "Crash": "FALSE",
        "PresentVehicles": "{EgoVehicle,Vehicles2,Vehicles3,Vehicles4,Vehicles5}",
        "VehiclesAy": "{(EgoVehicle↦0.0),(Vehicles2↦0.0),(Vehicles3↦0.0),(Vehicles4↦0.0),(Vehicles5↦0.0)}",
        "Reward": "0.7333682297140721",
        "VehiclesAx": "{(EgoVehicle↦-0.008628368377685547),(Vehicles2↦0.042593590915203094),(Vehicles3↦0.0419360026717186),(Vehicles4↦-0.009120404720306396),(Vehicles5↦0.036589354276657104)}",
        "VehiclesVx": "{(EgoVehicle↦20.001308917999268),(Vehicles2↦-0.1073990948498249),(Vehicles3↦0.1982313208281994),(Vehicles4↦0.7494668662548065),(Vehicles5↦0.5466212704777718)}",
        "VehiclesY": "{(EgoVehicle↦8.000000238418579),(Vehicles2↦0.0),(Vehicles3↦-4.0000001192092896),(Vehicles4↦-8.000000238418579),(Vehicles5↦-4.0000001192092896)}",
        "VehiclesVy": "{(EgoVehicle↦0.0),(Vehicles2↦0.0),(Vehicles3↦0.0),(Vehicles4↦0.0),(Vehicles5↦0.0)}",
        "VehiclesX": "{(EgoVehicle↦200.0),(Vehicles2↦34.513673186302185),(Vehicles3↦46.512845158576965),(Vehicles4↦54.17599678039551),(Vehicles5↦108.66293907165527)}"
      },
      "probabilisticVariables": null,
      "activating": [
        "SLOWER_45"
      ],
      "activatingOnlyWhenExecuted": true,
      "updating": null,
      "withPredicate": null
    },
    {
      "id": "SLOWER_45",
      "execute": "SLOWER",
      "after": "1000",
      "priority": 0,
      "additionalGuards": null,
      "activationKind": null,
      "fixedVariables": {
        "Crash": "FALSE",
        "PresentVehicles": "{EgoVehicle,Vehicles2,Vehicles3,Vehicles4,Vehicles5}",
        "VehiclesAy": "{(EgoVehicle↦0.0),(Vehicles2↦0.0),(Vehicles3↦0.0),(Vehicles4↦0.0),(Vehicles5↦0.0)}",
        "Reward": "0.7333379287414964",
        "VehiclesAx": "{(EgoVehicle↦-0.0011372566223144531),(Vehicles2↦0.033207801170647144),(Vehicles3↦0.03329215571284294),(Vehicles4↦-0.016494467854499817),(Vehicles5↦0.027837976813316345)}",
        "VehiclesVx": "{(EgoVehicle↦20.000171661376953),(Vehicles2↦-0.07419129367917776),(Vehicles3↦0.23152347654104233),(Vehicles4↦0.7329723984003067),(Vehicles5↦0.5744592472910881)}",
        "VehiclesY": "{(EgoVehicle↦8.000000238418579),(Vehicles2↦0.0),(Vehicles3↦-4.0000001192092896),(Vehicles4↦-8.000000238418579),(Vehicles5↦-4.0000001192092896)}",
        "VehiclesVy": "{(EgoVehicle↦0.0),(Vehicles2↦0.0),(Vehicles3↦0.0),(Vehicles4↦0.0),(Vehicles5↦0.0)}",
        "VehiclesX": "{(EgoVehicle↦200.0),(Vehicles2↦34.41987335681915),(Vehicles3↦46.72465622425079),(Vehicles4↦54.91902828216553),(Vehicles5↦109.22095775604248)}"
      },
      "probabilisticVariables": null,
      "activating": [
        "SLOWER_46"
      ],
      "activatingOnlyWhenExecuted": true,
      "updating": null,
      "withPredicate": null
    },
    {
      "id": "SLOWER_46",
      "execute": "SLOWER",
      "after": "1000",
      "priority": 0,
      "additionalGuards": null,
      "activationKind": null,
      "fixedVariables": {
        "Crash": "FALSE",
        "PresentVehicles": "{EgoVehicle,Vehicles2,Vehicles3,Vehicles4,Vehicles5}",
        "VehiclesAy": "{(EgoVehicle↦0.0),(Vehicles2↦0.0),(Vehicles3↦0.0),(Vehicles4↦0.0),(Vehicles5↦0.0)}",
        "Reward": "0.7333339384899639",
        "VehiclesAx": "{(EgoVehicle↦-0.00014781951904296875),(Vehicles2↦0.030477349646389484),(Vehicles3↦0.031210891902446747),(Vehicles4↦-0.017287731170654297),(Vehicles5↦0.02571098506450653)}",
        "VehiclesVx": "{(EgoVehicle↦20.00002384185791),(Vehicles2↦-0.04371394403278828),(Vehicles3↦0.2627343684434891),(Vehicles4↦0.7156846672296524),(Vehicles5↦0.6001702323555946)}",
        "VehiclesY": "{(EgoVehicle↦8.000000238418579),(Vehicles2↦0.0),(Vehicles3↦-4.0000001192092896),(Vehicles4↦-8.000000238418579),(Vehicles5↦-4.0000001192092896)}",
        "VehiclesVy": "{(EgoVehicle↦0.0),(Vehicles2↦0.0),(Vehicles3↦0.0),(Vehicles4↦0.0),(Vehicles5↦0.0)}",
        "VehiclesX": "{(EgoVehicle↦200.0),(Vehicles2↦34.358030557632446),(Vehicles3↦46.96877300739288),(Vehicles4↦55.64509034156799),(Vehicles5↦109.80581045150757)}"
      },
      "probabilisticVariables": null,
      "activating": [
        "SLOWER_47"
      ],
      "activatingOnlyWhenExecuted": true,
      "updating": null,
      "withPredicate": null
    },
    {
      "id": "SLOWER_47",
      "execute": "SLOWER",
      "after": "1000",
      "priority": 0,
      "additionalGuards": null,
      "activationKind": null,
      "fixedVariables": {
        "Crash": "FALSE",
        "PresentVehicles": "{EgoVehicle,Vehicles2,Vehicles3,Vehicles4,Vehicles5}",
        "VehiclesAy": "{(EgoVehicle↦0.0),(Vehicles2↦0.0),(Vehicles3↦0.0),(Vehicles4↦0.0),(Vehicles5↦0.0)}",
        "Reward": "0.7333334130247415",
        "VehiclesAx": "{(EgoVehicle↦-2.1457672119140625E-05),(Vehicles2↦0.028740687994286418),(Vehicles3↦0.030039753764867783),(Vehicles4↦-0.017172768712043762),(Vehicles5↦0.024535655975341797)}",
        "VehiclesVx": "{(EgoVehicle↦20.00000238418579),(Vehicles2↦-0.014973256038501859),(Vehicles3↦0.29277412220835686),(Vehicles4↦0.6985118985176086),(Vehicles5↦0.6247058883309364)}",
        "VehiclesY": "{(EgoVehicle↦8.000000238418579),(Vehicles2↦0.0),(Vehicles3↦-4.0000001192092896),(Vehicles4↦-8.000000238418579),(Vehicles5↦-4.0000001192092896)}",
        "VehiclesVy": "{(EgoVehicle↦0.0),(Vehicles2↦0.0),(Vehicles3↦0.0),(Vehicles4↦0.0),(Vehicles5↦0.0)}",
        "VehiclesX": "{(EgoVehicle↦200.0),(Vehicles2↦34.325939416885376),(Vehicles3↦47.24360704421997),(Vehicles4↦56.35388493537903),(Vehicles5↦110.4158878326416)}"
      },
      "probabilisticVariables": null,
      "activating": [
        "SLOWER_48"
      ],
      "activatingOnlyWhenExecuted": true,
      "updating": null,
      "withPredicate": null
    },
    {
      "id": "SLOWER_48",
      "execute": "SLOWER",
      "after": "1000",
      "priority": 0,
      "additionalGuards": null,
      "activationKind": null,
      "fixedVariables": {
        "Crash": "FALSE",
        "PresentVehicles": "{EgoVehicle,Vehicles2,Vehicles3,Vehicles4,Vehicles5}",
        "VehiclesAy": "{(EgoVehicle↦0.0),(Vehicles2↦0.0),(Vehicles3↦0.0),(Vehicles4↦0.0),(Vehicles5↦0.0)}",
        "Reward": "0.7333333438276751",
        "VehiclesAx": "{(EgoVehicle↦-2.384185791015625E-06),(Vehicles2↦0.027241185307502747),(Vehicles3↦0.02903113141655922),(Vehicles4↦-0.016906708478927612),(Vehicles5↦0.023552142083644867)}",
        "VehiclesVx": "{(EgoVehicle↦20.0),(Vehicles2↦0.012267929269000888),(Vehicles3↦0.3218052536249161),(Vehicles4↦0.681605190038681),(Vehicles5↦0.6482580304145813)}",
        "VehiclesY": "{(EgoVehicle↦8.000000238418579),(Vehicles2↦0.0),(Vehicles3↦-4.0000001192092896),(Vehicles4↦-8.000000238418579),(Vehicles5↦-4.0000001192092896)}",
        "VehiclesVy": "{(EgoVehicle↦0.0),(Vehicles2↦0.0),(Vehicles3↦0.0),(Vehicles4↦0.0),(Vehicles5↦0.0)}",
        "VehiclesX": "{(EgoVehicle↦200.0),(Vehicles2↦34.32197570800781),(Vehicles3↦47.548070549964905),(Vehicles4↦57.04561471939087),(Vehicles5↦111.05008125305176)}"
      },
      "probabilisticVariables": null,
      "activating": [
        "SLOWER_49"
      ],
      "activatingOnlyWhenExecuted": true,
      "updating": null,
      "withPredicate": null
    },
    {
      "id": "SLOWER_49",
      "execute": "SLOWER",
      "after": "1000",
      "priority": 0,
      "additionalGuards": null,
      "activationKind": null,
      "fixedVariables": {
        "Crash": "FALSE",
        "PresentVehicles": "{EgoVehicle,Vehicles2,Vehicles3,Vehicles4,Vehicles5}",
        "VehiclesAy": "{(EgoVehicle↦0.0),(Vehicles2↦0.0),(Vehicles3↦0.0),(Vehicles4↦0.0),(Vehicles5↦0.0)}",
        "Reward": "0.7333333347153043",
        "VehiclesAx": "{(EgoVehicle↦0.0),(Vehicles2↦0.025868836091831326),(Vehicles3↦0.02808365970849991),(Vehicles4↦-0.01659497618675232),(Vehicles5↦0.022650957107543945)}",
        "VehiclesVx": "{(EgoVehicle↦20.0),(Vehicles2↦0.038136765360832214),(Vehicles3↦0.349888913333416),(Vehicles4↦0.6650102138519287),(Vehicles5↦0.6709089875221252)}",
        "VehiclesY": "{(EgoVehicle↦8.000000238418579),(Vehicles2↦0.0),(Vehicles3↦-4.0000001192092896),(Vehicles4↦-8.000000238418579),(Vehicles5↦-4.0000001192092896)}",
        "VehiclesVy": "{(EgoVehicle↦0.0),(Vehicles2↦0.0),(Vehicles3↦0.0),(Vehicles4↦0.0),(Vehicles5↦0.0)}",
        "VehiclesX": "{(EgoVehicle↦200.0),(Vehicles2↦34.34469699859619),(Vehicles3↦47.88118302822113),(Vehicles4↦57.72055387496948),(Vehicles5↦111.7074728012085)}"
      },
      "probabilisticVariables": null,
      "activating": [
        "SLOWER_50"
      ],
      "activatingOnlyWhenExecuted": true,
      "updating": null,
      "withPredicate": null
    },
    {
      "id": "SLOWER_50",
      "execute": "SLOWER",
      "after": "1000",
      "priority": 0,
      "additionalGuards": null,
      "activationKind": null,
      "fixedVariables": {
        "Crash": "FALSE",
        "PresentVehicles": "{EgoVehicle,Vehicles2,Vehicles3,Vehicles4,Vehicles5}",
        "VehiclesAy": "{(EgoVehicle↦0.0),(Vehicles2↦0.0),(Vehicles3↦0.0),(Vehicles4↦0.0),(Vehicles5↦0.0)}",
        "Reward": "0.7333333335153213",
        "VehiclesAx": "{(EgoVehicle↦0.0),(Vehicles2↦0.024599763564765453),(Vehicles3↦0.027181394398212433),(Vehicles4↦-0.016255080699920654),(Vehicles5↦0.021810755133628845)}",
        "VehiclesVx": "{(EgoVehicle↦20.0),(Vehicles2↦0.06273652892559767),(Vehicles3↦0.3770703077316284),(Vehicles4↦0.6487551331520081),(Vehicles5↦0.6927197426557541)}",
        "VehiclesY": "{(EgoVehicle↦8.000000238418579),(Vehicles2↦0.0),(Vehicles3↦-4.0000001192092896),(Vehicles4↦-8.000000238418579),(Vehicles5↦-4.0000001192092896)}",
        "VehiclesVy": "{(EgoVehicle↦0.0),(Vehicles2↦0.0),(Vehicles3↦0.0),(Vehicles4↦0.0),(Vehicles5↦0.0)}",
        "VehiclesX": "{(EgoVehicle↦200.0),(Vehicles2↦34.39277112483978),(Vehicles3↦48.24201464653015),(Vehicles4↦58.37903618812561),(Vehicles5↦112.38716840744019)}"
      },
      "probabilisticVariables": null,
      "activating": [
        "SLOWER_51"
      ],
      "activatingOnlyWhenExecuted": true,
      "updating": null,
      "withPredicate": null
    },
    {
      "id": "SLOWER_51",
      "execute": "SLOWER",
      "after": "1000",
      "priority": 0,
      "additionalGuards": null,
      "activationKind": null,
      "fixedVariables": {
        "Crash": "FALSE",
        "PresentVehicles": "{EgoVehicle,Vehicles2,Vehicles3,Vehicles4,Vehicles5}",
        "VehiclesAy": "{(EgoVehicle↦0.0),(Vehicles2↦0.0),(Vehicles3↦0.0),(Vehicles4↦0.0),(Vehicles5↦0.0)}",
        "Reward": "0.7333333333572988",
        "VehiclesAx": "{(EgoVehicle↦0.0),(Vehicles2↦0.023422441445291042),(Vehicles3↦0.02632003277540207),(Vehicles4↦-0.015891939401626587),(Vehicles5↦0.021023228764533997)}",
        "VehiclesVx": "{(EgoVehicle↦20.0),(Vehicles2↦0.08615897037088871),(Vehicles3↦0.4033903405070305),(Vehicles4↦0.6328631937503815),(Vehicles5↦0.7137429714202881)}",
        "VehiclesY": "{(EgoVehicle↦8.000000238418579),(Vehicles2↦0.0),(Vehicles3↦-4.0000001192092896),(Vehicles4↦-8.000000238418579),(Vehicles5↦-4.0000001192092896)}",
        "VehiclesVy": "{(EgoVehicle↦0.0),(Vehicles2↦0.0),(Vehicles3↦0.0),(Vehicles4↦0.0),(Vehicles5↦0.0)}",
        "VehiclesX": "{(EgoVehicle↦200.0),(Vehicles2↦34.464967250823975),(Vehicles3↦48.62968027591705),(Vehicles4↦59.02140140533447),(Vehicles5↦113.08835744857788)}"
      },
      "probabilisticVariables": null,
      "activating": [
        "SLOWER_52"
      ],
      "activatingOnlyWhenExecuted": true,
      "updating": null,
      "withPredicate": null
    },
    {
      "id": "SLOWER_52",
      "execute": "SLOWER",
      "after": "1000",
      "priority": 0,
      "additionalGuards": null,
      "activationKind": null,
      "fixedVariables": {
        "Crash": "FALSE",
        "PresentVehicles": "{EgoVehicle,Vehicles2,Vehicles3,Vehicles4,Vehicles5}",
        "VehiclesAy": "{(EgoVehicle↦0.0),(Vehicles2↦0.0),(Vehicles3↦0.0),(Vehicles4↦0.0),(Vehicles5↦0.0)}",
        "Reward": "0.7333333333364892",
        "VehiclesAx": "{(EgoVehicle↦0.0),(Vehicles2↦0.022327899932861328),(Vehicles3↦0.02549700438976288),(Vehicles4↦-0.015507861971855164),(Vehicles5↦0.020283013582229614)}",
        "VehiclesVx": "{(EgoVehicle↦20.0),(Vehicles2↦0.10848687030375004),(Vehicles3↦0.42888734489679337),(Vehicles4↦0.6173553317785263),(Vehicles5↦0.7340259850025177)}",
        "VehiclesY": "{(EgoVehicle↦8.000000238418579),(Vehicles2↦0.0),(Vehicles3↦-4.0000001192092896),(Vehicles4↦-8.000000238418579),(Vehicles5↦-4.0000001192092896)}",
        "VehiclesVy": "{(EgoVehicle↦0.0),(Vehicles2↦0.0),(Vehicles3↦0.0),(Vehicles4↦0.0),(Vehicles5↦0.0)}",
        "VehiclesX": "{(EgoVehicle↦200.0),(Vehicles2↦34.56014394760132),(Vehicles3↦49.043333530426025),(Vehicles4↦59.64803099632263),(Vehicles5↦113.81027698516846)}"
      },
      "probabilisticVariables": null,
      "activating": [
        "SLOWER_53"
      ],
      "activatingOnlyWhenExecuted": true,
      "updating": null,
      "withPredicate": null
    },
    {
      "id": "SLOWER_53",
      "execute": "SLOWER",
      "after": "1000",
      "priority": 0,
      "additionalGuards": null,
      "activationKind": null,
      "fixedVariables": {
        "Crash": "FALSE",
        "PresentVehicles": "{EgoVehicle,Vehicles2,Vehicles3,Vehicles4,Vehicles5}",
        "VehiclesAy": "{(EgoVehicle↦0.0),(Vehicles2↦0.0),(Vehicles3↦0.0),(Vehicles4↦0.0),(Vehicles5↦0.0)}",
        "Reward": "0.733333333333749",
        "VehiclesAx": "{(EgoVehicle↦0.0),(Vehicles2↦0.02130836248397827),(Vehicles3↦0.024710074067115784),(Vehicles4↦-0.015104971826076508),(Vehicles5↦0.019585564732551575)}",
        "VehiclesVx": "{(EgoVehicle↦20.0),(Vehicles2↦0.1297952327877283),(Vehicles3↦0.45359741896390915),(Vehicles4↦0.6022503599524498),(Vehicles5↦0.7536115497350693)}",
        "VehiclesY": "{(EgoVehicle↦8.000000238418579),(Vehicles2↦0.0),(Vehicles3↦-4.0000001192092896),(Vehicles4↦-8.000000238418579),(Vehicles5↦-4.0000001192092896)}",
        "VehiclesVy": "{(EgoVehicle↦0.0),(Vehicles2↦0.0),(Vehicles3↦0.0),(Vehicles4↦0.0),(Vehicles5↦0.0)}",
        "VehiclesX": "{(EgoVehicle↦200.0),(Vehicles2↦34.677231311798096),(Vehicles3↦49.48216676712036),(Vehicles4↦60.25931239128113),(Vehicles5↦114.5521879196167)}"
      },
      "probabilisticVariables": null,
      "activating": [
        "SLOWER_54"
      ],
      "activatingOnlyWhenExecuted": true,
      "updating": null,
      "withPredicate": null
    },
    {
      "id": "SLOWER_54",
      "execute": "SLOWER",
      "after": "1000",
      "priority": 0,
      "additionalGuards": null,
      "activationKind": null,
      "fixedVariables": {
        "Crash": "FALSE",
        "PresentVehicles": "{EgoVehicle,Vehicles2,Vehicles3,Vehicles4,Vehicles5}",
        "VehiclesAy": "{(EgoVehicle↦0.0),(Vehicles2↦0.0),(Vehicles3↦0.0),(Vehicles4↦0.0),(Vehicles5↦0.0)}",
        "Reward": "0.7333333333333881",
        "VehiclesAx": "{(EgoVehicle↦0.0),(Vehicles2↦0.020356979221105576),(Vehicles3↦0.02395741641521454),(Vehicles4↦-0.014685019850730896),(Vehicles5↦0.018927007913589478)}",
        "VehiclesVx": "{(EgoVehicle↦20.0),(Vehicles2↦0.15015221200883389),(Vehicles3↦0.4775548353791237),(Vehicles4↦0.5875653401017189),(Vehicles5↦0.7725385576486588)}",
        "VehiclesY": "{(EgoVehicle↦8.000000238418579),(Vehicles2↦0.0),(Vehicles3↦-4.0000001192092896),(Vehicles4↦-8.000000238418579),(Vehicles5↦-4.0000001192092896)}",
        "VehiclesVy": "{(EgoVehicle↦0.0),(Vehicles2↦0.0),(Vehicles3↦0.0),(Vehicles4↦0.0),(Vehicles5↦0.0)}",
        "VehiclesX": "{(EgoVehicle↦200.0),(Vehicles2↦34.815242886543274),(Vehicles3↦49.94540512561798),(Vehicles4↦60.855650901794434),(Vehicles5↦115.31342267990112)}"
      },
      "probabilisticVariables": null,
      "activating": [
        "SLOWER_55"
      ],
      "activatingOnlyWhenExecuted": true,
      "updating": null,
      "withPredicate": null
    },
    {
      "id": "SLOWER_55",
      "execute": "SLOWER",
      "after": "1000",
      "priority": 0,
      "additionalGuards": null,
      "activationKind": null,
      "fixedVariables": {
        "Crash": "FALSE",
        "PresentVehicles": "{EgoVehicle,Vehicles2,Vehicles3,Vehicles4,Vehicles5}",
        "VehiclesAy": "{(EgoVehicle↦0.0),(Vehicles2↦0.0),(Vehicles3↦0.0),(Vehicles4↦0.0),(Vehicles5↦0.0)}",
        "Reward": "0.7333333333333405",
        "VehiclesAx": "{(EgoVehicle↦0.0),(Vehicles2↦0.019467668607831),(Vehicles3↦0.023237206041812897),(Vehicles4↦-0.014249719679355621),(Vehicles5↦0.018304362893104553)}",
        "VehiclesVx": "{(EgoVehicle↦20.0),(Vehicles2↦0.1696198806166649),(Vehicles3↦0.5007920414209366),(Vehicles4↦0.5733156204223633),(Vehicles5↦0.7908429205417633)}",
        "VehiclesY": "{(EgoVehicle↦8.000000238418579),(Vehicles2↦0.0),(Vehicles3↦-4.0000001192092896),(Vehicles4↦-8.000000238418579),(Vehicles5↦-4.0000001192092896)}",
        "VehiclesVy": "{(EgoVehicle↦0.0),(Vehicles2↦0.0),(Vehicles3↦0.0),(Vehicles4↦0.0),(Vehicles5↦0.0)}",
        "VehiclesX": "{(EgoVehicle↦200.0),(Vehicles2↦34.973251819610596),(Vehicles3↦50.43231248855591),(Vehicles4↦61.43748164176941),(Vehicles5↦116.09333753585815)}"
      },
      "probabilisticVariables": null,
      "activating": [
        "SLOWER_56"
      ],
      "activatingOnlyWhenExecuted": true,
      "updating": null,
      "withPredicate": null
    },
    {
      "id": "SLOWER_56",
      "execute": "SLOWER",
      "after": "1000",
      "priority": 0,
      "additionalGuards": null,
      "activationKind": null,
      "fixedVariables": {
        "Crash": "FALSE",
        "PresentVehicles": "{EgoVehicle,Vehicles2,Vehicles3,Vehicles4,Vehicles5}",
        "VehiclesAy": "{(EgoVehicle↦0.0),(Vehicles2↦0.0),(Vehicles3↦0.0),(Vehicles4↦0.0),(Vehicles5↦0.0)}",
        "Reward": "0.7333333333333343",
        "VehiclesAx": "{(EgoVehicle↦0.0),(Vehicles2↦0.018635019659996033),(Vehicles3↦0.022547729313373566),(Vehicles4↦-0.013800635933876038),(Vehicles5↦0.017714649438858032)}",
        "VehiclesVx": "{(EgoVehicle↦20.0),(Vehicles2↦0.18825490027666092),(Vehicles3↦0.5233397707343102),(Vehicles4↦0.5595149844884872),(Vehicles5↦0.8085575699806213)}",
        "VehiclesY": "{(EgoVehicle↦8.000000238418579),(Vehicles2↦0.0),(Vehicles3↦-4.0000001192092896),(Vehicles4↦-8.000000238418579),(Vehicles5↦-4.0000001192092896)}",
        "VehiclesVy": "{(EgoVehicle↦0.0),(Vehicles2↦0.0),(Vehicles3↦0.0),(Vehicles4↦0.0),(Vehicles5↦0.0)}",
        "VehiclesX": "{(EgoVehicle↦200.0),(Vehicles2↦35.15039086341858),(Vehicles3↦50.94217658042908),(Vehicles4↦62.005239725112915),(Vehicles5↦116.89131259918213)}"
      },
      "probabilisticVariables": null,
      "activating": [
        "SLOWER_57"
      ],
      "activatingOnlyWhenExecuted": true,
      "updating": null,
      "withPredicate": null
    },
    {
      "id": "SLOWER_57",
      "execute": "SLOWER",
      "after": "1000",
      "priority": 0,
      "additionalGuards": null,
      "activationKind": null,
      "fixedVariables": {
        "Crash": "FALSE",
        "PresentVehicles": "{EgoVehicle,Vehicles2,Vehicles3,Vehicles4,Vehicles5}",
        "VehiclesAy": "{(EgoVehicle↦0.0),(Vehicles2↦0.0),(Vehicles3↦0.0),(Vehicles4↦0.0),(Vehicles5↦0.0)}",
        "Reward": "0.7333333333333334",
        "VehiclesAx": "{(EgoVehicle↦0.0),(Vehicles2↦0.017854217439889908),(Vehicles3↦0.02188749611377716),(Vehicles4↦-0.013339631259441376),(Vehicles5↦0.01715525984764099)}",
        "VehiclesVx": "{(EgoVehicle↦20.0),(Vehicles2↦0.20610911771655083),(Vehicles3↦0.5452272668480873),(Vehicles4↦0.5461753532290459),(Vehicles5↦0.8257128298282623)}",
        "VehiclesY": "{(EgoVehicle↦8.000000238418579),(Vehicles2↦0.0),(Vehicles3↦-4.0000001192092896),(Vehicles4↦-8.000000238418579),(Vehicles5↦-4.0000001192092896)}",
        "VehiclesVy": "{(EgoVehicle↦0.0),(Vehicles2↦0.0),(Vehicles3↦0.0),(Vehicles4↦0.0),(Vehicles5↦0.0)}",
        "VehiclesX": "{(EgoVehicle↦200.0),(Vehicles2↦35.34584641456604),(Vehicles3↦51.474326848983765),(Vehicles4↦62.55938410758972),(Vehicles5↦117.7067756652832)}"
      },
      "probabilisticVariables": null,
      "activating": [
        "IDLE_58"
      ],
      "activatingOnlyWhenExecuted": true,
      "updating": null,
      "withPredicate": null
    },
    {
      "id": "IDLE_58",
      "execute": "IDLE",
      "after": "1000",
      "priority": 0,
      "additionalGuards": null,
      "activationKind": null,
      "fixedVariables": {
        "Crash": "FALSE",
        "PresentVehicles": "{EgoVehicle,Vehicles2,Vehicles3,Vehicles4,Vehicles5}",
        "VehiclesAy": "{(EgoVehicle↦0.0),(Vehicles2↦0.0),(Vehicles3↦0.0),(Vehicles4↦0.0),(Vehicles5↦0.0)}",
        "Reward": "0.7333333333333334",
        "VehiclesAx": "{(EgoVehicle↦0.0),(Vehicles2↦0.017121005803346634),(Vehicles3↦0.021254941821098328),(Vehicles4↦-0.01286827027797699),(Vehicles5↦0.01662418246269226)}",
        "VehiclesVx": "{(EgoVehicle↦20.0),(Vehicles2↦0.22323012351989746),(Vehicles3↦0.5664822086691856),(Vehicles4↦0.5333070829510689),(Vehicles5↦0.8423370122909546)}",
        "VehiclesY": "{(EgoVehicle↦8.000000238418579),(Vehicles2↦0.0),(Vehicles3↦-4.0000001192092896),(Vehicles4↦-8.000000238418579),(Vehicles5↦-4.0000001192092896)}",
        "VehiclesVy": "{(EgoVehicle↦0.0),(Vehicles2↦0.0),(Vehicles3↦0.0),(Vehicles4↦0.0),(Vehicles5↦0.0)}",
        "VehiclesX": "{(EgoVehicle↦200.0),(Vehicles2↦35.55886149406433),(Vehicles3↦52.028101682662964),(Vehicles4↦63.1003737449646),(Vehicles5↦118.53917837142944)}"
      },
      "probabilisticVariables": null,
      "activating": [
        "SLOWER_59"
      ],
      "activatingOnlyWhenExecuted": true,
      "updating": null,
      "withPredicate": null
    },
    {
      "id": "SLOWER_59",
      "execute": "SLOWER",
      "after": "1000",
      "priority": 0,
      "additionalGuards": null,
      "activationKind": null,
      "fixedVariables": {
        "Crash": "FALSE",
        "PresentVehicles": "{EgoVehicle,Vehicles2,Vehicles3,Vehicles4,Vehicles5}",
        "VehiclesAy": "{(EgoVehicle↦0.0),(Vehicles2↦0.0),(Vehicles3↦0.0),(Vehicles4↦0.0),(Vehicles5↦0.0)}",
        "Reward": "0.7333333333333334",
        "VehiclesAx": "{(EgoVehicle↦0.0),(Vehicles2↦0.016431473195552826),(Vehicles3↦0.02064872533082962),(Vehicles4↦-0.012388266623020172),(Vehicles5↦0.016119107604026794)}",
        "VehiclesVx": "{(EgoVehicle↦20.0),(Vehicles2↦0.2396615967154503),(Vehicles3↦0.5871309340000153),(Vehicles4↦0.5209188163280487),(Vehicles5↦0.8584561198949814)}",
        "VehiclesY": "{(EgoVehicle↦8.000000238418579),(Vehicles2↦0.0),(Vehicles3↦-4.0000001192092896),(Vehicles4↦-8.000000238418579),(Vehicles5↦-4.0000001192092896)}",
        "VehiclesVy": "{(EgoVehicle↦0.0),(Vehicles2↦0.0),(Vehicles3↦0.0),(Vehicles4↦0.0),(Vehicles5↦0.0)}",
        "VehiclesX": "{(EgoVehicle↦200.0),(Vehicles2↦35.78871786594391),(Vehicles3↦52.602893114089966),(Vehicles4↦63.62868547439575),(Vehicles5↦119.38799619674683)}"
      },
      "probabilisticVariables": null,
      "activating": [
        "SLOWER_60"
      ],
      "activatingOnlyWhenExecuted": true,
      "updating": null,
      "withPredicate": null
    },
    {
      "id": "SLOWER_60",
      "execute": "SLOWER",
      "after": "1000",
      "priority": 0,
      "additionalGuards": null,
      "activationKind": null,
      "fixedVariables": {
        "Crash": "FALSE",
        "PresentVehicles": "{EgoVehicle,Vehicles2,Vehicles3,Vehicles4,Vehicles5}",
        "VehiclesAy": "{(EgoVehicle↦0.0),(Vehicles2↦0.0),(Vehicles3↦0.0),(Vehicles4↦0.0),(Vehicles5↦0.0)}",
        "Reward": "0.7333333333333334",
        "VehiclesAx": "{(EgoVehicle↦0.0),(Vehicles2↦0.12344144284725189),(Vehicles3↦-0.3316871449351311),(Vehicles4↦0.08627954870462418),(Vehicles5↦-0.3494386374950409)}",
        "VehiclesVx": "{(EgoVehicle↦20.0),(Vehicles2↦0.3631030395627022),(Vehicles3↦0.2554437890648842),(Vehicles4↦0.6071983650326729),(Vehicles5↦0.5090174823999405)}",
        "VehiclesY": "{(EgoVehicle↦8.000000238418579),(Vehicles2↦-4.0000001192092896),(Vehicles3↦0.0),(Vehicles4↦-4.0000001192092896),(Vehicles5↦-8.000000238418579)}",
        "VehiclesVy": "{(EgoVehicle↦0.0),(Vehicles2↦0.0),(Vehicles3↦0.0),(Vehicles4↦0.0),(Vehicles5↦0.0)}",
        "VehiclesX": "{(EgoVehicle↦200.0),(Vehicles2↦-9.918969869613647),(Vehicles3↦36.03474199771881),(Vehicles4↦53.19809317588806),(Vehicles5↦64.14480805397034)}"
      },
      "probabilisticVariables": null,
      "activating": [
        "FASTER_61"
      ],
      "activatingOnlyWhenExecuted": true,
      "updating": null,
      "withPredicate": null
    },
    {
      "id": "FASTER_61",
      "execute": "FASTER",
      "after": "1000",
      "priority": 0,
      "additionalGuards": null,
      "activationKind": null,
      "fixedVariables": {
        "Crash": "FALSE",
        "PresentVehicles": "{EgoVehicle,Vehicles2,Vehicles3,Vehicles4,Vehicles5}",
        "VehiclesAy": "{(EgoVehicle↦0.0),(Vehicles2↦0.0),(Vehicles3↦0.0),(Vehicles4↦0.0),(Vehicles5↦0.0)}",
        "Reward": "0.8491083676268861",
        "VehiclesAx": "{(EgoVehicle↦4.341564178466797),(Vehicles2↦-4.434052892029285),(Vehicles3↦-3.9702994003891945),(Vehicles4↦-4.451153762638569),(Vehicles5↦-3.9613068848848343)}",
        "VehiclesVx": "{(EgoVehicle↦24.341564178466797),(Vehicles2↦-4.070949852466583),(Vehicles3↦-3.7148556113243103),(Vehicles4↦-3.843955397605896),(Vehicles5↦-3.452289402484894)}",
        "VehiclesY": "{(EgoVehicle↦8.000000238418579),(Vehicles2↦0.0),(Vehicles3↦-4.0000001192092896),(Vehicles4↦-8.000000238418579),(Vehicles5↦-4.0000001192092896)}",
        "VehiclesVy": "{(EgoVehicle↦0.0),(Vehicles2↦0.0),(Vehicles3↦0.0),(Vehicles4↦0.0),(Vehicles5↦0.0)}",
        "VehiclesX": "{(EgoVehicle↦200.0),(Vehicles2↦33.901241421699524),(Vehicles3↦51.41807794570923),(Vehicles4↦62.2541606426239),(Vehicles5↦118.73788833618164)}"
      },
      "probabilisticVariables": null,
      "activating": null,
      "activatingOnlyWhenExecuted": true,
      "updating": null,
      "withPredicate": null
    }
  ],
  "listeners": [],
  "metadata": {
    "fileType": "Timed_Trace",
    "formatVersion": 3,
    "savedAt": "2023-11-29T12:29:10.508422Z",
    "creator": "Simulation: MONTE_CARLO_SIMULATION; MAX_STEPS_BEFORE_PROPERTY : 0, EXECUTIONS : 1000, ENDING_TIME : 60000",
    "proB2KernelVersion": "4.12.3-SNAPSHOT",
    "proBCliVersion": "1.12.3-nightly",
    "modelName": "HighwayEnvironment"
  }
}